Workbook

Sheet Cover
A1: MICROSOFT CORPORATION (NASDAQ: MSFT)
A2: Independent Equity Research & Valuation Model
A3: Valuation reference date: October 27, 2026
A5: MODEL OVERVIEW | E5: MODEL SCOPE
A6: Company | B6: Microsoft Corporation (NASDAQ: MSFT) | E6: Integrated financial statements
A7: Author | B7: Eden Kabanga | E7: Bear / Base / Bull scenarios
A8: Research period | B8: FY2022–FY2026 historical analysis | E8: DCF and valuation sensitivities
A9: Projection period | B9: FY2027–FY2031 explicit projections; FY2032–FY2036 DCF normalization | E9: Historical peer P/E cross-check
A10: Research focus | B10: Can Microsoft's AI investment generate sufficient returns to justify current capital intensity? | E10: WACC, beta and supporting market data
A12: NAVIGATION | E12: MODEL CONVENTIONS
A13: Dashboard | B13: =HYPERLINK("#'Dashboard'!A1","Open") -> Open | E13: Blue font | F13: Hardcoded inputs
A14: Financial Statements | B14: =HYPERLINK("#'Fin Statement'!A1","Open") -> Open | E14: Green font | F14: Cross-sheet formulas
A15: Common Size & Ratios | B15: =HYPERLINK("#'Common Size&Ratio'!A1","Open") -> Open | E15: Black font | F15: Same-sheet formulas / calculations
A16: Trend Analysis | B16: =HYPERLINK("#'Trend Analysis'!A1","Open") -> Open | E16: Red font | F16: External workbook links, if any
A17: Assumptions | B17: =HYPERLINK("#'Assumptions'!A1","Open") -> Open | E17: Units | F17: USD millions unless noted
A18: Three-Statement Model | B18: =HYPERLINK("#'3 statement Model'!A1","Open") -> Open | E18: Per-share values | F18: US dollars per diluted share
A19: DCF | B19: =HYPERLINK("#'DCF'!A1","Open") -> Open | E19: Historical periods | F19: FY2022–FY2026 actuals
A20: Valuation Sensitivities | B20: =HYPERLINK("#'Valuation Sensitivities'!A1","Open") -> Open | E20: Forecast periods | F20: FY2027–FY2031 estimates
A21: Trading Comps | B21: =HYPERLINK("#'Trading Comps'!A1","Open") -> Open | E21: Scenario selector | F21: Assumptions!L2; scenario name in Assumptions!M2
A22: WACC | B22: =HYPERLINK("#'WACC'!A1","Open") -> Open
A23: Beta / Supporting Market Data | B23: =HYPERLINK("#'Beta'!A1","Open") -> Open
A24: Sources & Definitions | B24: =HYPERLINK("#'Sources & Definitions'!A1","Open") -> Open
A27: MODEL STATUS & VALUATION REFERENCES | E27: PRINCIPAL SOURCES
A28: Active scenario | B28: =Assumptions!M2 -> Base | E28: Microsoft FY2026 Form 10-K | F28: Historical financial statements, leases, segments and disclosures
A29: Reference share price | B29: =DCF!E13 -> 531.33 | E29: Microsoft earnings materials | F29: Operating context and public company disclosures
A30: Active DCF value / share | B30: =DCF!E55 -> 403.26434 | E30: U.S. Treasury yield curve | F30: Risk-free rate; observation dated October 23, 2026
A31: WACC | B31: =DCF!E6 -> 0.090535584 | E31: Damodaran equity risk premium | F31: Market risk premium; observation dated October 1, 2026
A32: Terminal growth (active scenario) | B32: =DCF!E7 -> 0.025 | E32: MSFT market price / historical prices | F32: $531.33 close on October 27, 2026; Excel STOCKHISTORY for historical observations
A33: Terminal incremental ROIC (active scenario) | B33: =DCF!E9 -> 0.15 | E33: Peer company filings and dated market capitalizations | F33: Alphabet, Amazon, Oracle and Salesforce; conventions documented in Trading Comps
A34: Terminal value / enterprise value | B34: =DCF!E47 -> 0.69667511
A37: IMPORTANT DEFINITIONS
A38: Cash FCF | B38: Operating cash flow less cash additions to PP&E
A39: Economic UFCF | B39: Unlevered operating cash flow after economic reinvestment, including modeled lease-financed asset additions
A40: Net cash | B40: Cash plus short-term investments less conventional interest-bearing debt
A41: ROIC / incremental ROIC | B41: Consolidated return diagnostics; not direct measurements of AI-specific project returns
A44: DISCLAIMER
A45: This workbook contains independent financial research based on public information and explicitly stated analyst assumptions. Forecasts and valuations involve uncertainty. The material is not personalized investment advice or a recommendation to buy or sell securities.

Sheet Dashboard
A1: MICROSOFT CORPORATION — EQUITY RESEARCH DASHBOARD | M1: =HYPERLINK("#'Cover'!A1","Back to Cover") -> Back to Cover | P1: Year | Q1: Revenue ($bn) | R1: Operating income ($bn) | T1: Year | U1: Cash CapEx / revenue | V1: Economic investment / revenue | X1: Year | Y1: CFO ($bn) | Z1: Cash CapEx ($bn) | AA1: Cash FCF ($bn) | AC1: Valuation reference | AD1: Value / share
A2: NASDAQ: MSFT | Independent valuation and capital-productivity analysis | P2: ='Fin Statement'!E5 -> 2022A | Q2: ='3 statement Model'!E9/1000 -> 198.27 | R2: ='3 statement Model'!E25/1000 -> 83.383 | T2: ='Fin Statement'!E5 -> 2022A | U2: ='Common Size&Ratio'!E171 -> 0.12047208 | X2: ='Fin Statement'!E5 -> 2022A | Y2: ='3 statement Model'!E68/1000 -> 89.035 | Z2: =ABS('3 statement Model'!E76)/1000 -> 23.886 | AA2: ='Common Size&Ratio'!E168/1000 -> 65.149 | AC2: Market | AD2: =$B$9 -> 531.33
A3: Research question: Can Microsoft's AI investment generate sufficient returns to justify current capital intensity? | P3: ='Fin Statement'!F5 -> 2023A | Q3: ='3 statement Model'!F9/1000 -> 211.915 | R3: ='3 statement Model'!F25/1000 -> 88.523 | T3: ='Fin Statement'!F5 -> 2023A | U3: ='Common Size&Ratio'!F171 -> 0.13263337 | X3: ='Fin Statement'!F5 -> 2023A | Y3: ='3 statement Model'!F68/1000 -> 87.582 | Z3: =ABS('3 statement Model'!F76)/1000 -> 28.107 | AA3: ='Common Size&Ratio'!F168/1000 -> 59.475 | AC3: Bear DCF | AD3: 300.21849
P4: ='Fin Statement'!G5 -> 2024A | Q4: ='3 statement Model'!G9/1000 -> 245.122 | R4: ='3 statement Model'!G25/1000 -> 109.433 | T4: ='Fin Statement'!G5 -> 2024A | U4: ='Common Size&Ratio'!G171 -> 0.18144842 | X4: ='Fin Statement'!G5 -> 2024A | Y4: ='3 statement Model'!G68/1000 -> 118.548 | Z4: =ABS('3 statement Model'!G76)/1000 -> 44.477 | AA4: ='Common Size&Ratio'!G168/1000 -> 74.071 | AC4: Base DCF | AD4: 403.26434
A5: INVESTMENT OVERVIEW | P5: ='Fin Statement'!H5 -> 2025A | Q5: ='3 statement Model'!H9/1000 -> 281.724 | R5: ='3 statement Model'!H25/1000 -> 128.528 | T5: ='Fin Statement'!H5 -> 2025A | U5: ='Common Size&Ratio'!H171 -> 0.22912851 | X5: ='Fin Statement'!H5 -> 2025A | Y5: ='3 statement Model'!H68/1000 -> 136.162 | Z5: =ABS('3 statement Model'!H76)/1000 -> 64.551 | AA5: ='Common Size&Ratio'!H168/1000 -> 71.611 | AC5: Bull DCF | AD5: 500.32106
A6: Valuation reference date | B6: 46322 | D6: Research judgment | E6: Valuation-cautious / Unrated | H6: Active scenario | I6: =Assumptions!M2 -> Base | K6: Scenario selector | L6: =Assumptions!L2 -> 2 | P6: ='Fin Statement'!I5 -> 2026A | Q6: ='3 statement Model'!I9/1000 -> 331.839 | R6: ='3 statement Model'!I25/1000 -> 155.237 | T6: ='Fin Statement'!I5 -> 2026A | U6: ='Common Size&Ratio'!I171 -> 0.34941041 | X6: ='Fin Statement'!I5 -> 2026A | Y6: ='3 statement Model'!I68/1000 -> 182.935 | Z6: =ABS('3 statement Model'!I76)/1000 -> 115.948 | AA6: ='Common Size&Ratio'!I168/1000 -> 66.987 | AC6: Peer P/E | AD6: =$B$17 -> 506.60636
P7: ='Fin Statement'!J5 -> 2027E | Q7: ='3 statement Model'!J9/1000 -> 390.02904 | R7: ='3 statement Model'!J25/1000 -> 180.97347 | T7: ='Fin Statement'!J5 -> 2027E | U7: ='Common Size&Ratio'!J171 -> 0.35894763 | V7: ='Common Size&Ratio'!J205 -> 0.39740631 | X7: ='Fin Statement'!J5 -> 2027E | Y7: ='3 statement Model'!J68/1000 -> 222.14056 | Z7: =ABS('3 statement Model'!J76)/1000 -> 140 | AA7: ='Common Size&Ratio'!J168/1000 -> 82.140565
A8: VALUATION SUMMARY | P8: ='Fin Statement'!K5 -> 2028E | Q8: ='3 statement Model'!K9/1000 -> 460.28555 | R8: ='3 statement Model'!K25/1000 -> 214.49307 | T8: ='Fin Statement'!K5 -> 2028E | U8: ='Common Size&Ratio'!K171 -> 0.33674748 | V8: ='Common Size&Ratio'!K205 -> 0.36933595 | X8: ='Fin Statement'!K5 -> 2028E | Y8: ='3 statement Model'!K68/1000 -> 267.1957 | Z8: =ABS('3 statement Model'!K76)/1000 -> 155 | AA8: ='Common Size&Ratio'!K168/1000 -> 112.1957
A9: Reference share price | B9: =DCF!E13 -> 531.33 | D9: DATED, INDEPENDENTLY RECONCILED SCENARIO SNAPSHOTS | P9: ='Fin Statement'!L5 -> 2029E | Q9: ='3 statement Model'!L9/1000 -> 536.51482 | R9: ='3 statement Model'!L25/1000 -> 252.69848 | T9: ='Fin Statement'!L5 -> 2029E | U9: ='Common Size&Ratio'!L171 -> 0.31685984 | V9: ='Common Size&Ratio'!L205 -> 0.34481806 | X9: ='Fin Statement'!L5 -> 2029E | Y9: ='3 statement Model'!L68/1000 -> 317.1445 | Z9: =ABS('3 statement Model'!L76)/1000 -> 170 | AA9: ='Common Size&Ratio'!L168/1000 -> 147.1445
A10: Active-scenario DCF value | B10: =DCF!E55 -> 403.26434 | D10: Scenario | E10: DCF / share | F10: Upside / (downside) | P10: ='Fin Statement'!M5 -> 2030E | Q10: ='3 statement Model'!M9/1000 -> 618.2188 | R10: ='3 statement Model'!M25/1000 -> 293.65393 | T10: ='Fin Statement'!M5 -> 2030E | U10: ='Common Size&Ratio'!M171 -> 0.2992468 | V10: ='Common Size&Ratio'!M205 -> 0.32351006 | X10: ='Fin Statement'!M5 -> 2030E | Y10: ='3 statement Model'!M68/1000 -> 367.24669 | Z10: =ABS('3 statement Model'!M76)/1000 -> 185 | AA10: ='Common Size&Ratio'!M168/1000 -> 182.24669
A11: Active upside / (downside) | B11: =DCF!E57 -> -0.24102847 | D11: Bear | E11: 300.21849 | F11: =E11/$B$9-1 -> -0.43496793 | P11: ='Fin Statement'!N5 -> 2031E | Q11: ='3 statement Model'!N9/1000 -> 702.02722 | R11: ='3 statement Model'!N25/1000 -> 337.67509 | T11: ='Fin Statement'!N5 -> 2031E | U11: ='Common Size&Ratio'!N171 -> 0.28488924 | V11: ='Common Size&Ratio'!N205 -> 0.30625593 | X11: ='Fin Statement'!N5 -> 2031E | Y11: ='3 statement Model'!N68/1000 -> 423.39655 | Z11: =ABS('3 statement Model'!N76)/1000 -> 200 | AA11: ='Common Size&Ratio'!N168/1000 -> 223.39655
A12: WACC | B12: =DCF!E6 -> 0.090535584 | D12: Base | E12: 403.26434 | F12: =E12/$B$9-1 -> -0.24102847
A13: Terminal growth | B13: =DCF!E7 -> 0.025 | D13: Bull | E13: 500.32106 | F13: =E13/$B$9-1 -> -0.058360974
A14: Terminal incremental ROIC | B14: =DCF!E9 -> 0.15
A15: Terminal value / enterprise value | B15: =DCF!E47 -> 0.69667511 | D15: Snapshot basis | E15: Hardcoded scenario values are dated, independently reconciled snapshots.
A16: Peer P/E median | B16: ='Trading Comps'!P14 -> 28.126049 | D16: Snapshot date | E16: 46324
A17: Indicative peer P/E value | B17: ='Trading Comps'!F21 -> 506.60636 | D17: Method note | E17: Active DCF remains live-linked to the scenario selector.
A19: ="FINANCIAL PERFORMANCE — FY2026 ACTUAL VS FY2031 ACTIVE SCENARIO ("&UPPER(Assumptions!M2)&")" -> FINANCIAL PERFORMANCE — FY2026 ACTUAL VS FY2031 ACTIVE SCENARIO (BASE)
A20: Metric | B20: FY2026A | C20: ="FY2031E ("&Assumptions!M2&")" -> FY2031E (Base) | D20: Definition / unit
A21: Revenue | B21: ='3 statement Model'!I9 -> 331839 | C21: ='3 statement Model'!N9 -> 702027.22 | D21: USD millions
A22: Operating income | B22: ='3 statement Model'!I25 -> 155237 | C22: ='3 statement Model'!N25 -> 337675.09 | D22: USD millions
A23: Operating margin | B23: ='Common Size&Ratio'!I139 -> 0.46780818 | C23: ='Common Size&Ratio'!N139 -> 0.481 | D23: % of revenue
A24: Operating cash flow | B24: ='3 statement Model'!I68 -> 182935 | C24: ='3 statement Model'!N68 -> 423396.55 | D24: USD millions
A25: Cash CapEx | B25: =ABS('3 statement Model'!I76) -> 115948 | C25: =ABS('3 statement Model'!N76) -> 200000 | D25: Cash additions to PP&E; USD millions
A26: Economic CapEx | B26: n/a* | C26: ='3 statement Model'!N174+'3 statement Model'!N175 -> 215000 | D26: Cash PP&E + modeled lease-financed additions
A27: Cash FCF | B27: ='Common Size&Ratio'!I168 -> 66987 | C27: ='Common Size&Ratio'!N168 -> 223396.55 | D27: CFO less cash additions to PP&E
A28: Economic UFCF | B28: n/a* | C28: =DCF!I27 -> 181368.64 | D28: Unlevered cash flow after economic reinvestment
A29: Consolidated ROIC | B29: ='Common Size&Ratio'!I144 -> 0.3585794 | C29: ='Common Size&Ratio'!N144 -> 0.34983704 | D29: NOPAT / average invested capital
A30: Cash CapEx / revenue | B30: ='Common Size&Ratio'!I171 -> 0.34941041 | C30: ='Common Size&Ratio'!N171 -> 0.28488924 | D30: Cash additions to PP&E / revenue
A31: Economic investment / revenue | B31: n/a* | C31: ='Common Size&Ratio'!N205 -> 0.30625593 | D31: Forecast economic investment / revenue
A32: * Comparable historical lease additions and economic UFCF are unavailable; no unsupported FY2026 figure is inferred.
A34: MODEL STATUS — LIVE FORMULA CHECKS
A35: Balance sheet | B35: =IF(MAX(ABS('3 statement Model'!J127),ABS('3 statement Model'!K127),ABS('3 statement Model'!L127),ABS('3 statement Model'!M127),ABS('3 statement Model'!N127))<0.1,"PASS","FAIL") -> PASS | D35: Cash-flow / balance-sheet cash | E35: =IF(MAX(ABS('3 statement Model'!J84-'3 statement Model'!J91),ABS('3 statement Model'!K84-'3 statement Model'!K91),ABS('3 statement Model'!L84-'3 statement Model'!L91),ABS('3 statement Model'!M84-'3 statement Model'!M91),ABS('3 statement Model'!N84-'3 statement Model'!N91))<0.1,"PASS","FAIL") -> PASS | G35: PP&E roll-forward | H35: =IF(MAX(ABS('3 statement Model'!J185),ABS('3 statement Model'!K185),ABS('3 statement Model'!L185),ABS('3 statement Model'!M185),ABS('3 statement Model'!N185))<0.1,"PASS","FAIL") -> PASS | J35: Lease consistency | K35: =IF(MAX(ABS('3 statement Model'!J99-'3 statement Model'!J297),ABS('3 statement Model'!K99-'3 statement Model'!K297),ABS('3 statement Model'!L99-'3 statement Model'!L297),ABS('3 statement Model'!M99-'3 statement Model'!M297),ABS('3 statement Model'!N99-'3 statement Model'!N297),ABS('3 statement Model'!J117-'3 statement Model'!J301),ABS('3 statement Model'!K117-'3 statement Model'!K301),ABS('3 statement Model'!L117-'3 statement Model'!L301),ABS('3 statement Model'!M117-'3 statement Model'!M301),ABS('3 statement Model'!N117-'3 statement Model'!N301),ABS('3 statement Model'!J175-'3 statement Model'!J286),ABS('3 statement Model'!K175-'3 statement Model'!K286),ABS('3 statement Model'!L175-'3 statement Model'!L286),ABS('3 statement Model'!M175-'3 statement Model'!M286),ABS('3 statement Model'!N175-'3 statement Model'!N286),ABS('3 statement Model'!J73+'3 statement Model'!J292),ABS('3 statement Model'!K73+'3 statement Model'!K292),ABS('3 statement Model'!L73+'3 statement Model'!L292),ABS('3 statement Model'!M73+'3 statement Model'!M292),ABS('3 statement Model'!N73+'3 statement Model'!N292))<0.1,"PASS","FAIL") -> PASS | M35: Scenario / model | N35: ="ACTIVE: "&UPPER(Assumptions!M2)&" | CHECKS: "&IF(AND(B35="PASS",E35="PASS",H35="PASS",K35="PASS"),"PASS","REVIEW") -> ACTIVE: BASE | CHECKS: PASS
A37: INVESTMENT RISKS & INTERPRETIVE LIMITATIONS
A38: Utilization and monetization | B38: Returns depend on sustained demand, deployment utilization and monetization of the expanding AI infrastructure base.
A39: Margin sustainability | B39: High consolidated margins may not fully capture mix, pricing and depreciation pressure from accelerated infrastructure investment.
A40: Infrastructure replacement | B40: Short technology cycles may require replacement investment before modeled economic lives are exhausted.
A41: Capital intensity | B41: Cash CapEx remains elevated; FY2031 economic investment includes modeled finance-lease-financed asset additions.
A42: Terminal productivity | B42: Valuation is sensitive to terminal incremental ROIC and the large terminal-value contribution to enterprise value.
A43: AI-return limitation | B43: Company-wide ROIC and incremental ROIC are consolidated diagnostics, not direct measurements of AI-specific project returns.

Sheet Fin Statement
B1: Historical Financial Analysis: MSFT | N1: =HYPERLINK("#'Cover'!A1","Cover") -> Cover
F2: Year Ended June 30
B4: Income Statement | E4: Historical | I4: Forecasted
B5: (In millions, except per share amounts) | E5: =(2021+COLUMN()-COLUMN($D$5))&IF(COLUMN()-COLUMN($D$5)<5,"A","E") -> 2022A | F5: =(2021+COLUMN()-COLUMN($D$5))&IF(COLUMN()-COLUMN($D$5)<5,"A","E") -> 2023A | G5: =(2021+COLUMN()-COLUMN($D$5))&IF(COLUMN()-COLUMN($D$5)<5,"A","E") -> 2024A | H5: =(2021+COLUMN()-COLUMN($D$5))&IF(COLUMN()-COLUMN($D$5)<5,"A","E") -> 2025A | I5: 2026A | J5: =(2021+COLUMN()-COLUMN($D$5))&IF(COLUMN()-COLUMN($D$5)<5,"A","E") -> 2027E | K5: =(2021+COLUMN()-COLUMN($D$5))&IF(COLUMN()-COLUMN($D$5)<5,"A","E") -> 2028E | L5: =(2021+COLUMN()-COLUMN($D$5))&IF(COLUMN()-COLUMN($D$5)<5,"A","E") -> 2029E | M5: =(2021+COLUMN()-COLUMN($D$5))&IF(COLUMN()-COLUMN($D$5)<5,"A","E") -> 2030E | N5: =(2021+COLUMN()-COLUMN($D$5))&IF(COLUMN()-COLUMN($D$5)<5,"A","E") -> 2031E
B6: Revenue:
B7: Product | E7: 72732 | F7: 64699 | G7: 64773 | H7: 63946 | I7: 64696 | J7: ='3 statement Model'!J7 -> 65989.92 | K7: ='3 statement Model'!K7 -> 67309.718 | L7: ='3 statement Model'!L7 -> 68655.913 | M7: ='3 statement Model'!M7 -> 70029.031 | N7: ='3 statement Model'!N7 -> 71429.612
B8: Service and other | E8: 125538 | F8: 147216 | G8: 180349 | H8: 217778 | I8: 267143 | J8: ='3 statement Model'!J8 -> 324039.12 | K8: ='3 statement Model'!K8 -> 392975.83 | L8: ='3 statement Model'!L8 -> 467858.9 | M8: ='3 statement Model'!M8 -> 548189.77 | N8: ='3 statement Model'!N8 -> 630597.61
B9: Total revenue | E9: =SUM(E7:E8) -> 198270 | F9: =SUM(F7:F8) -> 211915 | G9: =SUM(G7:G8) -> 245122 | H9: =SUM(H7:H8) -> 281724 | I9: =SUM(I7:I8) -> 331839 | J9: =IF(COUNT(J7:J8)=0,"",SUM(J7:J8)) -> 390029.04 | K9: =IF(COUNT(K7:K8)=0,"",SUM(K7:K8)) -> 460285.55 | L9: =IF(COUNT(L7:L8)=0,"",SUM(L7:L8)) -> 536514.82 | M9: =IF(COUNT(M7:M8)=0,"",SUM(M7:M8)) -> 618218.8 | N9: =IF(COUNT(N7:N8)=0,"",SUM(N7:N8)) -> 702027.22
B10: COGS
B11: Product | E11: 19064 | F11: 17804 | G11: 15272 | H11: 13501 | I11: 12098 | J11: ='3 statement Model'!J12 -> 12339.96 | K11: ='3 statement Model'!K12 -> 12586.759 | L11: ='3 statement Model'!L12 -> 12838.494 | M11: ='3 statement Model'!M12 -> 13095.264 | N11: ='3 statement Model'!N12 -> 13357.17
B12: Service and other | E12: 43586 | F12: 48059 | G12: 58842 | H12: 74330 | I12: 94276 | J12: ='3 statement Model'!J13 -> 121830.03 | K12: ='3 statement Model'!K13 -> 145751.47 | L12: ='3 statement Model'!L13 -> 170649.57 | M12: ='3 statement Model'!M13 -> 197099.13 | N12: ='3 statement Model'!N13 -> 223928.03
B13: Total cost of revenue | E13: =SUM(E11:E12) -> 62650 | F13: =SUM(F11:F12) -> 65863 | G13: =SUM(G11:G12) -> 74114 | H13: =SUM(H11:H12) -> 87831 | I13: =SUM(I11:I12) -> 106374 | J13: =IF(COUNT(J11:J12)=0,"",SUM(J11:J12)) -> 134169.99 | K13: =IF(COUNT(K11:K12)=0,"",SUM(K11:K12)) -> 158338.23 | L13: =IF(COUNT(L11:L12)=0,"",SUM(L11:L12)) -> 183488.07 | M13: =IF(COUNT(M11:M12)=0,"",SUM(M11:M12)) -> 210194.39 | N13: =IF(COUNT(N11:N12)=0,"",SUM(N11:N12)) -> 237285.2
B15: Gross margin | E15: =E9-E13 -> 135620 | F15: =F9-F13 -> 146052 | G15: =G9-G13 -> 171008 | H15: =H9-H13 -> 193893 | I15: =I9-I13 -> 225465 | J15: =IF(OR(J9="",J13=""),"",J9-J13) -> 255859.05 | K15: =IF(OR(K9="",K13=""),"",K9-K13) -> 301947.32 | L15: =IF(OR(L9="",L13=""),"",L9-L13) -> 353026.75 | M15: =IF(OR(M9="",M13=""),"",M9-M13) -> 408024.41 | N15: =IF(OR(N9="",N13=""),"",N9-N13) -> 464742.02
B17: Research and development | E17: 24512 | F17: 27195 | G17: 29510 | H17: 32488 | I17: 35562 | J17: ='3 statement Model'!J18 -> 38612.875 | K17: ='3 statement Model'!K18 -> 45107.984 | L17: ='3 statement Model'!L18 -> 52041.937 | M17: ='3 statement Model'!M18 -> 59349.005 | N17: ='3 statement Model'!N18 -> 65990.559
B18: Sales and marketing | E18: 21825 | F18: 22759 | G18: 24456 | H18: 25654 | I18: 26710 | J18: ='3 statement Model'!J19 -> 28082.091 | K18: ='3 statement Model'!K19 -> 32680.274 | L18: ='3 statement Model'!L19 -> 37556.037 | M18: ='3 statement Model'!M19 -> 42657.097 | N18: ='3 statement Model'!N19 -> 47035.824
B19: General and administrative | E19: 5900 | F19: 7575 | G19: 7609 | H19: 7223 | I19: 7956 | J19: ='3 statement Model'!J20 -> 8190.6098 | K19: ='3 statement Model'!K20 -> 9665.9966 | L19: ='3 statement Model'!L20 -> 10730.296 | M19: ='3 statement Model'!M20 -> 12364.376 | N19: ='3 statement Model'!N20 -> 14040.544
B20: EBITDA | E20: =E22+E21 -> 97843 | F20: =F22+F21 -> 102384 | G20: =G22+G21 -> 130391 | H20: =H22+H21 -> 157961 | I20: =I22+I21 -> 193771 | J20: ='3 statement Model'!J21 -> 234680.35 | K20: ='3 statement Model'!K21 -> 281830.21 | L20: ='3 statement Model'!L21 -> 334436.74 | M20: ='3 statement Model'!M21 -> 389564.1 | N20: ='3 statement Model'!N21 -> 448271.99
B21: Depreciation, Amortization, and other | E21: =E57 -> 14460 | F21: =F57 -> 13861 | G21: =G57 -> 20958 | H21: =H57 -> 29433 | I21: =I57 -> 38534 | J21: ='3 statement Model'!J23 -> 53706.88 | K21: ='3 statement Model'!K23 -> 67337.146 | L21: ='3 statement Model'!L23 -> 81738.257 | M21: ='3 statement Model'!M23 -> 95910.173 | N21: ='3 statement Model'!N23 -> 110596.9
B22: Operating income/EBIT | E22: =E15-SUM(E17:E19) -> 83383 | F22: =F15-SUM(F17:F19) -> 88523 | G22: =G15-SUM(G17:G19) -> 109433 | H22: =H15-SUM(H17:H19) -> 128528 | I22: =I15-SUM(I17:I19) -> 155237 | J22: ='3 statement Model'!J25 -> 180973.47 | K22: ='3 statement Model'!K25 -> 214493.07 | L22: ='3 statement Model'!L25 -> 252698.48 | M22: ='3 statement Model'!M25 -> 293653.93 | N22: ='3 statement Model'!N25 -> 337675.09
B23: Interest and dividends income | E23: 2094 | F23: 2994 | G23: 3157 | H23: 2647 | I23: =IF(OR(H23="",G98="",H98="",I98=""),"",H23/AVERAGE(G98,H98)*AVERAGE(H98,I98)) -> 2789.8247 | J23: ='3 statement Model'!J26 -> 2689.505 | K23: ='3 statement Model'!K26 -> 3517.2654 | L23: ='3 statement Model'!L26 -> 5080.5689 | M23: ='3 statement Model'!M26 -> 7610.0667 | N23: ='3 statement Model'!N26 -> 10997.846
B24: Interest expense | E24: -2063 | F24: -1968 | G24: -2935 | H24: -2385 | I24: -3051 | J24: ='3 statement Model'!J27 -> -5169.0662 | K24: ='3 statement Model'!K27 -> -5446.6191 | L24: ='3 statement Model'!L27 -> -5712.7091 | M24: ='3 statement Model'!M27 -> -5965.1667 | N24: ='3 statement Model'!N27 -> -6171.5862
B25: Other non-operating items | E25: =E26-E23-E24 -> 302 | F25: =F26-F23-F24 -> -238 | G25: =G26-G23-G24 -> -1868 | H25: =H26-H23-H24 -> -5163 | I25: =IF(OR(I26="",I23="",I24=""),"",I26-I23-I24) -> 10958.175 | J25: =IF(OR(J26="",J23="",J24=""),"",J26-J23-J24) -> 0 | K25: =IF(OR(K26="",K23="",K24=""),"",K26-K23-K24) -> 0 | L25: =IF(OR(L26="",L23="",L24=""),"",L26-L23-L24) -> 0 | M25: =IF(OR(M26="",M23="",M24=""),"",M26-M23-M24) -> 0 | N25: =IF(OR(N26="",N23="",N24=""),"",N26-N23-N24) -> 0
B26: Other income (expense), net | E26: 333 | F26: 788 | G26: -1646 | H26: -4901 | I26: 10697 | J26: ='3 statement Model'!J29 -> -2479.5612 | K26: ='3 statement Model'!K29 -> -1929.3536 | L26: ='3 statement Model'!L29 -> -632.14019 | M26: ='3 statement Model'!M29 -> 1644.9 | N26: ='3 statement Model'!N29 -> 4826.2598
B27: EBT | E27: =E22+E26 -> 83716 | F27: =F22+F26 -> 89311 | G27: =G22+G26 -> 107787 | H27: =H22+H26 -> 123627 | I27: =I22+I26 -> 165934 | J27: ='3 statement Model'!J30 -> 178493.91 | K27: ='3 statement Model'!K30 -> 212563.71 | L27: ='3 statement Model'!L30 -> 252066.34 | M27: ='3 statement Model'!M30 -> 295298.83 | N27: ='3 statement Model'!N30 -> 342501.35
B28: Provision for income taxes/ Taxes | E28: 10978 | F28: 16950 | G28: 19651 | H28: 21795 | I28: 32185 | J28: ='3 statement Model'!J32 -> 35698.783 | K28: ='3 statement Model'!K32 -> 42512.743 | L28: ='3 statement Model'!L32 -> 50413.268 | M28: ='3 statement Model'!M32 -> 59059.766 | N28: ='3 statement Model'!N32 -> 68500.271
B29: Net income | E29: =E27-E28 -> 72738 | F29: =F27-F28 -> 72361 | G29: =G27-G28 -> 88136 | H29: =H27-H28 -> 101832 | I29: =I27-I28 -> 133749 | J29: ='3 statement Model'!J33 -> 142795.13 | K29: ='3 statement Model'!K33 -> 170050.97 | L29: ='3 statement Model'!L33 -> 201653.07 | M29: ='3 statement Model'!M33 -> 236239.06 | N29: ='3 statement Model'!N33 -> 274001.08
B32: Historical Reported / Forecast Analyst-Modeled Segment Results | E32: Historical | I32: Forecasted
B33: (In millions, except growth) | E33: =(2021+COLUMN()-COLUMN($D$5))&IF(COLUMN()-COLUMN($D$5)<5,"A","E") -> 2022A | F33: =(2021+COLUMN()-COLUMN($D$5))&IF(COLUMN()-COLUMN($D$5)<5,"A","E") -> 2023A | G33: =(2021+COLUMN()-COLUMN($D$5))&IF(COLUMN()-COLUMN($D$5)<5,"A","E") -> 2024A | H33: =(2021+COLUMN()-COLUMN($D$5))&IF(COLUMN()-COLUMN($D$5)<5,"A","E") -> 2025A | I33: 2026A | J33: =(2021+COLUMN()-COLUMN($D$5))&IF(COLUMN()-COLUMN($D$5)<5,"A","E") -> 2027E | K33: =(2021+COLUMN()-COLUMN($D$5))&IF(COLUMN()-COLUMN($D$5)<5,"A","E") -> 2028E | L33: =(2021+COLUMN()-COLUMN($D$5))&IF(COLUMN()-COLUMN($D$5)<5,"A","E") -> 2029E | M33: =(2021+COLUMN()-COLUMN($D$5))&IF(COLUMN()-COLUMN($D$5)<5,"A","E") -> 2030E | N33: =(2021+COLUMN()-COLUMN($D$5))&IF(COLUMN()-COLUMN($D$5)<5,"A","E") -> 2031E
B34: SEGMENT REVENUE
B35: Productivity and Business Processes | E35: 63364 | F35: 94151 | G35: 106820 | H35: 120810 | I35: 139996 | J35: ='3 statement Model'!J39 -> 156795.52 | K35: ='3 statement Model'!K39 -> 175610.98 | L35: ='3 statement Model'!L39 -> 194928.19 | M35: ='3 statement Model'!M39 -> 214421.01 | N35: ='3 statement Model'!N39 -> 233718.9
B36: Intelligent Cloud | E36: 74965 | F36: 72944 | G36: 87464 | H36: 106265 | I36: 137791 | J36: ='3 statement Model'!J40 -> 181884.12 | K36: ='3 statement Model'!K40 -> 232811.67 | L36: ='3 statement Model'!L40 -> 288686.48 | M36: ='3 statement Model'!M40 -> 349310.64 | N36: ='3 statement Model'!N40 -> 412186.55
B37: More Personal Computing | E37: 59941 | F37: 44820 | G37: 50838 | H37: 54649 | I37: 54052 | J37: ='3 statement Model'!J41 -> 51349.4 | K37: ='3 statement Model'!K41 -> 51862.894 | L37: ='3 statement Model'!L41 -> 52900.152 | M37: ='3 statement Model'!M41 -> 54487.156 | N37: ='3 statement Model'!N41 -> 56121.771
B38: Total segment revenue | E38: =SUM(E35:E37) -> 198270 | F38: =SUM(F35:F37) -> 211915 | G38: =SUM(G35:G37) -> 245122 | H38: =SUM(H35:H37) -> 281724 | I38: =SUM(I35:I37) -> 331839 | J38: =IF(COUNT(J35:J37)=0,"",SUM(J35:J37)) -> 390029.04 | K38: =IF(COUNT(K35:K37)=0,"",SUM(K35:K37)) -> 460285.55 | L38: =IF(COUNT(L35:L37)=0,"",SUM(L35:L37)) -> 536514.82 | M38: =IF(COUNT(M35:M37)=0,"",SUM(M35:M37)) -> 618218.8 | N38: =IF(COUNT(N35:N37)=0,"",SUM(N35:N37)) -> 702027.22
B40: SEGMENT OPERATING INCOME — FORECAST ANALYST ALLOCATION
B41: Productivity and Business Processes | E41: 29690 | F41: 50074 | G41: 59661 | H41: 69773 | I41: 83879 | J41: ='3 statement Model'!J45 -> 92998.559 | K41: ='3 statement Model'!K45 -> 104832.68 | L41: ='3 statement Model'!L45 -> 117942.27 | M41: ='3 statement Model'!M45 -> 131266.02 | N41: ='3 statement Model'!N45 -> 145317.77
B42: Intelligent Cloud | E42: 33203 | F42: 28411 | G42: 37813 | H42: 44589 | I42: 56972 | J42: ='3 statement Model'!J46 -> 74445.825 | K42: ='3 statement Model'!K46 -> 95907.544 | L42: ='3 statement Model'!L46 -> 120538.08 | M42: ='3 statement Model'!M46 -> 147570.58 | N42: ='3 statement Model'!N46 -> 176856.78
B43: More Personal Computing | E43: 20490 | F43: 10038 | G43: 11959 | H43: 14166 | I43: 14386 | J43: ='3 statement Model'!J47 -> 13529.091 | K43: ='3 statement Model'!K47 -> 13752.841 | L43: ='3 statement Model'!L47 -> 14218.128 | M43: ='3 statement Model'!M47 -> 14817.325 | N43: ='3 statement Model'!N47 -> 15500.544
B44: Total segment operating income | E44: =SUM(E41:E43) -> 83383 | F44: =SUM(F41:F43) -> 88523 | G44: =SUM(G41:G43) -> 109433 | H44: =SUM(H41:H43) -> 128528 | I44: =SUM(I41:I43) -> 155237 | J44: =IF(COUNT(J41:J43)=0,"",SUM(J41:J43)) -> 180973.47 | K44: =IF(COUNT(K41:K43)=0,"",SUM(K41:K43)) -> 214493.07 | L44: =IF(COUNT(L41:L43)=0,"",SUM(L41:L43)) -> 252698.48 | M44: =IF(COUNT(M41:M43)=0,"",SUM(M41:M43)) -> 293653.93 | N44: =IF(COUNT(N41:N43)=0,"",SUM(N41:N43)) -> 337675.09
B46: KEY CLOUD DISCLOSURE
B47: Azure revenue (minimum disclosed) | H47: >75,000
B48: Azure and other cloud services growth | F48: 0.29 | G48: 0.3
B49: Azure revenue growth | H49: 0.34
B50: Note: FY2022 segment data is not comparable with FY2023–FY2026 due to reallocations. FY2027–FY2031 retains analyst-modeled legacy categories and estimated EBIT allocations; these are not reported post-reorganization segments.
B52: Cash Flow Statement | E52: Historical | I52: Forecasted
B53: (In millions) | E53: =(2021+COLUMN()-COLUMN($D$5))&IF(COLUMN()-COLUMN($D$5)<5,"A","E") -> 2022A | F53: =(2021+COLUMN()-COLUMN($D$5))&IF(COLUMN()-COLUMN($D$5)<5,"A","E") -> 2023A | G53: =(2021+COLUMN()-COLUMN($D$5))&IF(COLUMN()-COLUMN($D$5)<5,"A","E") -> 2024A | H53: =(2021+COLUMN()-COLUMN($D$5))&IF(COLUMN()-COLUMN($D$5)<5,"A","E") -> 2025A | I53: 2026A | J53: =(2021+COLUMN()-COLUMN($D$5))&IF(COLUMN()-COLUMN($D$5)<5,"A","E") -> 2027E | K53: =(2021+COLUMN()-COLUMN($D$5))&IF(COLUMN()-COLUMN($D$5)<5,"A","E") -> 2028E | L53: =(2021+COLUMN()-COLUMN($D$5))&IF(COLUMN()-COLUMN($D$5)<5,"A","E") -> 2029E | M53: =(2021+COLUMN()-COLUMN($D$5))&IF(COLUMN()-COLUMN($D$5)<5,"A","E") -> 2030E | N53: =(2021+COLUMN()-COLUMN($D$5))&IF(COLUMN()-COLUMN($D$5)<5,"A","E") -> 2031E
B54: Operations
B55: Net income | E55: 72738 | F55: 72361 | G55: 88136 | H55: 101832 | I55: 133749 | J55: ='3 statement Model'!J54 -> 142795.13 | K55: ='3 statement Model'!K54 -> 170050.97 | L55: ='3 statement Model'!L54 -> 201653.07 | M55: ='3 statement Model'!M54 -> 236239.06 | N55: ='3 statement Model'!N54 -> 274001.08
B56: Adjustments for Non-cash Operation
B57: Depreciation, amortization, and other | E57: 14460 | F57: 13861 | G57: 20958 | H57: 29433 | I57: 38534 | J57: ='3 statement Model'!J56 -> 53706.88 | K57: ='3 statement Model'!K56 -> 67337.146 | L57: ='3 statement Model'!L56 -> 81738.257 | M57: ='3 statement Model'!M56 -> 95910.173 | N57: ='3 statement Model'!N56 -> 110596.9
B58: Stock-based compensation expense | E58: 7502 | F58: 9611 | G58: 10734 | H58: 11974 | I58: 12405 | J58: ='3 statement Model'!J57 -> 14431.074 | K58: ='3 statement Model'!K57 -> 16570.28 | L58: ='3 statement Model'!L57 -> 18778.019 | M58: ='3 statement Model'!M57 -> 21019.439 | N58: ='3 statement Model'!N57 -> 23166.898
B59: Net recognized losses (gains) on investments and derivatives | E59: -409 | F59: 196 | G59: 1634 | H59: 5329 | I59: -11047 | J59: ='3 statement Model'!J58 -> 0 | K59: ='3 statement Model'!K58 -> 0 | L59: ='3 statement Model'!L58 -> 0 | M59: ='3 statement Model'!M58 -> 0 | N59: ='3 statement Model'!N58 -> 0
B60: Deferred income taxes | E60: -5702 | F60: -6059 | G60: -4738 | H60: -7056 | I60: 14189 | J60: ='3 statement Model'!J59 -> 0 | K60: ='3 statement Model'!K59 -> 0 | L60: ='3 statement Model'!L59 -> 0 | M60: ='3 statement Model'!M59 -> 0 | N60: ='3 statement Model'!N59 -> 0
B61: Other non-cash adjustments | E61: =SUM(E59:E60) -> -6111 | F61: =SUM(F59:F60) -> -5863 | G61: =SUM(G59:G60) -> -3104 | H61: =SUM(H59:H60) -> -1727 | I61: =SUM(I59:I60) -> 3142 | J61: =SUM(J59:J60) -> 0 | K61: =SUM(K59:K60) -> 0 | L61: =SUM(L59:L60) -> 0 | ... N61: =SUM(N59:N60) -> 0
B62: Changes in operating assets and liabilities:
B63: Accounts receivable | E63: -6834 | F63: -4087 | G63: -7191 | H63: -10581 | I63: -12737 | J63: ='3 statement Model'!J61 -> -14226.971 | K63: ='3 statement Model'!K61 -> -17131.039 | L63: ='3 statement Model'!L61 -> -17117.507 | M63: ='3 statement Model'!M61 -> -19698.495 | N63: ='3 statement Model'!N61 -> -18282.503
B64: Inventories | E64: -1123 | F64: 1242 | G64: 1284 | H64: 309 | I64: -461 | J64: ='3 statement Model'!J62 -> -440.94507 | K64: ='3 statement Model'!K62 -> -331.07177 | L64: ='3 statement Model'!L62 -> -344.51833 | M64: ='3 statement Model'!M62 -> -365.84006 | N64: ='3 statement Model'!N62 -> -371.10696
B65: Other current assets | E65: -709 | F65: -1991 | G65: -1648 | H65: -3044 | I65: -2627
B66: Other long-term assets | E66: -2805 | F66: -2833 | G66: -6817 | H66: -2950 | I66: -3964
B67: Other operating assets / operating lease CFO bridge (forecast aggregate) | E67: -3514 | F67: -4824 | G67: -8465 | H67: -5994 | I67: -6591 | J67: ='3 statement Model'!J63 -> 678.79286 | K67: ='3 statement Model'!K63 -> 830.49702 | L67: ='3 statement Model'!L63 -> 945.20652 | M67: ='3 statement Model'!M63 -> 1032.1944 | N67: ='3 statement Model'!N63 -> 1098.4102
B68: Accounts payable | E68: 2943 | F68: -2721 | G68: 3545 | H68: 569 | I68: 5268 | J68: ='3 statement Model'!J64 -> 9046.4618 | K68: ='3 statement Model'!K64 -> 7100.9928 | L68: ='3 statement Model'!L64 -> 6788.4599 | M68: ='3 statement Model'!M64 -> 6632.4664 | N68: ='3 statement Model'!N64 -> 6027.1919
B69: Deferred Revenue (Unearned revenue) | E69: 5109 | F69: 5535 | G69: 5348 | H69: 5438 | I69: 9361 | J69: ='3 statement Model'!J65 -> 10094.389 | K69: ='3 statement Model'!K65 -> 15456.432 | L69: ='3 statement Model'!L65 -> 16770.439 | M69: ='3 statement Model'!M65 -> 17974.876 | N69: ='3 statement Model'!N65 -> 18437.852
B70: Income taxes | E70: 696 | F70: -358 | G70: 1687 | H70: -38 | I70: -1875 | J70: ='3 statement Model'!J66 -> 444.35272 | K70: ='3 statement Model'!K66 -> 536.4951 | L70: ='3 statement Model'!L66 -> 582.10447 | M70: ='3 statement Model'!M66 -> 623.91067 | N70: ='3 statement Model'!N66 -> 639.98064
B71: Other current liabilities | E71: 2344 | F71: 2272 | G71: 4867 | H71: 5922 | I71: 6847
B72: Other long-term liabilities | E72: 825 | F72: 553 | G72: 749 | H72: -975 | I72: -4707
B73: Other operating liabilities (forecast aggregate) | E73: 3169 | F73: 2825 | G73: 5616 | H73: 4947 | I73: 2140 | J73: ='3 statement Model'!J67 -> 5611.3997 | K73: ='3 statement Model'!K67 -> 6774.9973 | L73: ='3 statement Model'!L67 -> 7350.9641 | M73: ='3 statement Model'!M67 -> 7878.9035 | N73: ='3 statement Model'!N67 -> 8081.8392
B74: Net cash from operations | E74: =IF(COUNT(E55,E57:E60,E63:E64,E67:E70,E73)=0,"",SUM(E55,E57:E60,E63:E64,E67,E68:E70,E73)) -> 89035 | F74: =IF(COUNT(F55,F57:F60,F63:F64,F67:F70,F73)=0,"",SUM(F55,F57:F60,F63:F64,F67,F68:F70,F73)) -> 87582 | G74: =IF(COUNT(G55,G57:G60,G63:G64,G67:G70,G73)=0,"",SUM(G55,G57:G60,G63:G64,G67,G68:G70,G73)) -> 118548 | H74: =IF(COUNT(H55,H57:H60,H63:H64,H67:H70,H73)=0,"",SUM(H55,H57:H60,H63:H64,H67,H68:H70,H73)) -> 136162 | I74: =IF(COUNT(I55,I57:I60,I63:I64,I67:I70,I73)=0,"",SUM(I55,I57:I60,I63:I64,I67,I68:I70,I73)) -> 182935 | J74: =IF(COUNT(J55,J57:J60,J63:J64,J67:J70,J73)=0,"",SUM(J55,J57:J60,J63:J64,J67:J70,J73)) -> 222140.56 | K74: =IF(COUNT(K55,K57:K60,K63:K64,K67:K70,K73)=0,"",SUM(K55,K57:K60,K63:K64,K67:K70,K73)) -> 267195.7 | L74: =IF(COUNT(L55,L57:L60,L63:L64,L67:L70,L73)=0,"",SUM(L55,L57:L60,L63:L64,L67:L70,L73)) -> 317144.5 | M74: =IF(COUNT(M55,M57:M60,M63:M64,M67:M70,M73)=0,"",SUM(M55,M57:M60,M63:M64,M67:M70,M73)) -> 367246.69 | N74: =IF(COUNT(N55,N57:N60,N63:N64,N67:N70,N73)=0,"",SUM(N55,N57:N60,N63:N64,N67:N70,N73)) -> 423396.55
B75: Financing
B76: Net debt issuance/(repayment) | E76: -9023 | F76: -2750 | G76: 575 | H76: -8962 | I76: -3000 | J76: ='3 statement Model'!J70 -> -2200 | K76: ='3 statement Model'!K70 -> -3000 | L76: ='3 statement Model'!L70 -> -1300 | M76: ='3 statement Model'!M70 -> -2300 | N76: ='3 statement Model'!N70 -> -2000
B77: Net share issuance/(repurchase) | E77: -30855 | F77: -20379 | G77: -15252 | H77: -16364 | I77: -20262 | J77: ='3 statement Model'!J71 -> -22000 | K77: ='3 statement Model'!K71 -> -24000 | L77: ='3 statement Model'!L71 -> -26000 | M77: ='3 statement Model'!M71 -> -28000 | N77: ='3 statement Model'!N71 -> -30000
B78: Common stock cash dividends paid | E78: -18135 | F78: -19800 | G78: -21771 | H78: -24082 | I78: -26445 | J78: ='3 statement Model'!J72 -> -28559.026 | K78: ='3 statement Model'!K72 -> -34010.194 | L78: ='3 statement Model'!L72 -> -40330.614 | M78: ='3 statement Model'!M72 -> -47247.813 | N78: ='3 statement Model'!N72 -> -54800.216
B79: Other, net | E79: -863 | F79: -1006 | G79: -1309 | H79: -2291 | I79: -2839 | J79: ='3 statement Model'!J73 -> -5549.5 | K79: ='3 statement Model'!K73 -> -6337.0417 | L79: ='3 statement Model'!L73 -> -7058.9549 | M79: ='3 statement Model'!M73 -> -7720.7086 | N79: ='3 statement Model'!N73 -> -8327.3162
B80: Net cash used in financing | E80: =IF(COUNT(E76:E79)=0,"",SUM(E76:E79)) -> -58876 | F80: =IF(COUNT(F76:F79)=0,"",SUM(F76:F79)) -> -43935 | G80: =IF(COUNT(G76:G79)=0,"",SUM(G76:G79)) -> -37757 | H80: =IF(COUNT(H76:H79)=0,"",SUM(H76:H79)) -> -51699 | I80: =IF(COUNT(I76:I79)=0,"",SUM(I76:I79)) -> -52546 | J80: =IF(COUNT(J76:J79)=0,"",SUM(J76:J79)) -> -58308.526 | K80: =IF(COUNT(K76:K79)=0,"",SUM(K76:K79)) -> -67347.236 | L80: =IF(COUNT(L76:L79)=0,"",SUM(L76:L79)) -> -74689.569 | ... N80: =IF(COUNT(N76:N79)=0,"",SUM(N76:N79)) -> -95127.533
B81: Investing
B82: Capex | E82: -23886 | F82: -28107 | G82: -44477 | H82: -64551 | I82: -115948 | J82: ='3 statement Model'!J76 -> -140000 | K82: ='3 statement Model'!K76 -> -155000 | L82: ='3 statement Model'!L76 -> -170000 | M82: ='3 statement Model'!M76 -> -185000 | N82: ='3 statement Model'!N76 -> -200000
B83: Acquisition of companies, net of cash acquired and divestitures, and purchases of intangible and other assets | E83: -22038 | F83: -1670 | G83: -69132 | H83: -5978 | I83: -1743 | J83: ='3 statement Model'!J77 -> 0 | K83: ='3 statement Model'!K77 -> 0 | L83: ='3 statement Model'!L77 -> 0 | M83: ='3 statement Model'!M77 -> 0 | N83: ='3 statement Model'!N77 -> 0
B84: Net investment activity | E84: 18438 | F84: 10213 | G84: 17937 | H84: -4387 | I84: -1948 | J84: ='3 statement Model'!J78 -> -2778.096 | K84: ='3 statement Model'!K78 -> -10721.125 | L84: ='3 statement Model'!L78 -> -11617.952 | M84: ='3 statement Model'!M78 -> -12440.077 | N84: ='3 statement Model'!N78 -> -12756.665
B85: Other, net | E85: -2825 | F85: -3116 | G85: -1298 | H85: 2317 | I85: -19861 | J85: ='3 statement Model'!J79 -> 0 | K85: ='3 statement Model'!K79 -> 0 | L85: ='3 statement Model'!L79 -> 0 | M85: ='3 statement Model'!M79 -> 0 | N85: ='3 statement Model'!N79 -> 0
B86: Net cash used in investing | E86: =IF(COUNT(E82:E85)=0,"",SUM(E82:E85)) -> -30311 | F86: =IF(COUNT(F82:F85)=0,"",SUM(F82:F85)) -> -22680 | G86: =IF(COUNT(G82:G85)=0,"",SUM(G82:G85)) -> -96970 | H86: =IF(COUNT(H82:H85)=0,"",SUM(H82:H85)) -> -72599 | I86: =IF(COUNT(I82:I85)=0,"",SUM(I82:I85)) -> -139500 | J86: =IF(COUNT(J82:J85)=0,"",SUM(J82:J85)) -> -142778.1 | K86: =IF(COUNT(K82:K85)=0,"",SUM(K82:K85)) -> -165721.13 | L86: =IF(COUNT(L82:L85)=0,"",SUM(L82:L85)) -> -181617.95 | ... N86: =IF(COUNT(N82:N85)=0,"",SUM(N82:N85)) -> -212756.67
B87: Effect of foreign exchange rates on cash and cash equivalents | E87: -141 | F87: -194 | G87: -210 | H87: 63 | I87: -196 | J87: ='3 statement Model'!J81 -> 0 | K87: ='3 statement Model'!K81 -> 0 | L87: ='3 statement Model'!L81 -> 0 | M87: ='3 statement Model'!M81 -> 0 | N87: ='3 statement Model'!N81 -> 0
B88: Net change in cash and cash equivalents | E88: =SUM(E74,E80,E86,E87) -> -293 | F88: =SUM(F74,F80,F86,F87) -> 20773 | G88: =SUM(G74,G80,G86,G87) -> -16389 | H88: =SUM(H74,H80,H86,H87) -> 11927 | I88: =SUM(I74,I80,I86,I87) -> -9307 | J88: =IF(COUNT(J74,J80,J86,J87)=0,"",SUM(J74,J80,J86,J87)) -> 21053.942 | K88: =IF(COUNT(K74,K80,K86,K87)=0,"",SUM(K74,K80,K86,K87)) -> 34127.338 | L88: =IF(COUNT(L74,L80,L86,L87)=0,"",SUM(L74,L80,L86,L87)) -> 60836.974 | M88: =IF(COUNT(M74,M80,M86,M87)=0,"",SUM(M74,M80,M86,M87)) -> 84538.095 | N88: =IF(COUNT(N74,N80,N86,N87)=0,"",SUM(N74,N80,N86,N87)) -> 115512.35
B89: Cash and cash equivalents, beginning of period | E89: 14224 | F89: 13931 | G89: 34704 | H89: 18315 | I89: 30242 | J89: ='3 statement Model'!J83 -> 20935 | K89: ='3 statement Model'!K83 -> 41988.942 | L89: ='3 statement Model'!L83 -> 76116.28 | M89: ='3 statement Model'!M83 -> 136953.25 | N89: ='3 statement Model'!N83 -> 221491.35
B90: Cash and cash equivalents, end of period | E90: =SUM(E88:E89) -> 13931 | F90: =SUM(F88:F89) -> 34704 | G90: =SUM(G88:G89) -> 18315 | H90: =SUM(H88:H89) -> 30242 | I90: =SUM(I88:I89) -> 20935 | J90: =IF(COUNT(J88:J89)=0,"",SUM(J88:J89)) -> 41988.942 | K90: =IF(COUNT(K88:K89)=0,"",SUM(K88:K89)) -> 76116.28 | L90: =IF(COUNT(L88:L89)=0,"",SUM(L88:L89)) -> 136953.25 | M90: =IF(COUNT(M88:M89)=0,"",SUM(M88:M89)) -> 221491.35 | N90: =IF(COUNT(N88:N89)=0,"",SUM(N88:N89)) -> 337003.7
B92: Balance sheet check | E92: =IF(OR(E109="",E132=""),"",E109-E132) -> 0 | F92: =IF(OR(F109="",F132=""),"",F109-F132) -> 0 | G92: =IF(OR(G109="",G132=""),"",G109-G132) -> 0 | H92: =IF(OR(H109="",H132=""),"",H109-H132) -> 0 | I92: =IF(OR(I109="",I132=""),"",I109-I132) -> 0 | J92: =IF(OR(J109="",J132=""),"",J109-J132) -> 2.3283064e-10 | K92: =IF(OR(K109="",K132=""),"",K109-K132) -> 0 | L92: =IF(OR(L109="",L132=""),"",L109-L132) -> 0 | ... N92: =IF(OR(N109="",N132=""),"",N109-N132) -> -2.3283064e-10
B94: Balance sheet | E94: Historical | I94: Forecasted
B95: (In millions) | E95: =(2021+COLUMN()-COLUMN($D$5))&IF(COLUMN()-COLUMN($D$5)<5,"A","E") -> 2022A | F95: =(2021+COLUMN()-COLUMN($D$5))&IF(COLUMN()-COLUMN($D$5)<5,"A","E") -> 2023A | G95: =(2021+COLUMN()-COLUMN($D$5))&IF(COLUMN()-COLUMN($D$5)<5,"A","E") -> 2024A | H95: =(2021+COLUMN()-COLUMN($D$5))&IF(COLUMN()-COLUMN($D$5)<5,"A","E") -> 2025A | I95: 2026A | J95: =(2021+COLUMN()-COLUMN($D$5))&IF(COLUMN()-COLUMN($D$5)<5,"A","E") -> 2027E | K95: =(2021+COLUMN()-COLUMN($D$5))&IF(COLUMN()-COLUMN($D$5)<5,"A","E") -> 2028E | L95: =(2021+COLUMN()-COLUMN($D$5))&IF(COLUMN()-COLUMN($D$5)<5,"A","E") -> 2029E | M95: =(2021+COLUMN()-COLUMN($D$5))&IF(COLUMN()-COLUMN($D$5)<5,"A","E") -> 2030E | N95: =(2021+COLUMN()-COLUMN($D$5))&IF(COLUMN()-COLUMN($D$5)<5,"A","E") -> 2031E
B96: Assets
B97: Current assets:
B98: Cash and cash equivalents | E98: 13931 | F98: 34704 | G98: 18315 | H98: 30242 | I98: 20935 | J98: ='3 statement Model'!J91 -> 41988.942 | K98: ='3 statement Model'!K91 -> 76116.28 | L98: ='3 statement Model'!L91 -> 136953.25 | M98: ='3 statement Model'!M91 -> 221491.35 | N98: ='3 statement Model'!N91 -> 337003.7
B99: Short-term investments | E99: 90826 | F99: 76558 | G99: 57228 | H99: 64323 | I99: 55908 | J99: ='3 statement Model'!J92 -> 58504.356 | K99: ='3 statement Model'!K92 -> 69042.833 | L99: ='3 statement Model'!L92 -> 80477.223 | M99: ='3 statement Model'!M92 -> 92732.82 | N99: ='3 statement Model'!N92 -> 105304.08
B100: Accounts receivable | E100: 44261 | F100: 48688 | G100: 56924 | H100: 69905 | I100: 80876 | J100: ='3 statement Model'!J94 -> 95102.971 | K100: ='3 statement Model'!K94 -> 112234.01 | L100: ='3 statement Model'!L94 -> 129351.52 | M100: ='3 statement Model'!M94 -> 149050.01 | N100: ='3 statement Model'!N94 -> 167332.52
B101: Inventories | E101: 3742 | F101: 2500 | G101: 1246 | H101: 938 | I101: 1397 | J101: ='3 statement Model'!J95 -> 1837.9451 | K101: ='3 statement Model'!K95 -> 2169.0168 | L101: ='3 statement Model'!L95 -> 2513.5352 | M101: ='3 statement Model'!M95 -> 2879.3752 | N101: ='3 statement Model'!N95 -> 3250.4822
B102: Other current assets | E102: 16924 | F102: 21807 | G102: 26021 | H102: 25723 | I102: 48594 | J102: ='3 statement Model'!J96 -> 48594 | K102: ='3 statement Model'!K96 -> 48594 | L102: ='3 statement Model'!L96 -> 48594 | M102: ='3 statement Model'!M96 -> 48594 | N102: ='3 statement Model'!N96 -> 48594
B103: Total current assets | E103: =IF(COUNT(E98:E102)=0,"",SUM(E98:E102)) -> 169684 | F103: =IF(COUNT(F98:F102)=0,"",SUM(F98:F102)) -> 184257 | G103: =IF(COUNT(G98:G102)=0,"",SUM(G98:G102)) -> 159734 | H103: =IF(COUNT(H98:H102)=0,"",SUM(H98:H102)) -> 191131 | I103: =IF(COUNT(I98:I102)=0,"",SUM(I98:I102)) -> 207710 | J103: =IF(COUNT(J98:J102)=0,"",SUM(J98:J102)) -> 246028.21 | K103: =IF(COUNT(K98:K102)=0,"",SUM(K98:K102)) -> 308156.14 | L103: =IF(COUNT(L98:L102)=0,"",SUM(L98:L102)) -> 397889.53 | ... N103: =IF(COUNT(N98:N102)=0,"",SUM(N98:N102)) -> 661484.78
B104: Property and equipment, net | E104: 74398 | F104: 95641 | G104: 135591 | H104: 204966 | I104: 313076 | J104: ='3 statement Model'!J98 -> 417301.12 | K104: ='3 statement Model'!K98 -> 522001.97 | L104: ='3 statement Model'!L98 -> 627116.72 | M104: ='3 statement Model'!M98 -> 732591.54 | N104: ='3 statement Model'!N98 -> 838379.64
B105: Operating lease right-of-use assets | E105: 13148 | F105: 14346 | G105: 18961 | H105: 24823 | I105: 24177 | J105: ='3 statement Model'!J99 -> 31256.528 | K105: ='3 statement Model'!K99 -> 36609.638 | L105: ='3 statement Model'!L99 -> 40669.073 | M105: ='3 statement Model'!M99 -> 43759.143 | N105: ='3 statement Model'!N99 -> 46122.896
B106: Equity and other investments | E106: 6891 | F106: 9879 | G106: 14600 | H106: 15405 | I106: 36348 | J106: ='3 statement Model'!J100 -> 36529.74 | K106: ='3 statement Model'!K100 -> 36712.389 | L106: ='3 statement Model'!L100 -> 36895.951 | M106: ='3 statement Model'!M100 -> 37080.43 | N106: ='3 statement Model'!N100 -> 37265.833
B107: Goodwill and intangible assets | E107: 78822 | F107: 77252 | G107: 146817 | H107: 142113 | I107: 138260 | J107: ='3 statement Model'!J101 -> 135328 | K107: ='3 statement Model'!K101 -> 133290 | L107: ='3 statement Model'!L101 -> 131437 | M107: ='3 statement Model'!M101 -> 130052 | N107: ='3 statement Model'!N101 -> 128667
B108: Other long-term assets | E108: 21897 | F108: 30601 | G108: 36460 | H108: 40565 | I108: 38805 | J108: ='3 statement Model'!J102 -> 38805 | K108: ='3 statement Model'!K102 -> 38805 | L108: ='3 statement Model'!L102 -> 38805 | M108: ='3 statement Model'!M102 -> 38805 | N108: ='3 statement Model'!N102 -> 38805
B109: Total assets | E109: =IF(COUNT(E103:E108)=0,"",SUM(E103:E108)) -> 364840 | F109: =IF(COUNT(F103:F108)=0,"",SUM(F103:F108)) -> 411976 | G109: =IF(COUNT(G103:G108)=0,"",SUM(G103:G108)) -> 512163 | H109: =IF(COUNT(H103:H108)=0,"",SUM(H103:H108)) -> 619003 | I109: =IF(COUNT(I103:I108)=0,"",SUM(I103:I108)) -> 758376 | J109: =IF(COUNT(J103:J108)=0,"",SUM(J103:J108)) -> 905248.6 | K109: =IF(COUNT(K103:K108)=0,"",SUM(K103:K108)) -> 1075575.1 | L109: =IF(COUNT(L103:L108)=0,"",SUM(L103:L108)) -> 1272813.3 | ... N109: =IF(COUNT(N103:N108)=0,"",SUM(N103:N108)) -> 1750725.2
B110: Liabilities and stockholders’ equity
...

Sheet Common Size&Ratio
B1: Common-Size Financial Analysis: MSFT | N1: =HYPERLINK("#'Cover'!A1","Cover") -> Cover
F2: Year Ended June 30
B4: Income Statement | E4: Historical | I4: Forecasted
B5: (% of revenue) | E5: =(2021+COLUMN()-COLUMN($D$5))&IF(COLUMN()-COLUMN($D$5)<5,"A","E") -> 2022A | F5: =(2021+COLUMN()-COLUMN($D$5))&IF(COLUMN()-COLUMN($D$5)<5,"A","E") -> 2023A | G5: =(2021+COLUMN()-COLUMN($D$5))&IF(COLUMN()-COLUMN($D$5)<5,"A","E") -> 2024A | H5: =(2021+COLUMN()-COLUMN($D$5))&IF(COLUMN()-COLUMN($D$5)<5,"A","E") -> 2025A | I5: 2026A | J5: =(2021+COLUMN()-COLUMN($D$5))&IF(COLUMN()-COLUMN($D$5)<5,"A","E") -> 2027E | K5: =(2021+COLUMN()-COLUMN($D$5))&IF(COLUMN()-COLUMN($D$5)<5,"A","E") -> 2028E | L5: =(2021+COLUMN()-COLUMN($D$5))&IF(COLUMN()-COLUMN($D$5)<5,"A","E") -> 2029E | M5: =(2021+COLUMN()-COLUMN($D$5))&IF(COLUMN()-COLUMN($D$5)<5,"A","E") -> 2030E | N5: =(2021+COLUMN()-COLUMN($D$5))&IF(COLUMN()-COLUMN($D$5)<5,"A","E") -> 2031E
B6: Revenue:
B7: Product | E7: =IF('Fin Statement'!E7="","",'Fin Statement'!E7/'Fin Statement'!E9) -> 0.36683311 | F7: =IF('Fin Statement'!F7="","",'Fin Statement'!F7/'Fin Statement'!F9) -> 0.30530637 | G7: =IF('Fin Statement'!G7="","",'Fin Statement'!G7/'Fin Statement'!G9) -> 0.26424801 | H7: =IF('Fin Statement'!H7="","",'Fin Statement'!H7/'Fin Statement'!H9) -> 0.22698102 | I7: =IF('Fin Statement'!I7="","",'Fin Statement'!I7/'Fin Statement'!I9) -> 0.19496201 | J7: =IF('Fin Statement'!J7="","",'Fin Statement'!J7/'Fin Statement'!J9) -> 0.16919232 | K7: =IF('Fin Statement'!K7="","",'Fin Statement'!K7/'Fin Statement'!K9) -> 0.1462347 | L7: =IF('Fin Statement'!L7="","",'Fin Statement'!L7/'Fin Statement'!L9) -> 0.12796648 | ... N7: =IF('Fin Statement'!N7="","",'Fin Statement'!N7/'Fin Statement'!N9) -> 0.10174764
B8: Service and other | E8: =IF('Fin Statement'!E8="","",'Fin Statement'!E8/'Fin Statement'!E9) -> 0.63316689 | F8: =IF('Fin Statement'!F8="","",'Fin Statement'!F8/'Fin Statement'!F9) -> 0.69469363 | G8: =IF('Fin Statement'!G8="","",'Fin Statement'!G8/'Fin Statement'!G9) -> 0.73575199 | H8: =IF('Fin Statement'!H8="","",'Fin Statement'!H8/'Fin Statement'!H9) -> 0.77301898 | I8: =IF('Fin Statement'!I8="","",'Fin Statement'!I8/'Fin Statement'!I9) -> 0.80503799 | J8: =IF('Fin Statement'!J8="","",'Fin Statement'!J8/'Fin Statement'!J9) -> 0.83080768 | K8: =IF('Fin Statement'!K8="","",'Fin Statement'!K8/'Fin Statement'!K9) -> 0.8537653 | L8: =IF('Fin Statement'!L8="","",'Fin Statement'!L8/'Fin Statement'!L9) -> 0.87203352 | ... N8: =IF('Fin Statement'!N8="","",'Fin Statement'!N8/'Fin Statement'!N9) -> 0.89825236
B9: Total revenue | E9: =IF('Fin Statement'!E9="","",'Fin Statement'!E9/'Fin Statement'!E9) -> 1 | F9: =IF('Fin Statement'!F9="","",'Fin Statement'!F9/'Fin Statement'!F9) -> 1 | G9: =IF('Fin Statement'!G9="","",'Fin Statement'!G9/'Fin Statement'!G9) -> 1 | H9: =IF('Fin Statement'!H9="","",'Fin Statement'!H9/'Fin Statement'!H9) -> 1 | I9: =IF('Fin Statement'!I9="","",'Fin Statement'!I9/'Fin Statement'!I9) -> 1 | J9: =IF('Fin Statement'!J9="","",'Fin Statement'!J9/'Fin Statement'!J9) -> 1 | K9: =IF('Fin Statement'!K9="","",'Fin Statement'!K9/'Fin Statement'!K9) -> 1 | L9: =IF('Fin Statement'!L9="","",'Fin Statement'!L9/'Fin Statement'!L9) -> 1 | ... N9: =IF('Fin Statement'!N9="","",'Fin Statement'!N9/'Fin Statement'!N9) -> 1
B10: COGS
B11: Product | E11: =IF('Fin Statement'!E11="","",'Fin Statement'!E11/'Fin Statement'!E9) -> 0.096151712 | F11: =IF('Fin Statement'!F11="","",'Fin Statement'!F11/'Fin Statement'!F9) -> 0.084014817 | G11: =IF('Fin Statement'!G11="","",'Fin Statement'!G11/'Fin Statement'!G9) -> 0.062303669 | H11: =IF('Fin Statement'!H11="","",'Fin Statement'!H11/'Fin Statement'!H9) -> 0.04792279 | I11: =IF('Fin Statement'!I11="","",'Fin Statement'!I11/'Fin Statement'!I9) -> 0.036457439 | J11: =IF('Fin Statement'!J11="","",'Fin Statement'!J11/'Fin Statement'!J9) -> 0.031638567 | K11: =IF('Fin Statement'!K11="","",'Fin Statement'!K11/'Fin Statement'!K9) -> 0.027345545 | L11: =IF('Fin Statement'!L11="","",'Fin Statement'!L11/'Fin Statement'!L9) -> 0.023929431 | ... N11: =IF('Fin Statement'!N11="","",'Fin Statement'!N11/'Fin Statement'!N9) -> 0.019026569
B12: Service and other | E12: =IF('Fin Statement'!E12="","",'Fin Statement'!E12/'Fin Statement'!E9) -> 0.21983154 | F12: =IF('Fin Statement'!F12="","",'Fin Statement'!F12/'Fin Statement'!F9) -> 0.22678432 | G12: =IF('Fin Statement'!G12="","",'Fin Statement'!G12/'Fin Statement'!G9) -> 0.24005189 | H12: =IF('Fin Statement'!H12="","",'Fin Statement'!H12/'Fin Statement'!H9) -> 0.26383979 | I12: =IF('Fin Statement'!I12="","",'Fin Statement'!I12/'Fin Statement'!I9) -> 0.28410163 | J12: =IF('Fin Statement'!J12="","",'Fin Statement'!J12/'Fin Statement'!J9) -> 0.31236143 | K12: =IF('Fin Statement'!K12="","",'Fin Statement'!K12/'Fin Statement'!K9) -> 0.31665446 | L12: =IF('Fin Statement'!L12="","",'Fin Statement'!L12/'Fin Statement'!L9) -> 0.31807057 | ... N12: =IF('Fin Statement'!N12="","",'Fin Statement'!N12/'Fin Statement'!N9) -> 0.31897343
B13: Total cost of revenue | E13: =IF('Fin Statement'!E13="","",'Fin Statement'!E13/'Fin Statement'!E9) -> 0.31598326 | F13: =IF('Fin Statement'!F13="","",'Fin Statement'!F13/'Fin Statement'!F9) -> 0.31079914 | G13: =IF('Fin Statement'!G13="","",'Fin Statement'!G13/'Fin Statement'!G9) -> 0.30235556 | H13: =IF('Fin Statement'!H13="","",'Fin Statement'!H13/'Fin Statement'!H9) -> 0.31176258 | I13: =IF('Fin Statement'!I13="","",'Fin Statement'!I13/'Fin Statement'!I9) -> 0.32055907 | J13: =IF('Fin Statement'!J13="","",'Fin Statement'!J13/'Fin Statement'!J9) -> 0.344 | K13: =IF('Fin Statement'!K13="","",'Fin Statement'!K13/'Fin Statement'!K9) -> 0.344 | L13: =IF('Fin Statement'!L13="","",'Fin Statement'!L13/'Fin Statement'!L9) -> 0.342 | ... N13: =IF('Fin Statement'!N13="","",'Fin Statement'!N13/'Fin Statement'!N9) -> 0.338
B14: Gross margin | E14: =IF('Fin Statement'!E15="","",'Fin Statement'!E15/'Fin Statement'!E9) -> 0.68401674 | F14: =IF('Fin Statement'!F15="","",'Fin Statement'!F15/'Fin Statement'!F9) -> 0.68920086 | G14: =IF('Fin Statement'!G15="","",'Fin Statement'!G15/'Fin Statement'!G9) -> 0.69764444 | H14: =IF('Fin Statement'!H15="","",'Fin Statement'!H15/'Fin Statement'!H9) -> 0.68823742 | I14: =IF('Fin Statement'!I15="","",'Fin Statement'!I15/'Fin Statement'!I9) -> 0.67944093 | J14: =IF('Fin Statement'!J15="","",'Fin Statement'!J15/'Fin Statement'!J9) -> 0.656 | K14: =IF('Fin Statement'!K15="","",'Fin Statement'!K15/'Fin Statement'!K9) -> 0.656 | L14: =IF('Fin Statement'!L15="","",'Fin Statement'!L15/'Fin Statement'!L9) -> 0.658 | ... N14: =IF('Fin Statement'!N15="","",'Fin Statement'!N15/'Fin Statement'!N9) -> 0.662
B15: Research and development | E15: =IF('Fin Statement'!E17="","",'Fin Statement'!E17/'Fin Statement'!E9) -> 0.12362939 | F15: =IF('Fin Statement'!F17="","",'Fin Statement'!F17/'Fin Statement'!F9) -> 0.12832975 | G15: =IF('Fin Statement'!G17="","",'Fin Statement'!G17/'Fin Statement'!G9) -> 0.12038903 | H15: =IF('Fin Statement'!H17="","",'Fin Statement'!H17/'Fin Statement'!H9) -> 0.11531854 | I15: =IF('Fin Statement'!I17="","",'Fin Statement'!I17/'Fin Statement'!I9) -> 0.10716643 | J15: =IF('Fin Statement'!J17="","",'Fin Statement'!J17/'Fin Statement'!J9) -> 0.099 | K15: =IF('Fin Statement'!K17="","",'Fin Statement'!K17/'Fin Statement'!K9) -> 0.098 | L15: =IF('Fin Statement'!L17="","",'Fin Statement'!L17/'Fin Statement'!L9) -> 0.097 | ... N15: =IF('Fin Statement'!N17="","",'Fin Statement'!N17/'Fin Statement'!N9) -> 0.094
B16: Sales and marketing | E16: =IF('Fin Statement'!E18="","",'Fin Statement'!E18/'Fin Statement'!E9) -> 0.11007717 | F16: =IF('Fin Statement'!F18="","",'Fin Statement'!F18/'Fin Statement'!F9) -> 0.10739683 | G16: =IF('Fin Statement'!G18="","",'Fin Statement'!G18/'Fin Statement'!G9) -> 0.099770726 | H16: =IF('Fin Statement'!H18="","",'Fin Statement'!H18/'Fin Statement'!H9) -> 0.091060754 | I16: =IF('Fin Statement'!I18="","",'Fin Statement'!I18/'Fin Statement'!I9) -> 0.08049084 | J16: =IF('Fin Statement'!J18="","",'Fin Statement'!J18/'Fin Statement'!J9) -> 0.072 | K16: =IF('Fin Statement'!K18="","",'Fin Statement'!K18/'Fin Statement'!K9) -> 0.071 | L16: =IF('Fin Statement'!L18="","",'Fin Statement'!L18/'Fin Statement'!L9) -> 0.07 | ... N16: =IF('Fin Statement'!N18="","",'Fin Statement'!N18/'Fin Statement'!N9) -> 0.067
B17: General and administrative | E17: =IF('Fin Statement'!E19="","",'Fin Statement'!E19/'Fin Statement'!E9) -> 0.029757402 | F17: =IF('Fin Statement'!F19="","",'Fin Statement'!F19/'Fin Statement'!F9) -> 0.035745464 | G17: =IF('Fin Statement'!G19="","",'Fin Statement'!G19/'Fin Statement'!G9) -> 0.031041685 | H17: =IF('Fin Statement'!H19="","",'Fin Statement'!H19/'Fin Statement'!H9) -> 0.025638568 | I17: =IF('Fin Statement'!I19="","",'Fin Statement'!I19/'Fin Statement'!I9) -> 0.023975482 | J17: =IF('Fin Statement'!J19="","",'Fin Statement'!J19/'Fin Statement'!J9) -> 0.021 | K17: =IF('Fin Statement'!K19="","",'Fin Statement'!K19/'Fin Statement'!K9) -> 0.021 | L17: =IF('Fin Statement'!L19="","",'Fin Statement'!L19/'Fin Statement'!L9) -> 0.02 | ... N17: =IF('Fin Statement'!N19="","",'Fin Statement'!N19/'Fin Statement'!N9) -> 0.02
B18: EBITDA | E18: =IF('Fin Statement'!E20="","",'Fin Statement'!E20/'Fin Statement'!E9) -> 0.49348363 | F18: =IF('Fin Statement'!F20="","",'Fin Statement'!F20/'Fin Statement'!F9) -> 0.48313711 | G18: =IF('Fin Statement'!G20="","",'Fin Statement'!G20/'Fin Statement'!G9) -> 0.53194328 | H18: =IF('Fin Statement'!H20="","",'Fin Statement'!H20/'Fin Statement'!H9) -> 0.56069415 | I18: =IF('Fin Statement'!I20="","",'Fin Statement'!I20/'Fin Statement'!I9) -> 0.58393076 | J18: =IF('Fin Statement'!J20="","",'Fin Statement'!J20/'Fin Statement'!J9) -> 0.6016997 | K18: =IF('Fin Statement'!K20="","",'Fin Statement'!K20/'Fin Statement'!K9) -> 0.61229429 | L18: =IF('Fin Statement'!L20="","",'Fin Statement'!L20/'Fin Statement'!L9) -> 0.62335042 | ... N18: =IF('Fin Statement'!N20="","",'Fin Statement'!N20/'Fin Statement'!N9) -> 0.63853933
B19: Depreciation and Amortization | E19: =IF('Fin Statement'!E21="","",'Fin Statement'!E21/'Fin Statement'!E9) -> 0.072930852 | F19: =IF('Fin Statement'!F21="","",'Fin Statement'!F21/'Fin Statement'!F9) -> 0.0654083 | G19: =IF('Fin Statement'!G21="","",'Fin Statement'!G21/'Fin Statement'!G9) -> 0.085500281 | H19: =IF('Fin Statement'!H21="","",'Fin Statement'!H21/'Fin Statement'!H9) -> 0.10447459 | I19: =IF('Fin Statement'!I21="","",'Fin Statement'!I21/'Fin Statement'!I9) -> 0.11612258 | J19: =IF('Fin Statement'!J21="","",'Fin Statement'!J21/'Fin Statement'!J9) -> 0.1376997 | K19: =IF('Fin Statement'!K21="","",'Fin Statement'!K21/'Fin Statement'!K9) -> 0.14629429 | L19: =IF('Fin Statement'!L21="","",'Fin Statement'!L21/'Fin Statement'!L9) -> 0.15235042 | ... N19: =IF('Fin Statement'!N21="","",'Fin Statement'!N21/'Fin Statement'!N9) -> 0.15753933
B20: Operating income/EBIT | E20: =IF('Fin Statement'!E22="","",'Fin Statement'!E22/'Fin Statement'!E9) -> 0.42055278 | F20: =IF('Fin Statement'!F22="","",'Fin Statement'!F22/'Fin Statement'!F9) -> 0.41772881 | G20: =IF('Fin Statement'!G22="","",'Fin Statement'!G22/'Fin Statement'!G9) -> 0.446443 | H20: =IF('Fin Statement'!H22="","",'Fin Statement'!H22/'Fin Statement'!H9) -> 0.45621956 | I20: =IF('Fin Statement'!I22="","",'Fin Statement'!I22/'Fin Statement'!I9) -> 0.46780818 | J20: =IF('Fin Statement'!J22="","",'Fin Statement'!J22/'Fin Statement'!J9) -> 0.464 | K20: =IF('Fin Statement'!K22="","",'Fin Statement'!K22/'Fin Statement'!K9) -> 0.466 | L20: =IF('Fin Statement'!L22="","",'Fin Statement'!L22/'Fin Statement'!L9) -> 0.471 | ... N20: =IF('Fin Statement'!N22="","",'Fin Statement'!N22/'Fin Statement'!N9) -> 0.481
B21: Interest and dividends income | E21: =IFERROR('Fin Statement'!E23/'Fin Statement'!E9,"") -> 0.010561356 | F21: =IFERROR('Fin Statement'!F23/'Fin Statement'!F9,"") -> 0.014128306 | G21: =IFERROR('Fin Statement'!G23/'Fin Statement'!G9,"") -> 0.012879301 | H21: =IFERROR('Fin Statement'!H23/'Fin Statement'!H9,"") -> 0.0093957206 | I21: =IFERROR('Fin Statement'!I23/'Fin Statement'!I9,"") -> 0.0084071635 | J21: =IFERROR('Fin Statement'!J23/'Fin Statement'!J9,"") -> 0.0068956532 | K21: =IFERROR('Fin Statement'!K23/'Fin Statement'!K9,"") -> 0.0076414857 | L21: =IFERROR('Fin Statement'!L23/'Fin Statement'!L9,"") -> 0.0094695781 | ... N21: =IFERROR('Fin Statement'!N23/'Fin Statement'!N9,"") -> 0.01566584
B22: Interest expense | E22: =IFERROR('Fin Statement'!E24/'Fin Statement'!E9,"") -> -0.010405003 | F22: =IFERROR('Fin Statement'!F24/'Fin Statement'!F9,"") -> -0.0092867423 | G22: =IFERROR('Fin Statement'!G24/'Fin Statement'!G9,"") -> -0.011973629 | H22: =IFERROR('Fin Statement'!H24/'Fin Statement'!H9,"") -> -0.0084657324 | I22: =IFERROR('Fin Statement'!I24/'Fin Statement'!I9,"") -> -0.0091942177 | J22: =IFERROR('Fin Statement'!J24/'Fin Statement'!J9,"") -> -0.013253029 | K22: =IFERROR('Fin Statement'!K24/'Fin Statement'!K9,"") -> -0.011833131 | L22: =IFERROR('Fin Statement'!L24/'Fin Statement'!L9,"") -> -0.010647812 | ... N22: =IFERROR('Fin Statement'!N24/'Fin Statement'!N9,"") -> -0.0087910924
B23: Other non-operating items | E23: =IFERROR('Fin Statement'!E25/'Fin Statement'!E9,"") -> 0.0015231755 | F23: =IFERROR('Fin Statement'!F25/'Fin Statement'!F9,"") -> -0.0011230918 | G23: =IFERROR('Fin Statement'!G25/'Fin Statement'!G9,"") -> -0.007620695 | H23: =IFERROR('Fin Statement'!H25/'Fin Statement'!H9,"") -> -0.018326447 | I23: =IFERROR('Fin Statement'!I25/'Fin Statement'!I9,"") -> 0.033022566 | J23: =IFERROR('Fin Statement'!J25/'Fin Statement'!J9,"") -> 0 | K23: =IFERROR('Fin Statement'!K25/'Fin Statement'!K9,"") -> 0 | L23: =IFERROR('Fin Statement'!L25/'Fin Statement'!L9,"") -> 0 | ... N23: =IFERROR('Fin Statement'!N25/'Fin Statement'!N9,"") -> 0
B24: Other income (expense), net | E24: =IF('Fin Statement'!E26="","",'Fin Statement'!E26/'Fin Statement'!E9) -> 0.0016795279 | F24: =IF('Fin Statement'!F26="","",'Fin Statement'!F26/'Fin Statement'!F9) -> 0.003718472 | G24: =IF('Fin Statement'!G26="","",'Fin Statement'!G26/'Fin Statement'!G9) -> -0.0067150235 | H24: =IF('Fin Statement'!H26="","",'Fin Statement'!H26/'Fin Statement'!H9) -> -0.017396459 | I24: =IF('Fin Statement'!I26="","",'Fin Statement'!I26/'Fin Statement'!I9) -> 0.032235512 | J24: =IF('Fin Statement'!J26="","",'Fin Statement'!J26/'Fin Statement'!J9) -> -0.006357376 | K24: =IF('Fin Statement'!K26="","",'Fin Statement'!K26/'Fin Statement'!K9) -> -0.004191645 | L24: =IF('Fin Statement'!L26="","",'Fin Statement'!L26/'Fin Statement'!L9) -> -0.0011782344 | ... N24: =IF('Fin Statement'!N26="","",'Fin Statement'!N26/'Fin Statement'!N9) -> 0.0068747473
B25: EBT | E25: =IF('Fin Statement'!E27="","",'Fin Statement'!E27/'Fin Statement'!E9) -> 0.42223231 | F25: =IF('Fin Statement'!F27="","",'Fin Statement'!F27/'Fin Statement'!F9) -> 0.42144728 | G25: =IF('Fin Statement'!G27="","",'Fin Statement'!G27/'Fin Statement'!G9) -> 0.43972797 | H25: =IF('Fin Statement'!H27="","",'Fin Statement'!H27/'Fin Statement'!H9) -> 0.4388231 | I25: =IF('Fin Statement'!I27="","",'Fin Statement'!I27/'Fin Statement'!I9) -> 0.5000437 | J25: =IF('Fin Statement'!J27="","",'Fin Statement'!J27/'Fin Statement'!J9) -> 0.45764262 | K25: =IF('Fin Statement'!K27="","",'Fin Statement'!K27/'Fin Statement'!K9) -> 0.46180836 | L25: =IF('Fin Statement'!L27="","",'Fin Statement'!L27/'Fin Statement'!L9) -> 0.46982177 | ... N25: =IF('Fin Statement'!N27="","",'Fin Statement'!N27/'Fin Statement'!N9) -> 0.48787475
B26: Provision for income taxes/ Taxes | E26: =IF('Fin Statement'!E28="","",'Fin Statement'!E28/'Fin Statement'!E9) -> 0.055368941 | F26: =IF('Fin Statement'!F28="","",'Fin Statement'!F28/'Fin Statement'!F9) -> 0.0799849 | G26: =IF('Fin Statement'!G28="","",'Fin Statement'!G28/'Fin Statement'!G9) -> 0.080168243 | H26: =IF('Fin Statement'!H28="","",'Fin Statement'!H28/'Fin Statement'!H9) -> 0.077362951 | I26: =IF('Fin Statement'!I28="","",'Fin Statement'!I28/'Fin Statement'!I9) -> 0.096989805 | J26: =IF('Fin Statement'!J28="","",'Fin Statement'!J28/'Fin Statement'!J9) -> 0.091528525 | K26: =IF('Fin Statement'!K28="","",'Fin Statement'!K28/'Fin Statement'!K9) -> 0.092361671 | L26: =IF('Fin Statement'!L28="","",'Fin Statement'!L28/'Fin Statement'!L9) -> 0.093964353 | ... N26: =IF('Fin Statement'!N28="","",'Fin Statement'!N28/'Fin Statement'!N9) -> 0.097574949
B27: Net income | E27: =IF('Fin Statement'!E29="","",'Fin Statement'!E29/'Fin Statement'!E9) -> 0.36686337 | F27: =IF('Fin Statement'!F29="","",'Fin Statement'!F29/'Fin Statement'!F9) -> 0.34146238 | G27: =IF('Fin Statement'!G29="","",'Fin Statement'!G29/'Fin Statement'!G9) -> 0.35955973 | H27: =IF('Fin Statement'!H29="","",'Fin Statement'!H29/'Fin Statement'!H9) -> 0.36146015 | I27: =IF('Fin Statement'!I29="","",'Fin Statement'!I29/'Fin Statement'!I9) -> 0.40305389 | J27: =IF('Fin Statement'!J29="","",'Fin Statement'!J29/'Fin Statement'!J9) -> 0.3661141 | K27: =IF('Fin Statement'!K29="","",'Fin Statement'!K29/'Fin Statement'!K9) -> 0.36944668 | L27: =IF('Fin Statement'!L29="","",'Fin Statement'!L29/'Fin Statement'!L9) -> 0.37585741 | ... N27: =IF('Fin Statement'!N29="","",'Fin Statement'!N29/'Fin Statement'!N9) -> 0.3902998
B30: Reported Segment Results | E30: Historical | I30: Forecasted
B31: (% of segment total, except growth) | E31: =(2021+COLUMN()-COLUMN($D$5))&IF(COLUMN()-COLUMN($D$5)<5,"A","E") -> 2022A | F31: =(2021+COLUMN()-COLUMN($D$5))&IF(COLUMN()-COLUMN($D$5)<5,"A","E") -> 2023A | G31: =(2021+COLUMN()-COLUMN($D$5))&IF(COLUMN()-COLUMN($D$5)<5,"A","E") -> 2024A | H31: =(2021+COLUMN()-COLUMN($D$5))&IF(COLUMN()-COLUMN($D$5)<5,"A","E") -> 2025A | I31: 2026A | J31: =(2021+COLUMN()-COLUMN($D$5))&IF(COLUMN()-COLUMN($D$5)<5,"A","E") -> 2027E | K31: =(2021+COLUMN()-COLUMN($D$5))&IF(COLUMN()-COLUMN($D$5)<5,"A","E") -> 2028E | L31: =(2021+COLUMN()-COLUMN($D$5))&IF(COLUMN()-COLUMN($D$5)<5,"A","E") -> 2029E | M31: =(2021+COLUMN()-COLUMN($D$5))&IF(COLUMN()-COLUMN($D$5)<5,"A","E") -> 2030E | N31: =(2021+COLUMN()-COLUMN($D$5))&IF(COLUMN()-COLUMN($D$5)<5,"A","E") -> 2031E
B32: SEGMENT REVENUE
B33: Productivity and Business Processes | E33: =IF('Fin Statement'!E35="","",'Fin Statement'!E35/'Fin Statement'!E38) -> 0.31958441 | F33: =IF('Fin Statement'!F35="","",'Fin Statement'!F35/'Fin Statement'!F38) -> 0.44428662 | G33: =IF('Fin Statement'!G35="","",'Fin Statement'!G35/'Fin Statement'!G38) -> 0.435783 | H33: =IF('Fin Statement'!H35="","",'Fin Statement'!H35/'Fin Statement'!H38) -> 0.42882396 | I33: =IFERROR('Fin Statement'!I35/'Fin Statement'!I38,"") -> 0.42187928 | J33: =IF('Fin Statement'!J35="","",'Fin Statement'!J35/'Fin Statement'!J38) -> 0.40200986 | K33: =IF('Fin Statement'!K35="","",'Fin Statement'!K35/'Fin Statement'!K38) -> 0.38152617 | L33: =IF('Fin Statement'!L35="","",'Fin Statement'!L35/'Fin Statement'!L38) -> 0.36332303 | M33: =IF('Fin Statement'!M35="","",'Fin Statement'!M35/'Fin Statement'!M38) -> 0.34683677 | N33: =IF('Fin Statement'!N35="","",'Fin Statement'!N35/'Fin Statement'!N38) -> 0.33292
B34: Intelligent Cloud | E34: =IF('Fin Statement'!E36="","",'Fin Statement'!E36/'Fin Statement'!E38) -> 0.37809553 | F34: =IF('Fin Statement'!F36="","",'Fin Statement'!F36/'Fin Statement'!F38) -> 0.34421348 | G34: =IF('Fin Statement'!G36="","",'Fin Statement'!G36/'Fin Statement'!G38) -> 0.35681824 | H34: =IF('Fin Statement'!H36="","",'Fin Statement'!H36/'Fin Statement'!H38) -> 0.37719541 | I34: =IFERROR('Fin Statement'!I36/'Fin Statement'!I38,"") -> 0.4152345 | J34: =IF('Fin Statement'!J36="","",'Fin Statement'!J36/'Fin Statement'!J38) -> 0.46633481 | K34: =IF('Fin Statement'!K36="","",'Fin Statement'!K36/'Fin Statement'!K38) -> 0.50579835 | L34: =IF('Fin Statement'!L36="","",'Fin Statement'!L36/'Fin Statement'!L38) -> 0.53807736 | M34: =IF('Fin Statement'!M36="","",'Fin Statement'!M36/'Fin Statement'!M38) -> 0.56502752 | N34: =IF('Fin Statement'!N36="","",'Fin Statement'!N36/'Fin Statement'!N38) -> 0.58713756
B35: More Personal Computing | E35: =IF('Fin Statement'!E37="","",'Fin Statement'!E37/'Fin Statement'!E38) -> 0.30232007 | F35: =IF('Fin Statement'!F37="","",'Fin Statement'!F37/'Fin Statement'!F38) -> 0.21149989 | G35: =IF('Fin Statement'!G37="","",'Fin Statement'!G37/'Fin Statement'!G38) -> 0.20739876 | H35: =IF('Fin Statement'!H37="","",'Fin Statement'!H37/'Fin Statement'!H38) -> 0.19398063 | I35: =IFERROR('Fin Statement'!I37/'Fin Statement'!I38,"") -> 0.16288622 | J35: =IF('Fin Statement'!J37="","",'Fin Statement'!J37/'Fin Statement'!J38) -> 0.13165532 | K35: =IF('Fin Statement'!K37="","",'Fin Statement'!K37/'Fin Statement'!K38) -> 0.11267548 | L35: =IF('Fin Statement'!L37="","",'Fin Statement'!L37/'Fin Statement'!L38) -> 0.09859961 | M35: =IF('Fin Statement'!M37="","",'Fin Statement'!M37/'Fin Statement'!M38) -> 0.088135716 | N35: =IF('Fin Statement'!N37="","",'Fin Statement'!N37/'Fin Statement'!N38) -> 0.079942443
B36: Total segment revenue | E36: =IF('Fin Statement'!E38="","",'Fin Statement'!E38/'Fin Statement'!E38) -> 1 | F36: =IF('Fin Statement'!F38="","",'Fin Statement'!F38/'Fin Statement'!F38) -> 1 | G36: =IF('Fin Statement'!G38="","",'Fin Statement'!G38/'Fin Statement'!G38) -> 1 | H36: =IF('Fin Statement'!H38="","",'Fin Statement'!H38/'Fin Statement'!H38) -> 1 | I36: =IFERROR('Fin Statement'!I38/'Fin Statement'!I38,"") -> 1 | J36: =IF('Fin Statement'!J38="","",'Fin Statement'!J38/'Fin Statement'!J38) -> 1 | K36: =IF('Fin Statement'!K38="","",'Fin Statement'!K38/'Fin Statement'!K38) -> 1 | L36: =IF('Fin Statement'!L38="","",'Fin Statement'!L38/'Fin Statement'!L38) -> 1 | M36: =IF('Fin Statement'!M38="","",'Fin Statement'!M38/'Fin Statement'!M38) -> 1 | N36: =IF('Fin Statement'!N38="","",'Fin Statement'!N38/'Fin Statement'!N38) -> 1
B38: SEGMENT OPERATING INCOME
B39: Productivity and Business Processes | E39: =IF('Fin Statement'!E41="","",'Fin Statement'!E41/'Fin Statement'!E44) -> 0.35606778 | F39: =IF('Fin Statement'!F41="","",'Fin Statement'!F41/'Fin Statement'!F44) -> 0.5656609 | G39: =IF('Fin Statement'!G41="","",'Fin Statement'!G41/'Fin Statement'!G44) -> 0.5451829 | H39: =IF('Fin Statement'!H41="","",'Fin Statement'!H41/'Fin Statement'!H44) -> 0.54286226 | I39: =IFERROR('Fin Statement'!I41/'Fin Statement'!I44,"") -> 0.54032866 | J39: =IF('Fin Statement'!J41="","",'Fin Statement'!J41/'Fin Statement'!J44) -> 0.5138795 | K39: =IF('Fin Statement'!K41="","",'Fin Statement'!K41/'Fin Statement'!K44) -> 0.48874625 | L39: =IF('Fin Statement'!L41="","",'Fin Statement'!L41/'Fin Statement'!L44) -> 0.46673123 | M39: =IF('Fin Statement'!M41="","",'Fin Statement'!M41/'Fin Statement'!M44) -> 0.44700925 | N39: =IF('Fin Statement'!N41="","",'Fin Statement'!N41/'Fin Statement'!N44) -> 0.43034791
B40: Intelligent Cloud | E40: =IF('Fin Statement'!E42="","",'Fin Statement'!E42/'Fin Statement'!E44) -> 0.39819867 | F40: =IF('Fin Statement'!F42="","",'Fin Statement'!F42/'Fin Statement'!F44) -> 0.32094484 | G40: =IF('Fin Statement'!G42="","",'Fin Statement'!G42/'Fin Statement'!G44) -> 0.34553562 | H40: =IF('Fin Statement'!H42="","",'Fin Statement'!H42/'Fin Statement'!H44) -> 0.34692052 | I40: =IFERROR('Fin Statement'!I42/'Fin Statement'!I44,"") -> 0.36700014 | J40: =IF('Fin Statement'!J42="","",'Fin Statement'!J42/'Fin Statement'!J44) -> 0.41136319 | K40: =IF('Fin Statement'!K42="","",'Fin Statement'!K42/'Fin Statement'!K44) -> 0.44713587 | L40: =IF('Fin Statement'!L42="","",'Fin Statement'!L42/'Fin Statement'!L44) -> 0.47700358 | M40: =IF('Fin Statement'!M42="","",'Fin Statement'!M42/'Fin Statement'!M44) -> 0.50253229 | N40: =IF('Fin Statement'!N42="","",'Fin Statement'!N42/'Fin Statement'!N44) -> 0.52374836
B41: More Personal Computing | E41: =IF('Fin Statement'!E43="","",'Fin Statement'!E43/'Fin Statement'!E44) -> 0.24573354 | F41: =IF('Fin Statement'!F43="","",'Fin Statement'!F43/'Fin Statement'!F44) -> 0.11339426 | G41: =IF('Fin Statement'!G43="","",'Fin Statement'!G43/'Fin Statement'!G44) -> 0.10928148 | H41: =IF('Fin Statement'!H43="","",'Fin Statement'!H43/'Fin Statement'!H44) -> 0.11021723 | I41: =IFERROR('Fin Statement'!I43/'Fin Statement'!I44,"") -> 0.092671206 | J41: =IF('Fin Statement'!J43="","",'Fin Statement'!J43/'Fin Statement'!J44) -> 0.074757314 | K41: =IF('Fin Statement'!K43="","",'Fin Statement'!K43/'Fin Statement'!K44) -> 0.064117884 | L41: =IF('Fin Statement'!L43="","",'Fin Statement'!L43/'Fin Statement'!L44) -> 0.056265191 | M41: =IF('Fin Statement'!M43="","",'Fin Statement'!M43/'Fin Statement'!M44) -> 0.050458459 | N41: =IF('Fin Statement'!N43="","",'Fin Statement'!N43/'Fin Statement'!N44) -> 0.045903723
B42: Total segment operating income | E42: =IF('Fin Statement'!E44="","",'Fin Statement'!E44/'Fin Statement'!E44) -> 1 | F42: =IF('Fin Statement'!F44="","",'Fin Statement'!F44/'Fin Statement'!F44) -> 1 | G42: =IF('Fin Statement'!G44="","",'Fin Statement'!G44/'Fin Statement'!G44) -> 1 | H42: =IF('Fin Statement'!H44="","",'Fin Statement'!H44/'Fin Statement'!H44) -> 1 | I42: =IFERROR('Fin Statement'!I44/'Fin Statement'!I44,"") -> 1 | J42: =IF('Fin Statement'!J44="","",'Fin Statement'!J44/'Fin Statement'!J44) -> 1 | K42: =IF('Fin Statement'!K44="","",'Fin Statement'!K44/'Fin Statement'!K44) -> 1 | L42: =IF('Fin Statement'!L44="","",'Fin Statement'!L44/'Fin Statement'!L44) -> 1 | M42: =IF('Fin Statement'!M44="","",'Fin Statement'!M44/'Fin Statement'!M44) -> 1 | N42: =IF('Fin Statement'!N44="","",'Fin Statement'!N44/'Fin Statement'!N44) -> 1
B44: KEY CLOUD DISCLOSURE
B45: Azure revenue (minimum disclosed) | H45: >75,000
B46: Azure and other cloud services growth | F46: 0.29 | G46: 0.3
B47: Azure revenue growth | H47: 0.34
B50: Cash Flow Statement | E50: Historical | I50: Forecasted
B51: (% of revenue) | E51: =(2021+COLUMN()-COLUMN($D$5))&IF(COLUMN()-COLUMN($D$5)<5,"A","E") -> 2022A | F51: =(2021+COLUMN()-COLUMN($D$5))&IF(COLUMN()-COLUMN($D$5)<5,"A","E") -> 2023A | G51: =(2021+COLUMN()-COLUMN($D$5))&IF(COLUMN()-COLUMN($D$5)<5,"A","E") -> 2024A | H51: =(2021+COLUMN()-COLUMN($D$5))&IF(COLUMN()-COLUMN($D$5)<5,"A","E") -> 2025A | I51: 2026A | J51: =(2021+COLUMN()-COLUMN($D$5))&IF(COLUMN()-COLUMN($D$5)<5,"A","E") -> 2027E | K51: =(2021+COLUMN()-COLUMN($D$5))&IF(COLUMN()-COLUMN($D$5)<5,"A","E") -> 2028E | L51: =(2021+COLUMN()-COLUMN($D$5))&IF(COLUMN()-COLUMN($D$5)<5,"A","E") -> 2029E | M51: =(2021+COLUMN()-COLUMN($D$5))&IF(COLUMN()-COLUMN($D$5)<5,"A","E") -> 2030E | N51: =(2021+COLUMN()-COLUMN($D$5))&IF(COLUMN()-COLUMN($D$5)<5,"A","E") -> 2031E
B52: Operations
B53: Net income | E53: =IF('Fin Statement'!E55="","",'Fin Statement'!E55/'Fin Statement'!E9) -> 0.36686337 | F53: =IF('Fin Statement'!F55="","",'Fin Statement'!F55/'Fin Statement'!F9) -> 0.34146238 | G53: =IF('Fin Statement'!G55="","",'Fin Statement'!G55/'Fin Statement'!G9) -> 0.35955973 | H53: =IF('Fin Statement'!H55="","",'Fin Statement'!H55/'Fin Statement'!H9) -> 0.36146015 | I53: =IF('Fin Statement'!I55="","",'Fin Statement'!I55/'Fin Statement'!I9) -> 0.40305389 | J53: =IF('Fin Statement'!J55="","",'Fin Statement'!J55/'Fin Statement'!J9) -> 0.3661141 | K53: =IF('Fin Statement'!K55="","",'Fin Statement'!K55/'Fin Statement'!K9) -> 0.36944668 | L53: =IF('Fin Statement'!L55="","",'Fin Statement'!L55/'Fin Statement'!L9) -> 0.37585741 | ... N53: =IF('Fin Statement'!N55="","",'Fin Statement'!N55/'Fin Statement'!N9) -> 0.3902998
B54: Adjustments for Non-cash Operation
B55: Depreciation, amortization, and other | E55: =IF('Fin Statement'!E57="","",'Fin Statement'!E57/'Fin Statement'!E9) -> 0.072930852 | F55: =IF('Fin Statement'!F57="","",'Fin Statement'!F57/'Fin Statement'!F9) -> 0.0654083 | G55: =IF('Fin Statement'!G57="","",'Fin Statement'!G57/'Fin Statement'!G9) -> 0.085500281 | H55: =IF('Fin Statement'!H57="","",'Fin Statement'!H57/'Fin Statement'!H9) -> 0.10447459 | I55: =IF('Fin Statement'!I57="","",'Fin Statement'!I57/'Fin Statement'!I9) -> 0.11612258 | J55: =IF('Fin Statement'!J57="","",'Fin Statement'!J57/'Fin Statement'!J9) -> 0.1376997 | K55: =IF('Fin Statement'!K57="","",'Fin Statement'!K57/'Fin Statement'!K9) -> 0.14629429 | L55: =IF('Fin Statement'!L57="","",'Fin Statement'!L57/'Fin Statement'!L9) -> 0.15235042 | ... N55: =IF('Fin Statement'!N57="","",'Fin Statement'!N57/'Fin Statement'!N9) -> 0.15753933
B56: Stock-based compensation expense | E56: =IF('Fin Statement'!E58="","",'Fin Statement'!E58/'Fin Statement'!E9) -> 0.037837293 | F56: =IF('Fin Statement'!F58="","",'Fin Statement'!F58/'Fin Statement'!F9) -> 0.04535309 | G56: =IF('Fin Statement'!G58="","",'Fin Statement'!G58/'Fin Statement'!G9) -> 0.043790439 | H56: =IF('Fin Statement'!H58="","",'Fin Statement'!H58/'Fin Statement'!H9) -> 0.042502591 | I56: =IF('Fin Statement'!I58="","",'Fin Statement'!I58/'Fin Statement'!I9) -> 0.037382586 | J56: =IF('Fin Statement'!J58="","",'Fin Statement'!J58/'Fin Statement'!J9) -> 0.037 | K56: =IF('Fin Statement'!K58="","",'Fin Statement'!K58/'Fin Statement'!K9) -> 0.036 | L56: =IF('Fin Statement'!L58="","",'Fin Statement'!L58/'Fin Statement'!L9) -> 0.035 | ... N56: =IF('Fin Statement'!N58="","",'Fin Statement'!N58/'Fin Statement'!N9) -> 0.033
B57: Net recognized losses (gains) on investments and derivatives | E57: =IF('Fin Statement'!E59="","",'Fin Statement'!E59/'Fin Statement'!E9) -> -0.0020628436 | F57: =IF('Fin Statement'!F59="","",'Fin Statement'!F59/'Fin Statement'!F9) -> 0.00092489913 | G57: =IF('Fin Statement'!G59="","",'Fin Statement'!G59/'Fin Statement'!G9) -> 0.0066660683 | H57: =IF('Fin Statement'!H59="","",'Fin Statement'!H59/'Fin Statement'!H9) -> 0.018915676 | I57: =IF('Fin Statement'!I59="","",'Fin Statement'!I59/'Fin Statement'!I9) -> -0.03329024 | J57: =IF('Fin Statement'!J59="","",'Fin Statement'!J59/'Fin Statement'!J9) -> 0 | K57: =IF('Fin Statement'!K59="","",'Fin Statement'!K59/'Fin Statement'!K9) -> 0 | L57: =IF('Fin Statement'!L59="","",'Fin Statement'!L59/'Fin Statement'!L9) -> 0 | ... N57: =IF('Fin Statement'!N59="","",'Fin Statement'!N59/'Fin Statement'!N9) -> 0
B58: Deferred income taxes | E58: =IF('Fin Statement'!E60="","",'Fin Statement'!E60/'Fin Statement'!E9) -> -0.028758763 | F58: =IF('Fin Statement'!F60="","",'Fin Statement'!F60/'Fin Statement'!F9) -> -0.028591652 | G58: =IF('Fin Statement'!G60="","",'Fin Statement'!G60/'Fin Statement'!G9) -> -0.01932915 | H58: =IF('Fin Statement'!H60="","",'Fin Statement'!H60/'Fin Statement'!H9) -> -0.025045789 | I58: =IF('Fin Statement'!I60="","",'Fin Statement'!I60/'Fin Statement'!I9) -> 0.042758687 | J58: =IF('Fin Statement'!J60="","",'Fin Statement'!J60/'Fin Statement'!J9) -> 0 | K58: =IF('Fin Statement'!K60="","",'Fin Statement'!K60/'Fin Statement'!K9) -> 0 | L58: =IF('Fin Statement'!L60="","",'Fin Statement'!L60/'Fin Statement'!L9) -> 0 | ... N58: =IF('Fin Statement'!N60="","",'Fin Statement'!N60/'Fin Statement'!N9) -> 0
B59: Other non-cash adjustments | E59: =IF('Fin Statement'!E61="","",'Fin Statement'!E61/'Fin Statement'!E9) -> -0.030821607 | F59: =IF('Fin Statement'!F61="","",'Fin Statement'!F61/'Fin Statement'!F9) -> -0.027666753 | G59: =IF('Fin Statement'!G61="","",'Fin Statement'!G61/'Fin Statement'!G9) -> -0.012663082 | H59: =IF('Fin Statement'!H61="","",'Fin Statement'!H61/'Fin Statement'!H9) -> -0.0061301132 | I59: =IF('Fin Statement'!I61="","",'Fin Statement'!I61/'Fin Statement'!I9) -> 0.009468447 | J59: =IF('Fin Statement'!J61="","",'Fin Statement'!J61/'Fin Statement'!J9) -> 0 | K59: =IF('Fin Statement'!K61="","",'Fin Statement'!K61/'Fin Statement'!K9) -> 0 | L59: =IF('Fin Statement'!L61="","",'Fin Statement'!L61/'Fin Statement'!L9) -> 0 | ... N59: =IF('Fin Statement'!N61="","",'Fin Statement'!N61/'Fin Statement'!N9) -> 0
B60: Changes in operating assets and liabilities:
B61: Accounts receivable | E61: =IF('Fin Statement'!E63="","",'Fin Statement'!E63/'Fin Statement'!E9) -> -0.034468149 | F61: =IF('Fin Statement'!F63="","",'Fin Statement'!F63/'Fin Statement'!F9) -> -0.019286034 | G61: =IF('Fin Statement'!G63="","",'Fin Statement'!G63/'Fin Statement'!G9) -> -0.029336412 | H61: =IF('Fin Statement'!H63="","",'Fin Statement'!H63/'Fin Statement'!H9) -> -0.037558036 | I61: =IF('Fin Statement'!I63="","",'Fin Statement'!I63/'Fin Statement'!I9) -> -0.038383071 | J61: =IF('Fin Statement'!J63="","",'Fin Statement'!J63/'Fin Statement'!J9) -> -0.036476698 | K61: =IF('Fin Statement'!K63="","",'Fin Statement'!K63/'Fin Statement'!K9) -> -0.037218286 | L61: =IF('Fin Statement'!L63="","",'Fin Statement'!L63/'Fin Statement'!L9) -> -0.031905003 | ... N61: =IF('Fin Statement'!N63="","",'Fin Statement'!N63/'Fin Statement'!N9) -> -0.026042442
B62: Inventories | E62: =IF('Fin Statement'!E64="","",'Fin Statement'!E64/'Fin Statement'!E9) -> -0.0056639935 | F62: =IF('Fin Statement'!F64="","",'Fin Statement'!F64/'Fin Statement'!F9) -> 0.0058608404 | G62: =IF('Fin Statement'!G64="","",'Fin Statement'!G64/'Fin Statement'!G9) -> 0.0052382079 | H62: =IF('Fin Statement'!H64="","",'Fin Statement'!H64/'Fin Statement'!H9) -> 0.0010968182 | I62: =IF('Fin Statement'!I64="","",'Fin Statement'!I64/'Fin Statement'!I9) -> -0.0013892279 | J62: =IF('Fin Statement'!J64="","",'Fin Statement'!J64/'Fin Statement'!J9) -> -0.0011305442 | K62: =IF('Fin Statement'!K64="","",'Fin Statement'!K64/'Fin Statement'!K9) -> -0.00071927475 | L62: =IF('Fin Statement'!L64="","",'Fin Statement'!L64/'Fin Statement'!L9) -> -0.00064214132 | ... N62: =IF('Fin Statement'!N64="","",'Fin Statement'!N64/'Fin Statement'!N9) -> -0.0005286219
B63: Other current assets | E63: =IF('Fin Statement'!E65="","",'Fin Statement'!E65/'Fin Statement'!E9) -> -0.0035759318 | F63: =IF('Fin Statement'!F65="","",'Fin Statement'!F65/'Fin Statement'!F9) -> -0.0093952764 | G63: =IF('Fin Statement'!G65="","",'Fin Statement'!G65/'Fin Statement'!G9) -> -0.0067231827 | H63: =IF('Fin Statement'!H65="","",'Fin Statement'!H65/'Fin Statement'!H9) -> -0.010804901 | I63: =IF('Fin Statement'!I65="","",'Fin Statement'!I65/'Fin Statement'!I9) -> -0.0079164896 | J63: =IF('Fin Statement'!J65="","",'Fin Statement'!J65/'Fin Statement'!J9) | K63: =IF('Fin Statement'!K65="","",'Fin Statement'!K65/'Fin Statement'!K9) | L63: =IF('Fin Statement'!L65="","",'Fin Statement'!L65/'Fin Statement'!L9) | ... N63: =IF('Fin Statement'!N65="","",'Fin Statement'!N65/'Fin Statement'!N9)
B64: Other long-term assets | E64: =IF('Fin Statement'!E66="","",'Fin Statement'!E66/'Fin Statement'!E9) -> -0.014147375 | F64: =IF('Fin Statement'!F66="","",'Fin Statement'!F66/'Fin Statement'!F9) -> -0.013368568 | G64: =IF('Fin Statement'!G66="","",'Fin Statement'!G66/'Fin Statement'!G9) -> -0.027810641 | H64: =IF('Fin Statement'!H66="","",'Fin Statement'!H66/'Fin Statement'!H9) -> -0.010471241 | I64: =IF('Fin Statement'!I66="","",'Fin Statement'!I66/'Fin Statement'!I9) -> -0.011945552 | J64: =IF('Fin Statement'!J66="","",'Fin Statement'!J66/'Fin Statement'!J9) | K64: =IF('Fin Statement'!K66="","",'Fin Statement'!K66/'Fin Statement'!K9) | L64: =IF('Fin Statement'!L66="","",'Fin Statement'!L66/'Fin Statement'!L9) | ... N64: =IF('Fin Statement'!N66="","",'Fin Statement'!N66/'Fin Statement'!N9)
B65: Other operating assets | E65: =IF('Fin Statement'!E67="","",'Fin Statement'!E67/'Fin Statement'!E9) -> -0.017723307 | F65: =IF('Fin Statement'!F67="","",'Fin Statement'!F67/'Fin Statement'!F9) -> -0.022763844 | G65: =IF('Fin Statement'!G67="","",'Fin Statement'!G67/'Fin Statement'!G9) -> -0.034533824 | H65: =IF('Fin Statement'!H67="","",'Fin Statement'!H67/'Fin Statement'!H9) -> -0.021276143 | I65: =IF('Fin Statement'!I67="","",'Fin Statement'!I67/'Fin Statement'!I9) -> -0.019862042 | J65: =IF('Fin Statement'!J67="","",'Fin Statement'!J67/'Fin Statement'!J9) -> 0.0017403649 | K65: =IF('Fin Statement'!K67="","",'Fin Statement'!K67/'Fin Statement'!K9) -> 0.0018043083 | L65: =IF('Fin Statement'!L67="","",'Fin Statement'!L67/'Fin Statement'!L9) -> 0.0017617529 | ... N65: =IF('Fin Statement'!N67="","",'Fin Statement'!N67/'Fin Statement'!N9) -> 0.0015646262
B66: Accounts payable | E66: =IF('Fin Statement'!E68="","",'Fin Statement'!E68/'Fin Statement'!E9) -> 0.014843395 | F66: =IF('Fin Statement'!F68="","",'Fin Statement'!F68/'Fin Statement'!F9) -> -0.012840054 | G66: =IF('Fin Statement'!G68="","",'Fin Statement'!G68/'Fin Statement'!G9) -> 0.014462186 | H66: =IF('Fin Statement'!H68="","",'Fin Statement'!H68/'Fin Statement'!H9) -> 0.0020197072 | I66: =IF('Fin Statement'!I68="","",'Fin Statement'!I68/'Fin Statement'!I9) -> 0.015875168 | J66: =IF('Fin Statement'!J68="","",'Fin Statement'!J68/'Fin Statement'!J9) -> 0.023194329 | K66: =IF('Fin Statement'!K68="","",'Fin Statement'!K68/'Fin Statement'!K9) -> 0.015427364 | L66: =IF('Fin Statement'!L68="","",'Fin Statement'!L68/'Fin Statement'!L9) -> 0.012652884 | ... N66: =IF('Fin Statement'!N68="","",'Fin Statement'!N68/'Fin Statement'!N9) -> 0.0085854105
B67: Deferred Revenue (Unearned revenue) | E67: =IF('Fin Statement'!E69="","",'Fin Statement'!E69/'Fin Statement'!E9) -> 0.025767892 | F67: =IF('Fin Statement'!F69="","",'Fin Statement'!F69/'Fin Statement'!F9) -> 0.026118963 | G67: =IF('Fin Statement'!G69="","",'Fin Statement'!G69/'Fin Statement'!G9) -> 0.021817707 | H67: =IF('Fin Statement'!H69="","",'Fin Statement'!H69/'Fin Statement'!H9) -> 0.01930258 | I67: =IF('Fin Statement'!I69="","",'Fin Statement'!I69/'Fin Statement'!I9) -> 0.028209463 | J67: =IF('Fin Statement'!J69="","",'Fin Statement'!J69/'Fin Statement'!J9) -> 0.025881121 | K67: =IF('Fin Statement'!K69="","",'Fin Statement'!K69/'Fin Statement'!K9) -> 0.033580094 | L67: =IF('Fin Statement'!L69="","",'Fin Statement'!L69/'Fin Statement'!L9) -> 0.031258109 | ... N67: =IF('Fin Statement'!N69="","",'Fin Statement'!N69/'Fin Statement'!N9) -> 0.026263729
B68: Income taxes | E68: =IF('Fin Statement'!E70="","",'Fin Statement'!E70/'Fin Statement'!E9) -> 0.0035103647 | F68: =IF('Fin Statement'!F70="","",'Fin Statement'!F70/'Fin Statement'!F9) -> -0.0016893566 | G68: =IF('Fin Statement'!G70="","",'Fin Statement'!G70/'Fin Statement'!G9) -> 0.0068822872 | H68: =IF('Fin Statement'!H70="","",'Fin Statement'!H70/'Fin Statement'!H9) -> -0.00013488379 | I68: =IF('Fin Statement'!I70="","",'Fin Statement'!I70/'Fin Statement'!I9) -> -0.0056503304 | J68: =IF('Fin Statement'!J70="","",'Fin Statement'!J70/'Fin Statement'!J9) -> 0.0011392811 | K68: =IF('Fin Statement'!K70="","",'Fin Statement'!K70/'Fin Statement'!K9) -> 0.0011655701 | L68: =IF('Fin Statement'!L70="","",'Fin Statement'!L70/'Fin Statement'!L9) -> 0.0010849737 | ... N68: =IF('Fin Statement'!N70="","",'Fin Statement'!N70/'Fin Statement'!N9) -> 0.00091161799
B69: Other current liabilities | E69: =IF('Fin Statement'!E71="","",'Fin Statement'!E71/'Fin Statement'!E9) -> 0.011822263 | F69: =IF('Fin Statement'!F71="","",'Fin Statement'!F71/'Fin Statement'!F9) -> 0.01072128 | G69: =IF('Fin Statement'!G71="","",'Fin Statement'!G71/'Fin Statement'!G9) -> 0.019855419 | H69: =IF('Fin Statement'!H71="","",'Fin Statement'!H71/'Fin Statement'!H9) -> 0.021020573 | I69: =IF('Fin Statement'!I71="","",'Fin Statement'!I71/'Fin Statement'!I9) -> 0.0206335 | J69: =IF('Fin Statement'!J71="","",'Fin Statement'!J71/'Fin Statement'!J9) | K69: =IF('Fin Statement'!K71="","",'Fin Statement'!K71/'Fin Statement'!K9) | L69: =IF('Fin Statement'!L71="","",'Fin Statement'!L71/'Fin Statement'!L9) | ... N69: =IF('Fin Statement'!N71="","",'Fin Statement'!N71/'Fin Statement'!N9)
B70: Other long-term liabilities | E70: =IF('Fin Statement'!E72="","",'Fin Statement'!E72/'Fin Statement'!E9) -> 0.0041609926 | F70: =IF('Fin Statement'!F72="","",'Fin Statement'!F72/'Fin Statement'!F9) -> 0.0026095368 | G70: =IF('Fin Statement'!G72="","",'Fin Statement'!G72/'Fin Statement'!G9) -> 0.0030556213 | H70: =IF('Fin Statement'!H72="","",'Fin Statement'!H72/'Fin Statement'!H9) -> -0.003460834 | I70: =IF('Fin Statement'!I72="","",'Fin Statement'!I72/'Fin Statement'!I9) -> -0.01418459 | J70: =IF('Fin Statement'!J72="","",'Fin Statement'!J72/'Fin Statement'!J9) | K70: =IF('Fin Statement'!K72="","",'Fin Statement'!K72/'Fin Statement'!K9) | L70: =IF('Fin Statement'!L72="","",'Fin Statement'!L72/'Fin Statement'!L9) | ... N70: =IF('Fin Statement'!N72="","",'Fin Statement'!N72/'Fin Statement'!N9)
B71: Other operating liabilities | E71: =IF('Fin Statement'!E73="","",'Fin Statement'!E73/'Fin Statement'!E9) -> 0.015983255 | F71: =IF('Fin Statement'!F73="","",'Fin Statement'!F73/'Fin Statement'!F9) -> 0.013330817 | G71: =IF('Fin Statement'!G73="","",'Fin Statement'!G73/'Fin Statement'!G9) -> 0.02291104 | H71: =IF('Fin Statement'!H73="","",'Fin Statement'!H73/'Fin Statement'!H9) -> 0.017559739 | I71: =IF('Fin Statement'!I73="","",'Fin Statement'!I73/'Fin Statement'!I9) -> 0.0064489105 | J71: =IF('Fin Statement'!J73="","",'Fin Statement'!J73/'Fin Statement'!J9) -> 0.014387133 | K71: =IF('Fin Statement'!K73="","",'Fin Statement'!K73/'Fin Statement'!K9) -> 0.014719118 | L71: =IF('Fin Statement'!L73="","",'Fin Statement'!L73/'Fin Statement'!L9) -> 0.013701325 | ... N71: =IF('Fin Statement'!N73="","",'Fin Statement'!N73/'Fin Statement'!N9) -> 0.011512145
B72: Net cash from operations | E72: =IF('Fin Statement'!E74="","",'Fin Statement'!E74/'Fin Statement'!E9) -> 0.44905936 | F72: =IF('Fin Statement'!F74="","",'Fin Statement'!F74/'Fin Statement'!F9) -> 0.41328835 | G72: =IF('Fin Statement'!G74="","",'Fin Statement'!G74/'Fin Statement'!G9) -> 0.48362856 | H72: =IF('Fin Statement'!H74="","",'Fin Statement'!H74/'Fin Statement'!H9) -> 0.48331701 | I72: =IF('Fin Statement'!I74="","",'Fin Statement'!I74/'Fin Statement'!I9) -> 0.55127637 | J72: =IF('Fin Statement'!J74="","",'Fin Statement'!J74/'Fin Statement'!J9) -> 0.56954878 | K72: =IF('Fin Statement'!K74="","",'Fin Statement'!K74/'Fin Statement'!K9) -> 0.58049986 | L72: =IF('Fin Statement'!L74="","",'Fin Statement'!L74/'Fin Statement'!L9) -> 0.59111973 | ... N72: =IF('Fin Statement'!N74="","",'Fin Statement'!N74/'Fin Statement'!N9) -> 0.6031056
B73: Financing
B74: Net debt issuance/(repayment) | E74: =IF('Fin Statement'!E76="","",'Fin Statement'!E76/'Fin Statement'!E9) -> -0.04550865 | F74: =IF('Fin Statement'!F76="","",'Fin Statement'!F76/'Fin Statement'!F9) -> -0.012976901 | G74: =IF('Fin Statement'!G76="","",'Fin Statement'!G76/'Fin Statement'!G9) -> 0.0023457707 | H74: =IF('Fin Statement'!H76="","",'Fin Statement'!H76/'Fin Statement'!H9) -> -0.031811276 | I74: =IF('Fin Statement'!I76="","",'Fin Statement'!I76/'Fin Statement'!I9) -> -0.0090405287 | J74: =IF('Fin Statement'!J76="","",'Fin Statement'!J76/'Fin Statement'!J9) -> -0.0056406056 | K74: =IF('Fin Statement'!K76="","",'Fin Statement'!K76/'Fin Statement'!K9) -> -0.0065176932 | L74: =IF('Fin Statement'!L76="","",'Fin Statement'!L76/'Fin Statement'!L9) -> -0.0024230458 | ... N74: =IF('Fin Statement'!N76="","",'Fin Statement'!N76/'Fin Statement'!N9) -> -0.0028488924
B75: Net share issuance/(repurchase) | E75: =IF('Fin Statement'!E77="","",'Fin Statement'!E77/'Fin Statement'!E9) -> -0.15562112 | F75: =IF('Fin Statement'!F77="","",'Fin Statement'!F77/'Fin Statement'!F9) -> -0.096165916 | G75: =IF('Fin Statement'!G77="","",'Fin Statement'!G77/'Fin Statement'!G9) -> -0.062222077 | H75: =IF('Fin Statement'!H77="","",'Fin Statement'!H77/'Fin Statement'!H9) -> -0.058085218 | I75: =IF('Fin Statement'!I77="","",'Fin Statement'!I77/'Fin Statement'!I9) -> -0.061059731 | J75: =IF('Fin Statement'!J77="","",'Fin Statement'!J77/'Fin Statement'!J9) -> -0.056406056 | K75: =IF('Fin Statement'!K77="","",'Fin Statement'!K77/'Fin Statement'!K9) -> -0.052141546 | L75: =IF('Fin Statement'!L77="","",'Fin Statement'!L77/'Fin Statement'!L9) -> -0.048460917 | ... N75: =IF('Fin Statement'!N77="","",'Fin Statement'!N77/'Fin Statement'!N9) -> -0.042733386
B76: Common stock cash dividends paid | E76: =IF('Fin Statement'!E78="","",'Fin Statement'!E78/'Fin Statement'!E9) -> -0.091466182 | F76: =IF('Fin Statement'!F78="","",'Fin Statement'!F78/'Fin Statement'!F9) -> -0.093433688 | G76: =IF('Fin Statement'!G78="","",'Fin Statement'!G78/'Fin Statement'!G9) -> -0.088816997 | H76: =IF('Fin Statement'!H78="","",'Fin Statement'!H78/'Fin Statement'!H9) -> -0.085480825 | I76: =IF('Fin Statement'!I78="","",'Fin Statement'!I78/'Fin Statement'!I9) -> -0.07969226 | J76: =IF('Fin Statement'!J78="","",'Fin Statement'!J78/'Fin Statement'!J9) -> -0.07322282 | K76: =IF('Fin Statement'!K78="","",'Fin Statement'!K78/'Fin Statement'!K9) -> -0.073889337 | L76: =IF('Fin Statement'!L78="","",'Fin Statement'!L78/'Fin Statement'!L9) -> -0.075171483 | ... N76: =IF('Fin Statement'!N78="","",'Fin Statement'!N78/'Fin Statement'!N9) -> -0.07805996
B77: Other, net | E77: =IF('Fin Statement'!E79="","",'Fin Statement'!E79/'Fin Statement'!E9) -> -0.0043526504 | F77: =IF('Fin Statement'!F79="","",'Fin Statement'!F79/'Fin Statement'!F9) -> -0.0047471864 | G77: =IF('Fin Statement'!G79="","",'Fin Statement'!G79/'Fin Statement'!G9) -> -0.0053401979 | H77: =IF('Fin Statement'!H79="","",'Fin Statement'!H79/'Fin Statement'!H9) -> -0.0081320725 | I77: =IF('Fin Statement'!I79="","",'Fin Statement'!I79/'Fin Statement'!I9) -> -0.0085553537 | J77: =IF('Fin Statement'!J79="","",'Fin Statement'!J79/'Fin Statement'!J9) -> -0.014228428 | K77: =IF('Fin Statement'!K79="","",'Fin Statement'!K79/'Fin Statement'!K9) -> -0.013767631 | L77: =IF('Fin Statement'!L79="","",'Fin Statement'!L79/'Fin Statement'!L9) -> -0.013157055 | ... N77: =IF('Fin Statement'!N79="","",'Fin Statement'!N79/'Fin Statement'!N9) -> -0.011861814
B78: Net cash used in financing | E78: =IF('Fin Statement'!E80="","",'Fin Statement'!E80/'Fin Statement'!E9) -> -0.29694861 | F78: =IF('Fin Statement'!F80="","",'Fin Statement'!F80/'Fin Statement'!F9) -> -0.20732369 | G78: =IF('Fin Statement'!G80="","",'Fin Statement'!G80/'Fin Statement'!G9) -> -0.1540335 | H78: =IF('Fin Statement'!H80="","",'Fin Statement'!H80/'Fin Statement'!H9) -> -0.18350939 | I78: =IF('Fin Statement'!I80="","",'Fin Statement'!I80/'Fin Statement'!I9) -> -0.15834787 | J78: =IF('Fin Statement'!J80="","",'Fin Statement'!J80/'Fin Statement'!J9) -> -0.14949791 | K78: =IF('Fin Statement'!K80="","",'Fin Statement'!K80/'Fin Statement'!K9) -> -0.14631621 | L78: =IF('Fin Statement'!L80="","",'Fin Statement'!L80/'Fin Statement'!L9) -> -0.1392125 | ... N78: =IF('Fin Statement'!N80="","",'Fin Statement'!N80/'Fin Statement'!N9) -> -0.13550405
B79: Investing
B80: Capex | E80: =IF('Fin Statement'!E82="","",'Fin Statement'!E82/'Fin Statement'!E9) -> -0.12047208 | F80: =IF('Fin Statement'!F82="","",'Fin Statement'!F82/'Fin Statement'!F9) -> -0.13263337 | G80: =IF('Fin Statement'!G82="","",'Fin Statement'!G82/'Fin Statement'!G9) -> -0.18144842 | H80: =IF('Fin Statement'!H82="","",'Fin Statement'!H82/'Fin Statement'!H9) -> -0.22912851 | I80: =IF('Fin Statement'!I82="","",'Fin Statement'!I82/'Fin Statement'!I9) -> -0.34941041 | J80: =IF('Fin Statement'!J82="","",'Fin Statement'!J82/'Fin Statement'!J9) -> -0.35894763 | K80: =IF('Fin Statement'!K82="","",'Fin Statement'!K82/'Fin Statement'!K9) -> -0.33674748 | L80: =IF('Fin Statement'!L82="","",'Fin Statement'!L82/'Fin Statement'!L9) -> -0.31685984 | ... N80: =IF('Fin Statement'!N82="","",'Fin Statement'!N82/'Fin Statement'!N9) -> -0.28488924
B81: Acquisition of companies, net of cash acquired and divestitures, and purchases of intangible and other assets | E81: =IF('Fin Statement'!E83="","",'Fin Statement'!E83/'Fin Statement'!E9) -> -0.11115146 | F81: =IF('Fin Statement'!F83="","",'Fin Statement'!F83/'Fin Statement'!F9) -> -0.0078805181 | G81: =IF('Fin Statement'!G83="","",'Fin Statement'!G83/'Fin Statement'!G9) -> -0.28203099 | H81: =IF('Fin Statement'!H83="","",'Fin Statement'!H83/'Fin Statement'!H9) -> -0.021219349 | I81: =IF('Fin Statement'!I83="","",'Fin Statement'!I83/'Fin Statement'!I9) -> -0.0052525472 | J81: =IF('Fin Statement'!J83="","",'Fin Statement'!J83/'Fin Statement'!J9) -> 0 | K81: =IF('Fin Statement'!K83="","",'Fin Statement'!K83/'Fin Statement'!K9) -> 0 | L81: =IF('Fin Statement'!L83="","",'Fin Statement'!L83/'Fin Statement'!L9) -> 0 | ... N81: =IF('Fin Statement'!N83="","",'Fin Statement'!N83/'Fin Statement'!N9) -> 0
B82: Net investment activity | E82: =IF('Fin Statement'!E84="","",'Fin Statement'!E84/'Fin Statement'!E9) -> 0.092994402 | F82: =IF('Fin Statement'!F84="","",'Fin Statement'!F84/'Fin Statement'!F9) -> 0.048193851 | G82: =IF('Fin Statement'!G84="","",'Fin Statement'!G84/'Fin Statement'!G9) -> 0.073175806 | H82: =IF('Fin Statement'!H84="","",'Fin Statement'!H84/'Fin Statement'!H9) -> -0.015571978 | I82: =IF('Fin Statement'!I84="","",'Fin Statement'!I84/'Fin Statement'!I9) -> -0.0058703166 | J82: =IF('Fin Statement'!J84="","",'Fin Statement'!J84/'Fin Statement'!J9) -> -0.0071227927 | K82: =IF('Fin Statement'!K84="","",'Fin Statement'!K84/'Fin Statement'!K9) -> -0.023292335 | L82: =IF('Fin Statement'!L84="","",'Fin Statement'!L84/'Fin Statement'!L9) -> -0.021654485 | ... N82: =IF('Fin Statement'!N84="","",'Fin Statement'!N84/'Fin Statement'!N9) -> -0.018171183
B83: Other, net | E83: =IF('Fin Statement'!E85="","",'Fin Statement'!E85/'Fin Statement'!E9) -> -0.014248247 | F83: =IF('Fin Statement'!F85="","",'Fin Statement'!F85/'Fin Statement'!F9) -> -0.014704009 | G83: =IF('Fin Statement'!G85="","",'Fin Statement'!G85/'Fin Statement'!G9) -> -0.0052953223 | H83: =IF('Fin Statement'!H85="","",'Fin Statement'!H85/'Fin Statement'!H9) -> 0.0082243614 | I83: =IF('Fin Statement'!I85="","",'Fin Statement'!I85/'Fin Statement'!I9) -> -0.059851313 | J83: =IF('Fin Statement'!J85="","",'Fin Statement'!J85/'Fin Statement'!J9) -> 0 | K83: =IF('Fin Statement'!K85="","",'Fin Statement'!K85/'Fin Statement'!K9) -> 0 | L83: =IF('Fin Statement'!L85="","",'Fin Statement'!L85/'Fin Statement'!L9) -> 0 | ... N83: =IF('Fin Statement'!N85="","",'Fin Statement'!N85/'Fin Statement'!N9) -> 0
B84: Net cash used in investing | E84: =IF('Fin Statement'!E86="","",'Fin Statement'!E86/'Fin Statement'!E9) -> -0.15287739 | F84: =IF('Fin Statement'!F86="","",'Fin Statement'!F86/'Fin Statement'!F9) -> -0.10702404 | G84: =IF('Fin Statement'!G86="","",'Fin Statement'!G86/'Fin Statement'!G9) -> -0.39559893 | H84: =IF('Fin Statement'!H86="","",'Fin Statement'!H86/'Fin Statement'!H9) -> -0.25769548 | I84: =IF('Fin Statement'!I86="","",'Fin Statement'!I86/'Fin Statement'!I9) -> -0.42038458 | J84: =IF('Fin Statement'!J86="","",'Fin Statement'!J86/'Fin Statement'!J9) -> -0.36607042 | K84: =IF('Fin Statement'!K86="","",'Fin Statement'!K86/'Fin Statement'!K9) -> -0.36003982 | L84: =IF('Fin Statement'!L86="","",'Fin Statement'!L86/'Fin Statement'!L9) -> -0.33851433 | ... N84: =IF('Fin Statement'!N86="","",'Fin Statement'!N86/'Fin Statement'!N9) -> -0.30306042
B85: Effect of foreign exchange rates on cash and cash equivalents | E85: =IF('Fin Statement'!E87="","",'Fin Statement'!E87/'Fin Statement'!E9) -> -0.00071115146 | F85: =IF('Fin Statement'!F87="","",'Fin Statement'!F87/'Fin Statement'!F9) -> -0.00091546139 | G85: =IF('Fin Statement'!G87="","",'Fin Statement'!G87/'Fin Statement'!G9) -> -0.00085671625 | H85: =IF('Fin Statement'!H87="","",'Fin Statement'!H87/'Fin Statement'!H9) -> 0.00022362312 | I85: =IF('Fin Statement'!I87="","",'Fin Statement'!I87/'Fin Statement'!I9) -> -0.00059064787 | J85: =IF('Fin Statement'!J87="","",'Fin Statement'!J87/'Fin Statement'!J9) -> 0 | K85: =IF('Fin Statement'!K87="","",'Fin Statement'!K87/'Fin Statement'!K9) -> 0 | L85: =IF('Fin Statement'!L87="","",'Fin Statement'!L87/'Fin Statement'!L9) -> 0 | ... N85: =IF('Fin Statement'!N87="","",'Fin Statement'!N87/'Fin Statement'!N9) -> 0
B86: Net change in cash and cash equivalents | E86: =IF('Fin Statement'!E88="","",'Fin Statement'!E88/'Fin Statement'!E9) -> -0.0014777828 | F86: =IF('Fin Statement'!F88="","",'Fin Statement'!F88/'Fin Statement'!F9) -> 0.098025152 | G86: =IF('Fin Statement'!G88="","",'Fin Statement'!G88/'Fin Statement'!G9) -> -0.066860584 | H86: =IF('Fin Statement'!H88="","",'Fin Statement'!H88/'Fin Statement'!H9) -> 0.042335761 | I86: =IF('Fin Statement'!I88="","",'Fin Statement'!I88/'Fin Statement'!I9) -> -0.028046734 | J86: =IF('Fin Statement'!J88="","",'Fin Statement'!J88/'Fin Statement'!J9) -> 0.053980448 | K86: =IF('Fin Statement'!K88="","",'Fin Statement'!K88/'Fin Statement'!K9) -> 0.074143839 | L86: =IF('Fin Statement'!L88="","",'Fin Statement'!L88/'Fin Statement'!L9) -> 0.11339291 | ... N86: =IF('Fin Statement'!N88="","",'Fin Statement'!N88/'Fin Statement'!N9) -> 0.16454112
B87: Cash and cash equivalents, beginning of period | E87: =IF('Fin Statement'!E89="","",'Fin Statement'!E89/'Fin Statement'!E9) -> 0.071740556 | F87: =IF('Fin Statement'!F89="","",'Fin Statement'!F89/'Fin Statement'!F9) -> 0.065738622 | G87: =IF('Fin Statement'!G89="","",'Fin Statement'!G89/'Fin Statement'!G9) -> 0.14157848 | H87: =IF('Fin Statement'!H89="","",'Fin Statement'!H89/'Fin Statement'!H9) -> 0.065010436 | I87: =IF('Fin Statement'!I89="","",'Fin Statement'!I89/'Fin Statement'!I9) -> 0.091134556 | J87: =IF('Fin Statement'!J89="","",'Fin Statement'!J89/'Fin Statement'!J9) -> 0.05367549 | K87: =IF('Fin Statement'!K89="","",'Fin Statement'!K89/'Fin Statement'!K9) -> 0.091223682 | L87: =IF('Fin Statement'!L89="","",'Fin Statement'!L89/'Fin Statement'!L9) -> 0.14187172 | ... N87: =IF('Fin Statement'!N89="","",'Fin Statement'!N89/'Fin Statement'!N9) -> 0.31550251
B88: Cash and cash equivalents, end of period | E88: =IF('Fin Statement'!E90="","",'Fin Statement'!E90/'Fin Statement'!E9) -> 0.070262773 | F88: =IF('Fin Statement'!F90="","",'Fin Statement'!F90/'Fin Statement'!F9) -> 0.16376377 | G88: =IF('Fin Statement'!G90="","",'Fin Statement'!G90/'Fin Statement'!G9) -> 0.074717896 | H88: =IF('Fin Statement'!H90="","",'Fin Statement'!H90/'Fin Statement'!H9) -> 0.1073462 | I88: =IF('Fin Statement'!I90="","",'Fin Statement'!I90/'Fin Statement'!I9) -> 0.063087823 | J88: =IF('Fin Statement'!J90="","",'Fin Statement'!J90/'Fin Statement'!J9) -> 0.10765594 | K88: =IF('Fin Statement'!K90="","",'Fin Statement'!K90/'Fin Statement'!K9) -> 0.16536752 | L88: =IF('Fin Statement'!L90="","",'Fin Statement'!L90/'Fin Statement'!L9) -> 0.25526463 | ... N88: =IF('Fin Statement'!N90="","",'Fin Statement'!N90/'Fin Statement'!N9) -> 0.48004363
B92: Balance sheet | E92: Historical | I92: Forecasted
B93: (% of total assets) | E93: =(2021+COLUMN()-COLUMN($D$5))&IF(COLUMN()-COLUMN($D$5)<5,"A","E") -> 2022A | F93: =(2021+COLUMN()-COLUMN($D$5))&IF(COLUMN()-COLUMN($D$5)<5,"A","E") -> 2023A | G93: =(2021+COLUMN()-COLUMN($D$5))&IF(COLUMN()-COLUMN($D$5)<5,"A","E") -> 2024A | H93: =(2021+COLUMN()-COLUMN($D$5))&IF(COLUMN()-COLUMN($D$5)<5,"A","E") -> 2025A | I93: 2026A | J93: =(2021+COLUMN()-COLUMN($D$5))&IF(COLUMN()-COLUMN($D$5)<5,"A","E") -> 2027E | K93: =(2021+COLUMN()-COLUMN($D$5))&IF(COLUMN()-COLUMN($D$5)<5,"A","E") -> 2028E | L93: =(2021+COLUMN()-COLUMN($D$5))&IF(COLUMN()-COLUMN($D$5)<5,"A","E") -> 2029E | M93: =(2021+COLUMN()-COLUMN($D$5))&IF(COLUMN()-COLUMN($D$5)<5,"A","E") -> 2030E | N93: =(2021+COLUMN()-COLUMN($D$5))&IF(COLUMN()-COLUMN($D$5)<5,"A","E") -> 2031E
B94: Assets
B95: Current assets:
B96: Cash and short-term investments | E96: =IF(OR('Fin Statement'!E109="",'Fin Statement'!E109=0),"",SUM('Fin Statement'!E98:'Fin Statement'!E99)/'Fin Statement'!E109) -> 0.28713135 | F96: =IF(OR('Fin Statement'!F109="",'Fin Statement'!F109=0),"",SUM('Fin Statement'!F98:'Fin Statement'!F99)/'Fin Statement'!F109) -> 0.27006913 | G96: =IF(OR('Fin Statement'!G109="",'Fin Statement'!G109=0),"",SUM('Fin Statement'!G98:'Fin Statement'!G99)/'Fin Statement'!G109) -> 0.14749796 | H96: =IF(OR('Fin Statement'!H109="",'Fin Statement'!H109=0),"",SUM('Fin Statement'!H98:'Fin Statement'!H99)/'Fin Statement'!H109) -> 0.15276986 | I96: =IF(OR('Fin Statement'!I109="",'Fin Statement'!I109=0),"",SUM('Fin Statement'!I98:'Fin Statement'!I99)/'Fin Statement'!I109) -> 0.10132573 | J96: =IF(OR('Fin Statement'!J109="",'Fin Statement'!J109=0),"",SUM('Fin Statement'!J98:'Fin Statement'!J99)/'Fin Statement'!J109) -> 0.11101182 | K96: =IF(OR('Fin Statement'!K109="",'Fin Statement'!K109=0),"",SUM('Fin Statement'!K98:'Fin Statement'!K99)/'Fin Statement'!K109) -> 0.13495953 | L96: =IF(OR('Fin Statement'!L109="",'Fin Statement'!L109=0),"",SUM('Fin Statement'!L98:'Fin Statement'!L99)/'Fin Statement'!L109) -> 0.17082669 | ... N96: =IF(OR('Fin Statement'!N109="",'Fin Statement'!N109=0),"",SUM('Fin Statement'!N98:'Fin Statement'!N99)/'Fin Statement'!N109) -> 0.25264261
B97: Accounts receivable | E97: =IF('Fin Statement'!E100="","",'Fin Statement'!E100/'Fin Statement'!E109) -> 0.12131619 | F97: =IF('Fin Statement'!F100="","",'Fin Statement'!F100/'Fin Statement'!F109) -> 0.11818164 | G97: =IF('Fin Statement'!G100="","",'Fin Statement'!G100/'Fin Statement'!G109) -> 0.1111443 | H97: =IF('Fin Statement'!H100="","",'Fin Statement'!H100/'Fin Statement'!H109) -> 0.1129316 | I97: =IF('Fin Statement'!I100="","",'Fin Statement'!I100/'Fin Statement'!I109) -> 0.10664367 | J97: =IF('Fin Statement'!J100="","",'Fin Statement'!J100/'Fin Statement'!J109) -> 0.1050573 | K97: =IF('Fin Statement'!K100="","",'Fin Statement'!K100/'Fin Statement'!K109) -> 0.1043479 | L97: =IF('Fin Statement'!L100="","",'Fin Statement'!L100/'Fin Statement'!L109) -> 0.10162647 | ... N97: =IF('Fin Statement'!N100="","",'Fin Statement'!N100/'Fin Statement'!N109) -> 0.095578975
B98: Inventories | E98: =IF('Fin Statement'!E101="","",'Fin Statement'!E101/'Fin Statement'!E109) -> 0.010256551 | F98: =IF('Fin Statement'!F101="","",'Fin Statement'!F101/'Fin Statement'!F109) -> 0.0060683147 | G98: =IF('Fin Statement'!G101="","",'Fin Statement'!G101/'Fin Statement'!G109) -> 0.0024328192 | H98: =IF('Fin Statement'!H101="","",'Fin Statement'!H101/'Fin Statement'!H109) -> 0.00151534 | I98: =IF('Fin Statement'!I101="","",'Fin Statement'!I101/'Fin Statement'!I109) -> 0.0018420942 | J98: =IF('Fin Statement'!J101="","",'Fin Statement'!J101/'Fin Statement'!J109) -> 0.0020303208 | K98: =IF('Fin Statement'!K101="","",'Fin Statement'!K101/'Fin Statement'!K109) -> 0.0020166112 | L98: =IF('Fin Statement'!L101="","",'Fin Statement'!L101/'Fin Statement'!L109) -> 0.0019747871 | ... N98: =IF('Fin Statement'!N101="","",'Fin Statement'!N101/'Fin Statement'!N109) -> 0.0018566491
B99: Other current assets | E99: =IF('Fin Statement'!E102="","",'Fin Statement'!E102/'Fin Statement'!E109) -> 0.046387458 | F99: =IF('Fin Statement'!F102="","",'Fin Statement'!F102/'Fin Statement'!F109) -> 0.052932695 | G99: =IF('Fin Statement'!G102="","",'Fin Statement'!G102/'Fin Statement'!G109) -> 0.050806091 | H99: =IF('Fin Statement'!H102="","",'Fin Statement'!H102/'Fin Statement'!H109) -> 0.041555534 | I99: =IF('Fin Statement'!I102="","",'Fin Statement'!I102/'Fin Statement'!I109) -> 0.064076395 | J99: =IF('Fin Statement'!J102="","",'Fin Statement'!J102/'Fin Statement'!J109) -> 0.053680282 | K99: =IF('Fin Statement'!K102="","",'Fin Statement'!K102/'Fin Statement'!K109) -> 0.045179549 | L99: =IF('Fin Statement'!L102="","",'Fin Statement'!L102/'Fin Statement'!L109) -> 0.03817842 | ... N99: =IF('Fin Statement'!N102="","",'Fin Statement'!N102/'Fin Statement'!N109) -> 0.027756498
B100: Total current assets | E100: =IF('Fin Statement'!E103="","",'Fin Statement'!E103/'Fin Statement'!E109) -> 0.46509155 | F100: =IF('Fin Statement'!F103="","",'Fin Statement'!F103/'Fin Statement'!F109) -> 0.44725178 | G100: =IF('Fin Statement'!G103="","",'Fin Statement'!G103/'Fin Statement'!G109) -> 0.31188118 | H100: =IF('Fin Statement'!H103="","",'Fin Statement'!H103/'Fin Statement'!H109) -> 0.30877233 | I100: =IF('Fin Statement'!I103="","",'Fin Statement'!I103/'Fin Statement'!I109) -> 0.27388789 | J100: =IF('Fin Statement'!J103="","",'Fin Statement'!J103/'Fin Statement'!J109) -> 0.27177972 | K100: =IF('Fin Statement'!K103="","",'Fin Statement'!K103/'Fin Statement'!K109) -> 0.28650359 | L100: =IF('Fin Statement'!L103="","",'Fin Statement'!L103/'Fin Statement'!L109) -> 0.31260636 | ... N100: =IF('Fin Statement'!N103="","",'Fin Statement'!N103/'Fin Statement'!N109) -> 0.37783474
B101: Property and equipment, net | E101: =IF('Fin Statement'!E104="","",'Fin Statement'!E104/'Fin Statement'!E109) -> 0.20391953 | F101: =IF('Fin Statement'!F104="","",'Fin Statement'!F104/'Fin Statement'!F109) -> 0.23215187 | G101: =IF('Fin Statement'!G104="","",'Fin Statement'!G104/'Fin Statement'!G109) -> 0.26474189 | H101: =IF('Fin Statement'!H104="","",'Fin Statement'!H104/'Fin Statement'!H109) -> 0.33112279 | I101: =IF('Fin Statement'!I104="","",'Fin Statement'!I104/'Fin Statement'!I109) -> 0.41282425 | J101: =IF('Fin Statement'!J104="","",'Fin Statement'!J104/'Fin Statement'!J109) -> 0.46097958 | K101: =IF('Fin Statement'!K104="","",'Fin Statement'!K104/'Fin Statement'!K109) -> 0.48532358 | L101: =IF('Fin Statement'!L104="","",'Fin Statement'!L104/'Fin Statement'!L109) -> 0.49270127 | ... N101: =IF('Fin Statement'!N104="","",'Fin Statement'!N104/'Fin Statement'!N109) -> 0.47887565
B102: Operating lease right-of-use assets | E102: =IF('Fin Statement'!E105="","",'Fin Statement'!E105/'Fin Statement'!E109) -> 0.036037715 | F102: =IF('Fin Statement'!F105="","",'Fin Statement'!F105/'Fin Statement'!F109) -> 0.034822417 | G102: =IF('Fin Statement'!G105="","",'Fin Statement'!G105/'Fin Statement'!G109) -> 0.037021417 | H102: =IF('Fin Statement'!H105="","",'Fin Statement'!H105/'Fin Statement'!H109) -> 0.040101583 | I102: =IF('Fin Statement'!I105="","",'Fin Statement'!I105/'Fin Statement'!I109) -> 0.031879965 | J102: =IF('Fin Statement'!J105="","",'Fin Statement'!J105/'Fin Statement'!J109) -> 0.034528115 | K102: =IF('Fin Statement'!K105="","",'Fin Statement'!K105/'Fin Statement'!K109) -> 0.034037266 | L102: =IF('Fin Statement'!L105="","",'Fin Statement'!L105/'Fin Statement'!L109) -> 0.031952113 | ... N102: =IF('Fin Statement'!N105="","",'Fin Statement'!N105/'Fin Statement'!N109) -> 0.026345024
B103: Equity and other investments | E103: =IF('Fin Statement'!E106="","",'Fin Statement'!E106/'Fin Statement'!E109) -> 0.018887732 | F103: =IF('Fin Statement'!F106="","",'Fin Statement'!F106/'Fin Statement'!F109) -> 0.023979552 | G103: =IF('Fin Statement'!G106="","",'Fin Statement'!G106/'Fin Statement'!G109) -> 0.02850655 | H103: =IF('Fin Statement'!H106="","",'Fin Statement'!H106/'Fin Statement'!H109) -> 0.024886794 | I103: =IF('Fin Statement'!I106="","",'Fin Statement'!I106/'Fin Statement'!I109) -> 0.047928732 | J103: =IF('Fin Statement'!J106="","",'Fin Statement'!J106/'Fin Statement'!J109) -> 0.040353269 | K103: =IF('Fin Statement'!K106="","",'Fin Statement'!K106/'Fin Statement'!K109) -> 0.034132798 | L103: =IF('Fin Statement'!L106="","",'Fin Statement'!L106/'Fin Statement'!L109) -> 0.028987717 | ... N103: =IF('Fin Statement'!N106="","",'Fin Statement'!N106/'Fin Statement'!N109) -> 0.021285941
B104: Goodwill and intangible assets | E104: =IF('Fin Statement'!E107="","",'Fin Statement'!E107/'Fin Statement'!E109) -> 0.21604539 | F104: =IF('Fin Statement'!F107="","",'Fin Statement'!F107/'Fin Statement'!F109) -> 0.18751578 | G104: =IF('Fin Statement'!G107="","",'Fin Statement'!G107/'Fin Statement'!G109) -> 0.28666069 | H104: =IF('Fin Statement'!H107="","",'Fin Statement'!H107/'Fin Statement'!H109) -> 0.2295837 | I104: =IF('Fin Statement'!I107="","",'Fin Statement'!I107/'Fin Statement'!I109) -> 0.18231062 | J104: =IF('Fin Statement'!J107="","",'Fin Statement'!J107/'Fin Statement'!J109) -> 0.14949264 | K104: =IF('Fin Statement'!K107="","",'Fin Statement'!K107/'Fin Statement'!K109) -> 0.1239244 | L104: =IF('Fin Statement'!L107="","",'Fin Statement'!L107/'Fin Statement'!L109) -> 0.10326495 | ... N104: =IF('Fin Statement'!N107="","",'Fin Statement'!N107/'Fin Statement'!N109) -> 0.073493546
B105: Other long-term assets | E105: =IF('Fin Statement'!E108="","",'Fin Statement'!E108/'Fin Statement'!E109) -> 0.06001809 | F105: =IF('Fin Statement'!F108="","",'Fin Statement'!F108/'Fin Statement'!F109) -> 0.074278599 | G105: =IF('Fin Statement'!G108="","",'Fin Statement'!G108/'Fin Statement'!G109) -> 0.071188274 | H105: =IF('Fin Statement'!H108="","",'Fin Statement'!H108/'Fin Statement'!H109) -> 0.0655328 | I105: =IF('Fin Statement'!I108="","",'Fin Statement'!I108/'Fin Statement'!I109) -> 0.05116855 | J105: =IF('Fin Statement'!J108="","",'Fin Statement'!J108/'Fin Statement'!J109) -> 0.042866678 | K105: =IF('Fin Statement'!K108="","",'Fin Statement'!K108/'Fin Statement'!K109) -> 0.036078372 | L105: =IF('Fin Statement'!L108="","",'Fin Statement'!L108/'Fin Statement'!L109) -> 0.030487583 | ... N105: =IF('Fin Statement'!N108="","",'Fin Statement'!N108/'Fin Statement'!N109) -> 0.022165101
B106: Total assets | E106: =IF('Fin Statement'!E109="","",'Fin Statement'!E109/'Fin Statement'!E109) -> 1 | F106: =IF('Fin Statement'!F109="","",'Fin Statement'!F109/'Fin Statement'!F109) -> 1 | G106: =IF('Fin Statement'!G109="","",'Fin Statement'!G109/'Fin Statement'!G109) -> 1 | H106: =IF('Fin Statement'!H109="","",'Fin Statement'!H109/'Fin Statement'!H109) -> 1 | I106: =IF('Fin Statement'!I109="","",'Fin Statement'!I109/'Fin Statement'!I109) -> 1 | J106: =IF('Fin Statement'!J109="","",'Fin Statement'!J109/'Fin Statement'!J109) -> 1 | K106: =IF('Fin Statement'!K109="","",'Fin Statement'!K109/'Fin Statement'!K109) -> 1 | L106: =IF('Fin Statement'!L109="","",'Fin Statement'!L109/'Fin Statement'!L109) -> 1 | ... N106: =IF('Fin Statement'!N109="","",'Fin Statement'!N109/'Fin Statement'!N109) -> 1
B107: Liabilities and stockholders’ equity
B108: Current liabilities:
B109: Accounts payable | E109: =IF('Fin Statement'!E112="","",'Fin Statement'!E112/'Fin Statement'!E109) -> 0.052077623 | F109: =IF('Fin Statement'!F112="","",'Fin Statement'!F112/'Fin Statement'!F109) -> 0.043922462 | G109: =IF('Fin Statement'!G112="","",'Fin Statement'!G112/'Fin Statement'!G109) -> 0.042947265 | H109: =IF('Fin Statement'!H112="","",'Fin Statement'!H112/'Fin Statement'!H109) -> 0.044788151 | I109: =IF('Fin Statement'!I112="","",'Fin Statement'!I112/'Fin Statement'!I109) -> 0.05593004 | J109: =IF('Fin Statement'!J112="","",'Fin Statement'!J112/'Fin Statement'!J109) -> 0.056848982 | K109: =IF('Fin Statement'!K112="","",'Fin Statement'!K112/'Fin Statement'!K109) -> 0.054448501 | L109: =IF('Fin Statement'!L112="","",'Fin Statement'!L112/'Fin Statement'!L109) -> 0.051344463 | ... N109: =IF('Fin Statement'!N112="","",'Fin Statement'!N112/'Fin Statement'!N109) -> 0.044559577
B110: Short-term debt | E110: =IF('Fin Statement'!E113="","",'Fin Statement'!E113/'Fin Statement'!E109) -> 0 | F110: =IF('Fin Statement'!F113="","",'Fin Statement'!F113/'Fin Statement'!F109) -> 0 | G110: =IF('Fin Statement'!G113="","",'Fin Statement'!G113/'Fin Statement'!G109) -> 0.013068105 | H110: =IF('Fin Statement'!H113="","",'Fin Statement'!H113/'Fin Statement'!H109) -> 0 | I110: =IF('Fin Statement'!I113="","",'Fin Statement'!I113/'Fin Statement'!I109) | J110: =IF('Fin Statement'!J113="","",'Fin Statement'!J113/'Fin Statement'!J109) -> 0 | K110: =IF('Fin Statement'!K113="","",'Fin Statement'!K113/'Fin Statement'!K109) -> 0 | L110: =IF('Fin Statement'!L113="","",'Fin Statement'!L113/'Fin Statement'!L109) -> 0 | ... N110: =IF('Fin Statement'!N113="","",'Fin Statement'!N113/'Fin Statement'!N109) -> 0
...

Sheet Trend Analysis
B1: Trend Analysis and Observation | P1: =HYPERLINK("#'Cover'!A1","Cover") -> Cover
E3: Historical | J3: Net Change | K3: Change per years | O3: Net Direction | P3: Pattern
B4: Profitability | E4: 2022 | F4: 2023 | G4: 2024 | H4: 2025 | I4: 2026 | J4: FY2022 - FY 2026 | K4: 2023 | L4: 2024 | M4: 2025 | N4: 2026
B5: Gross margin | E5: ='Common Size&Ratio'!E14 -> 0.68401674 | F5: ='Common Size&Ratio'!F14 -> 0.68920086 | G5: ='Common Size&Ratio'!G14 -> 0.69764444 | H5: ='Common Size&Ratio'!H14 -> 0.68823742 | I5: ='Common Size&Ratio'!I14 -> 0.67944093 | J5: =(I5-E5)*100 -> -0.45758111 | K5: =(F5-E5)*100 -> 0.5184114 | L5: =(G5-F5)*100 -> 0.84435794 | M5: =(H5-G5)*100 -> -0.94070144 | N5: =(I5-H5)*100 -> -0.87964902 | O5: =IF(J5>0,"Up",IF(J5<0,"Down","Flat")) -> Down | P5: {=IF(COUNT(K5:N5)<2,"n/a", IF(OR(COUNTIF(K5:N5,">0")=COUNT(K5:N5),COUNTIF(K5:N5,"<0")=COUNT(K5:N5)), IF(COUNTIF(K5:N5,">0")=COUNT(K5:N5),"Persistent rise – ","Persistent decline – ")& IF(ABS(N5)>1.25*SUMPRODUCT(ABS(IFERROR(K5:M5*1,0)))/COUNT(K5:M5),"accelerating", IF(ABS(N5)<0.75*SUMPRODUCT(ABS(IFERROR(K5:M5*1,0)))/COUNT(K5:M5),"decelerating","steady pace")), IF(SUMPRODUCT(--(IFERROR(K5:M5*L5:N5,0)<0))=1, IF(INDEX(K5:N5,MATCH(TRUE,INDEX(ISNUMBER(K5:N5),0),0))>0,"Reversing – peak ","Reversing – trough ")& INDEX($E$4:$I$4,MATCH(IF(INDEX(K5:N5,MATCH(TRUE,INDEX(ISNUMBER(K5:N5),0),0))>0,MAX(E5:I5),MIN(E5:I5)),E5:I5,0)), "Volatile – direction changed "&SUMPRODUCT(--(IFERROR(K5:M5*L5:N5,0)<0))&"x")))} -> Reversing – peak 2024
B6: EBIT (operating) margin | E6: ='Common Size&Ratio'!E20 -> 0.42055278 | F6: ='Common Size&Ratio'!F20 -> 0.41772881 | G6: ='Common Size&Ratio'!G20 -> 0.446443 | H6: ='Common Size&Ratio'!H20 -> 0.45621956 | I6: ='Common Size&Ratio'!I20 -> 0.46780818 | J6: =(I6-E6)*100 -> 4.7255403 | K6: =(F6-E6)*100 -> -0.28239752 | L6: =(G6-F6)*100 -> 2.8714189 | M6: =(H6-G6)*100 -> 0.97765667 | N6: =(I6-H6)*100 -> 1.1588622 | O6: =IF(J6>0,"Up",IF(J6<0,"Down","Flat")) -> Up | P6: {=IF(COUNT(K6:N6)<2,"n/a", IF(OR(COUNTIF(K6:N6,">0")=COUNT(K6:N6),COUNTIF(K6:N6,"<0")=COUNT(K6:N6)), IF(COUNTIF(K6:N6,">0")=COUNT(K6:N6),"Persistent rise – ","Persistent decline – ")& IF(ABS(N6)>1.25*SUMPRODUCT(ABS(IFERROR(K6:M6*1,0)))/COUNT(K6:M6),"accelerating", IF(ABS(N6)<0.75*SUMPRODUCT(ABS(IFERROR(K6:M6*1,0)))/COUNT(K6:M6),"decelerating","steady pace")), IF(SUMPRODUCT(--(IFERROR(K6:M6*L6:N6,0)<0))=1, IF(INDEX(K6:N6,MATCH(TRUE,INDEX(ISNUMBER(K6:N6),0),0))>0,"Reversing – peak ","Reversing – trough ")& INDEX($E$4:$I$4,MATCH(IF(INDEX(K6:N6,MATCH(TRUE,INDEX(ISNUMBER(K6:N6),0),0))>0,MAX(E6:I6),MIN(E6:I6)),E6:I6,0)), "Volatile – direction changed "&SUMPRODUCT(--(IFERROR(K6:M6*L6:N6,0)<0))&"x")))} -> Reversing – trough 2023
B7: Net profit margin | E7: ='Common Size&Ratio'!E27 -> 0.36686337 | F7: ='Common Size&Ratio'!F27 -> 0.34146238 | G7: ='Common Size&Ratio'!G27 -> 0.35955973 | H7: ='Common Size&Ratio'!H27 -> 0.36146015 | I7: ='Common Size&Ratio'!I27 -> 0.40305389 | J7: =(I7-E7)*100 -> 3.6190522 | K7: =(F7-E7)*100 -> -2.5400989 | L7: =(G7-F7)*100 -> 1.8097351 | M7: =(H7-G7)*100 -> 0.1900423 | N7: =(I7-H7)*100 -> 4.1593738 | O7: =IF(J7>0,"Up",IF(J7<0,"Down","Flat")) -> Up | P7: {=IF(COUNT(K7:N7)<2,"n/a", IF(OR(COUNTIF(K7:N7,">0")=COUNT(K7:N7),COUNTIF(K7:N7,"<0")=COUNT(K7:N7)), IF(COUNTIF(K7:N7,">0")=COUNT(K7:N7),"Persistent rise – ","Persistent decline – ")& IF(ABS(N7)>1.25*SUMPRODUCT(ABS(IFERROR(K7:M7*1,0)))/COUNT(K7:M7),"accelerating", IF(ABS(N7)<0.75*SUMPRODUCT(ABS(IFERROR(K7:M7*1,0)))/COUNT(K7:M7),"decelerating","steady pace")), IF(SUMPRODUCT(--(IFERROR(K7:M7*L7:N7,0)<0))=1, IF(INDEX(K7:N7,MATCH(TRUE,INDEX(ISNUMBER(K7:N7),0),0))>0,"Reversing – peak ","Reversing – trough ")& INDEX($E$4:$I$4,MATCH(IF(INDEX(K7:N7,MATCH(TRUE,INDEX(ISNUMBER(K7:N7),0),0))>0,MAX(E7:I7),MIN(E7:I7)),E7:I7,0)), "Volatile – direction changed "&SUMPRODUCT(--(IFERROR(K7:M7*L7:N7,0)<0))&"x")))} -> Reversing – trough 2023
B8: ROIC (NOPAT ÷ average invested capital) | E8: =IF('Common Size&Ratio'!E144="",0,"") -> 0 | F8: ='Common Size&Ratio'!F144 -> 0.56526971 | G8: ='Common Size&Ratio'!G144 -> 0.46272339 | H8: ='Common Size&Ratio'!H144 -> 0.39457044 | I8: ='Common Size&Ratio'!I144 -> 0.3585794 | J8: =(I8-E8)*100 -> 35.85794 | K8: =(F8-E8)*100 -> 56.526971 | L8: =(G8-F8)*100 -> -10.254632 | M8: =(H8-G8)*100 -> -6.8152949 | N8: =(I8-H8)*100 -> -3.5991046 | O8: =IF(J8>0,"Up",IF(J8<0,"Down","Flat")) -> Up | P8: {=IF(COUNT(K8:N8)<2,"n/a", IF(OR(COUNTIF(K8:N8,">0")=COUNT(K8:N8),COUNTIF(K8:N8,"<0")=COUNT(K8:N8)), IF(COUNTIF(K8:N8,">0")=COUNT(K8:N8),"Persistent rise – ","Persistent decline – ")& IF(ABS(N8)>1.25*SUMPRODUCT(ABS(IFERROR(K8:M8*1,0)))/COUNT(K8:M8),"accelerating", IF(ABS(N8)<0.75*SUMPRODUCT(ABS(IFERROR(K8:M8*1,0)))/COUNT(K8:M8),"decelerating","steady pace")), IF(SUMPRODUCT(--(IFERROR(K8:M8*L8:N8,0)<0))=1, IF(INDEX(K8:N8,MATCH(TRUE,INDEX(ISNUMBER(K8:N8),0),0))>0,"Reversing – peak ","Reversing – trough ")& INDEX($E$4:$I$4,MATCH(IF(INDEX(K8:N8,MATCH(TRUE,INDEX(ISNUMBER(K8:N8),0),0))>0,MAX(E8:I8),MIN(E8:I8)),E8:I8,0)), "Volatile – direction changed "&SUMPRODUCT(--(IFERROR(K8:M8*L8:N8,0)<0))&"x")))} -> Reversing – peak 2023
B9: ROCE (EBIT ÷ average capital employed) | E9: =IF('Common Size&Ratio'!E143="",,"0") -> 0 | F9: ='Common Size&Ratio'!F143 -> 0.30652804 | G9: ='Common Size&Ratio'!G143 -> 0.31504929 | H9: ='Common Size&Ratio'!H143 -> 0.29729073 | I9: ='Common Size&Ratio'!I143 -> 0.29088684 | J9: =(I9-E9)*100 -> 29.088684 | K9: =(F9-E9)*100 -> 30.652804 | L9: =(G9-F9)*100 -> 0.85212437 | M9: =(H9-G9)*100 -> -1.7758554 | N9: =(I9-H9)*100 -> -0.64038898 | O9: =IF(J9>0,"Up",IF(J9<0,"Down","Flat")) -> Up | P9: {=IF(COUNT(K9:N9)<2,"n/a", IF(OR(COUNTIF(K9:N9,">0")=COUNT(K9:N9),COUNTIF(K9:N9,"<0")=COUNT(K9:N9)), IF(COUNTIF(K9:N9,">0")=COUNT(K9:N9),"Persistent rise – ","Persistent decline – ")& IF(ABS(N9)>1.25*SUMPRODUCT(ABS(IFERROR(K9:M9*1,0)))/COUNT(K9:M9),"accelerating", IF(ABS(N9)<0.75*SUMPRODUCT(ABS(IFERROR(K9:M9*1,0)))/COUNT(K9:M9),"decelerating","steady pace")), IF(SUMPRODUCT(--(IFERROR(K9:M9*L9:N9,0)<0))=1, IF(INDEX(K9:N9,MATCH(TRUE,INDEX(ISNUMBER(K9:N9),0),0))>0,"Reversing – peak ","Reversing – trough ")& INDEX($E$4:$I$4,MATCH(IF(INDEX(K9:N9,MATCH(TRUE,INDEX(ISNUMBER(K9:N9),0),0))>0,MAX(E9:I9),MIN(E9:I9)),E9:I9,0)), "Volatile – direction changed "&SUMPRODUCT(--(IFERROR(K9:M9*L9:N9,0)<0))&"x")))} -> Reversing – peak 2024
B10: WACC (WACC tab, row 28) | E10: =WACC!E28 -> 0.074896582 | F10: =WACC!F28 -> 0.08351616 | G10: =WACC!G28 -> 0.081537557 | H10: =WACC!H28 -> 0.087468723 | I10: =WACC!I28 -> 0.090535584 | J10: =(I10-E10)*100 -> 1.5639003 | K10: =(F10-E10)*100 -> 0.86195784 | L10: =(G10-F10)*100 -> -0.1978603 | M10: =(H10-G10)*100 -> 0.5931166 | N10: =(I10-H10)*100 -> 0.30668611 | O10: =IF(J10>0,"Up",IF(J10<0,"Down","Flat")) -> Up | P10: {=IF(COUNT(K10:N10)<2,"n/a", IF(OR(COUNTIF(K10:N10,">0")=COUNT(K10:N10),COUNTIF(K10:N10,"<0")=COUNT(K10:N10)), IF(COUNTIF(K10:N10,">0")=COUNT(K10:N10),"Persistent rise – ","Persistent decline – ")& IF(ABS(N10)>1.25*SUMPRODUCT(ABS(IFERROR(K10:M10*1,0)))/COUNT(K10:M10),"accelerating", IF(ABS(N10)<0.75*SUMPRODUCT(ABS(IFERROR(K10:M10*1,0)))/COUNT(K10:M10),"decelerating","steady pace")), IF(SUMPRODUCT(--(IFERROR(K10:M10*L10:N10,0)<0))=1, IF(INDEX(K10:N10,MATCH(TRUE,INDEX(ISNUMBER(K10:N10),0),0))>0,"Reversing – peak ","Reversing – trough ")& INDEX($E$4:$I$4,MATCH(IF(INDEX(K10:N10,MATCH(TRUE,INDEX(ISNUMBER(K10:N10),0),0))>0,MAX(E10:I10),MIN(E10:I10)),E10:I10,0)), "Volatile – direction changed "&SUMPRODUCT(--(IFERROR(K10:M10*L10:N10,0)<0))&"x")))} -> Volatile – direction changed 2x
B11: ROIC − WACC spread | E11: =IF(E8=0,0%,E8-E10) -> 0 | F11: =IF(F8="",0%,F8-F10) -> 0.48175355 | G11: =IF(G8="",0%,G8-G10) -> 0.38118584 | H11: =IF(H8="",0%,H8-H10) -> 0.30710172 | I11: =IF(I8="",0%,I8-I10) -> 0.26804381 | J11: =(I11-E11)*100 -> 26.804381 | K11: =(F11-E11)*100 -> 48.175355 | L11: =(G11-F11)*100 -> -10.056772 | M11: =(H11-G11)*100 -> -7.4084115 | N11: =(I11-H11)*100 -> -3.9057907 | O11: =IF(J11>0,"Up",IF(J11<0,"Down","Flat")) -> Up | P11: {=IF(COUNT(K11:N11)<2,"n/a", IF(OR(COUNTIF(K11:N11,">0")=COUNT(K11:N11),COUNTIF(K11:N11,"<0")=COUNT(K11:N11)), IF(COUNTIF(K11:N11,">0")=COUNT(K11:N11),"Persistent rise – ","Persistent decline – ")& IF(ABS(N11)>1.25*SUMPRODUCT(ABS(IFERROR(K11:M11*1,0)))/COUNT(K11:M11),"accelerating", IF(ABS(N11)<0.75*SUMPRODUCT(ABS(IFERROR(K11:M11*1,0)))/COUNT(K11:M11),"decelerating","steady pace")), IF(SUMPRODUCT(--(IFERROR(K11:M11*L11:N11,0)<0))=1, IF(INDEX(K11:N11,MATCH(TRUE,INDEX(ISNUMBER(K11:N11),0),0))>0,"Reversing – peak ","Reversing – trough ")& INDEX($E$4:$I$4,MATCH(IF(INDEX(K11:N11,MATCH(TRUE,INDEX(ISNUMBER(K11:N11),0),0))>0,MAX(E11:I11),MIN(E11:I11)),E11:I11,0)), "Volatile – direction changed "&SUMPRODUCT(--(IFERROR(K11:M11*L11:N11,0)<0))&"x")))} -> Reversing – peak 2023
B12: Incremental ROIC (approx.) | E12: =IF('Common Size&Ratio'!E146="",0,"") -> 0 | F12: ='Common Size&Ratio'!F146 -> -0.023704492 | G12: ='Common Size&Ratio'!G146 -> 0.17348886 | H12: ='Common Size&Ratio'!H146 -> 0.34498345 | I12: ='Common Size&Ratio'!I146 -> 0.16926553 | J12: =(I12-E12)*100 -> 16.926553 | K12: =(F12-E12)*100 -> -2.3704492 | L12: =(G12-F12)*100 -> 19.719335 | M12: =(H12-G12)*100 -> 17.149459 | N12: =(I12-H12)*100 -> -17.571792 | O12: =IF(J12>0,"Up",IF(J12<0,"Down","Flat")) -> Up | P12: {=IF(COUNT(K12:N12)<2,"n/a", IF(OR(COUNTIF(K12:N12,">0")=COUNT(K12:N12),COUNTIF(K12:N12,"<0")=COUNT(K12:N12)), IF(COUNTIF(K12:N12,">0")=COUNT(K12:N12),"Persistent rise – ","Persistent decline – ")& IF(ABS(N12)>1.25*SUMPRODUCT(ABS(IFERROR(K12:M12*1,0)))/COUNT(K12:M12),"accelerating", IF(ABS(N12)<0.75*SUMPRODUCT(ABS(IFERROR(K12:M12*1,0)))/COUNT(K12:M12),"decelerating","steady pace")), IF(SUMPRODUCT(--(IFERROR(K12:M12*L12:N12,0)<0))=1, IF(INDEX(K12:N12,MATCH(TRUE,INDEX(ISNUMBER(K12:N12),0),0))>0,"Reversing – peak ","Reversing – trough ")& INDEX($E$4:$I$4,MATCH(IF(INDEX(K12:N12,MATCH(TRUE,INDEX(ISNUMBER(K12:N12),0),0))>0,MAX(E12:I12),MIN(E12:I12)),E12:I12,0)), "Volatile – direction changed "&SUMPRODUCT(--(IFERROR(K12:M12*L12:N12,0)<0))&"x")))} -> Volatile – direction changed 2x
B13: Revenue growth (YoY) | E13: =IF('Common Size&Ratio'!E147="",0,"") -> 0 | F13: ='Common Size&Ratio'!F147 -> 0.068820296 | G13: ='Common Size&Ratio'!G147 -> 0.15669962 | H13: ='Common Size&Ratio'!H147 -> 0.14932156 | I13: ='Common Size&Ratio'!I147 -> 0.17788687 | J13: =(I13-E13)*100 -> 17.788687 | K13: =(F13-E13)*100 -> 6.8820296 | L13: =(G13-F13)*100 -> 8.7879325 | M13: =(H13-G13)*100 -> -0.73780578 | N13: =(I13-H13)*100 -> 2.8565306 | O13: =IF(J13>0,"Up",IF(J13<0,"Down","Flat")) -> Up | P13: {=IF(COUNT(K13:N13)<2,"n/a", IF(OR(COUNTIF(K13:N13,">0")=COUNT(K13:N13),COUNTIF(K13:N13,"<0")=COUNT(K13:N13)), IF(COUNTIF(K13:N13,">0")=COUNT(K13:N13),"Persistent rise – ","Persistent decline – ")& IF(ABS(N13)>1.25*SUMPRODUCT(ABS(IFERROR(K13:M13*1,0)))/COUNT(K13:M13),"accelerating", IF(ABS(N13)<0.75*SUMPRODUCT(ABS(IFERROR(K13:M13*1,0)))/COUNT(K13:M13),"decelerating","steady pace")), IF(SUMPRODUCT(--(IFERROR(K13:M13*L13:N13,0)<0))=1, IF(INDEX(K13:N13,MATCH(TRUE,INDEX(ISNUMBER(K13:N13),0),0))>0,"Reversing – peak ","Reversing – trough ")& INDEX($E$4:$I$4,MATCH(IF(INDEX(K13:N13,MATCH(TRUE,INDEX(ISNUMBER(K13:N13),0),0))>0,MAX(E13:I13),MIN(E13:I13)),E13:I13,0)), "Volatile – direction changed "&SUMPRODUCT(--(IFERROR(K13:M13*L13:N13,0)<0))&"x")))} -> Volatile – direction changed 2x
B14: Operating income growth (YoY) | E14: =IF('Common Size&Ratio'!E152="",0,"") -> 0 | F14: ='Common Size&Ratio'!F152 -> 0.061643261 | G14: ='Common Size&Ratio'!G152 -> 0.2362098 | H14: ='Common Size&Ratio'!H152 -> 0.17449033 | I14: ='Common Size&Ratio'!I152 -> 0.20780686 | J14: =(I14-E14)*100 -> 20.780686 | K14: =(F14-E14)*100 -> 6.1643261 | L14: =(G14-F14)*100 -> 17.456654 | M14: =(H14-G14)*100 -> -6.1719471 | N14: =(I14-H14)*100 -> 3.3316532 | O14: =IF(J14>0,"Up",IF(J14<0,"Down","Flat")) -> Up | P14: {=IF(COUNT(K14:N14)<2,"n/a", IF(OR(COUNTIF(K14:N14,">0")=COUNT(K14:N14),COUNTIF(K14:N14,"<0")=COUNT(K14:N14)), IF(COUNTIF(K14:N14,">0")=COUNT(K14:N14),"Persistent rise – ","Persistent decline – ")& IF(ABS(N14)>1.25*SUMPRODUCT(ABS(IFERROR(K14:M14*1,0)))/COUNT(K14:M14),"accelerating", IF(ABS(N14)<0.75*SUMPRODUCT(ABS(IFERROR(K14:M14*1,0)))/COUNT(K14:M14),"decelerating","steady pace")), IF(SUMPRODUCT(--(IFERROR(K14:M14*L14:N14,0)<0))=1, IF(INDEX(K14:N14,MATCH(TRUE,INDEX(ISNUMBER(K14:N14),0),0))>0,"Reversing – peak ","Reversing – trough ")& INDEX($E$4:$I$4,MATCH(IF(INDEX(K14:N14,MATCH(TRUE,INDEX(ISNUMBER(K14:N14),0),0))>0,MAX(E14:I14),MIN(E14:I14)),E14:I14,0)), "Volatile – direction changed "&SUMPRODUCT(--(IFERROR(K14:M14*L14:N14,0)<0))&"x")))} -> Volatile – direction changed 2x
B15: Memo: Other income (expense), net, % of revenue | E15: ='Common Size&Ratio'!E24 -> 0.0016795279 | F15: ='Common Size&Ratio'!F24 -> 0.003718472 | G15: ='Common Size&Ratio'!G24 -> -0.0067150235 | H15: ='Common Size&Ratio'!H24 -> -0.017396459 | I15: ='Common Size&Ratio'!I24 -> 0.032235512 | J15: =(I15-E15)*100 -> 3.0555984 | K15: =(F15-E15)*100 -> 0.20389441 | L15: =(G15-F15)*100 -> -1.0433496 | M15: =(H15-G15)*100 -> -1.0681435 | N15: =(I15-H15)*100 -> 4.9631971 | O15: =IF(J15>0,"Up",IF(J15<0,"Down","Flat")) -> Up | P15: {=IF(COUNT(K15:N15)<2,"n/a", IF(OR(COUNTIF(K15:N15,">0")=COUNT(K15:N15),COUNTIF(K15:N15,"<0")=COUNT(K15:N15)), IF(COUNTIF(K15:N15,">0")=COUNT(K15:N15),"Persistent rise – ","Persistent decline – ")& IF(ABS(N15)>1.25*SUMPRODUCT(ABS(IFERROR(K15:M15*1,0)))/COUNT(K15:M15),"accelerating", IF(ABS(N15)<0.75*SUMPRODUCT(ABS(IFERROR(K15:M15*1,0)))/COUNT(K15:M15),"decelerating","steady pace")), IF(SUMPRODUCT(--(IFERROR(K15:M15*L15:N15,0)<0))=1, IF(INDEX(K15:N15,MATCH(TRUE,INDEX(ISNUMBER(K15:N15),0),0))>0,"Reversing – peak ","Reversing – trough ")& INDEX($E$4:$I$4,MATCH(IF(INDEX(K15:N15,MATCH(TRUE,INDEX(ISNUMBER(K15:N15),0),0))>0,MAX(E15:I15),MIN(E15:I15)),E15:I15,0)), "Volatile – direction changed "&SUMPRODUCT(--(IFERROR(K15:M15*L15:N15,0)<0))&"x")))} -> Volatile – direction changed 2x
B16: Memo: Effective tax rate (tax ÷ EBT) | E16: =WACC!E22 -> 0.13113383 | F16: =WACC!F22 -> 0.18978625 | G16: =WACC!G22 -> 0.18231327 | H16: =WACC!H22 -> 0.17629644 | I16: =WACC!I22 -> 0.19396266 | J16: =(I16-E16)*100 -> 6.2828826 | K16: =(F16-E16)*100 -> 5.8652419 | L16: =(G16-F16)*100 -> -0.74729866 | M16: =(H16-G16)*100 -> -0.60168259 | N16: =(I16-H16)*100 -> 1.766622 | O16: =IF(J16>0,"Up",IF(J16<0,"Down","Flat")) -> Up | P16: {=IF(COUNT(K16:N16)<2,"n/a", IF(OR(COUNTIF(K16:N16,">0")=COUNT(K16:N16),COUNTIF(K16:N16,"<0")=COUNT(K16:N16)), IF(COUNTIF(K16:N16,">0")=COUNT(K16:N16),"Persistent rise – ","Persistent decline – ")& IF(ABS(N16)>1.25*SUMPRODUCT(ABS(IFERROR(K16:M16*1,0)))/COUNT(K16:M16),"accelerating", IF(ABS(N16)<0.75*SUMPRODUCT(ABS(IFERROR(K16:M16*1,0)))/COUNT(K16:M16),"decelerating","steady pace")), IF(SUMPRODUCT(--(IFERROR(K16:M16*L16:N16,0)<0))=1, IF(INDEX(K16:N16,MATCH(TRUE,INDEX(ISNUMBER(K16:N16),0),0))>0,"Reversing – peak ","Reversing – trough ")& INDEX($E$4:$I$4,MATCH(IF(INDEX(K16:N16,MATCH(TRUE,INDEX(ISNUMBER(K16:N16),0),0))>0,MAX(E16:I16),MIN(E16:I16)),E16:I16,0)), "Volatile – direction changed "&SUMPRODUCT(--(IFERROR(K16:M16*L16:N16,0)<0))&"x")))} -> Volatile – direction changed 2x
B18: Capital Intensity
B19: Total revenue ($m) | E19: ='Fin Statement'!E9 -> 198270 | F19: ='Fin Statement'!F9 -> 211915 | G19: ='Fin Statement'!G9 -> 245122 | H19: ='Fin Statement'!H9 -> 281724 | I19: ='Fin Statement'!I9 -> 331839 | J19: =(I19-E19) -> 133569 | K19: =(F19-E19) -> 13645 | L19: =(G19-F19) -> 33207 | M19: =(H19-G19) -> 36602 | N19: =(I19-H19) -> 50115 | O19: =IF(J19>0,"Up",IF(J19<0,"Down","Flat")) -> Up | P19: {=IF(COUNT(K19:N19)<2,"n/a", IF(OR(COUNTIF(K19:N19,">0")=COUNT(K19:N19),COUNTIF(K19:N19,"<0")=COUNT(K19:N19)), IF(COUNTIF(K19:N19,">0")=COUNT(K19:N19),"Persistent rise – ","Persistent decline – ")& IF(ABS(N19)>1.25*SUMPRODUCT(ABS(IFERROR(K19:M19*1,0)))/COUNT(K19:M19),"accelerating", IF(ABS(N19)<0.75*SUMPRODUCT(ABS(IFERROR(K19:M19*1,0)))/COUNT(K19:M19),"decelerating","steady pace")), IF(SUMPRODUCT(--(IFERROR(K19:M19*L19:N19,0)<0))=1, IF(INDEX(K19:N19,MATCH(TRUE,INDEX(ISNUMBER(K19:N19),0),0))>0,"Reversing – peak ","Reversing – trough ")& INDEX($E$4:$I$4,MATCH(IF(INDEX(K19:N19,MATCH(TRUE,INDEX(ISNUMBER(K19:N19),0),0))>0,MAX(E19:I19),MIN(E19:I19)),E19:I19,0)), "Volatile – direction changed "&SUMPRODUCT(--(IFERROR(K19:M19*L19:N19,0)<0))&"x")))} -> Persistent rise – accelerating
B20: Capital expenditure ($m) | E20: =ABS('Fin Statement'!E82) -> 23886 | F20: =ABS('Fin Statement'!F82) -> 28107 | G20: =ABS('Fin Statement'!G82) -> 44477 | H20: =ABS('Fin Statement'!H82) -> 64551 | I20: =ABS('Fin Statement'!I82) -> 115948 | J20: =(I20-E20) -> 92062 | K20: =(F20-E20) -> 4221 | L20: =(G20-F20) -> 16370 | M20: =(H20-G20) -> 20074 | N20: =(I20-H20) -> 51397 | O20: =IF(J20>0,"Up",IF(J20<0,"Down","Flat")) -> Up | P20: {=IF(COUNT(K20:N20)<2,"n/a", IF(OR(COUNTIF(K20:N20,">0")=COUNT(K20:N20),COUNTIF(K20:N20,"<0")=COUNT(K20:N20)), IF(COUNTIF(K20:N20,">0")=COUNT(K20:N20),"Persistent rise – ","Persistent decline – ")& IF(ABS(N20)>1.25*SUMPRODUCT(ABS(IFERROR(K20:M20*1,0)))/COUNT(K20:M20),"accelerating", IF(ABS(N20)<0.75*SUMPRODUCT(ABS(IFERROR(K20:M20*1,0)))/COUNT(K20:M20),"decelerating","steady pace")), IF(SUMPRODUCT(--(IFERROR(K20:M20*L20:N20,0)<0))=1, IF(INDEX(K20:N20,MATCH(TRUE,INDEX(ISNUMBER(K20:N20),0),0))>0,"Reversing – peak ","Reversing – trough ")& INDEX($E$4:$I$4,MATCH(IF(INDEX(K20:N20,MATCH(TRUE,INDEX(ISNUMBER(K20:N20),0),0))>0,MAX(E20:I20),MIN(E20:I20)),E20:I20,0)), "Volatile – direction changed "&SUMPRODUCT(--(IFERROR(K20:M20*L20:N20,0)<0))&"x")))} -> Persistent rise – accelerating
B21: CapEx / revenue | E21: ='Common Size&Ratio'!E171 -> 0.12047208 | F21: ='Common Size&Ratio'!F171 -> 0.13263337 | G21: ='Common Size&Ratio'!G171 -> 0.18144842 | H21: ='Common Size&Ratio'!H171 -> 0.22912851 | I21: ='Common Size&Ratio'!I171 -> 0.34941041 | J21: =(I21-E21)*100 -> 22.893832 | K21: =(F21-E21)*100 -> 1.2161284 | L21: =(G21-F21)*100 -> 4.8815054 | M21: =(H21-G21)*100 -> 4.7680087 | N21: =(I21-H21)*100 -> 12.02819 | O21: =IF(J21>0,"Up",IF(J21<0,"Down","Flat")) -> Up | P21: {=IF(COUNT(K21:N21)<2,"n/a", IF(OR(COUNTIF(K21:N21,">0")=COUNT(K21:N21),COUNTIF(K21:N21,"<0")=COUNT(K21:N21)), IF(COUNTIF(K21:N21,">0")=COUNT(K21:N21),"Persistent rise – ","Persistent decline – ")& IF(ABS(N21)>1.25*SUMPRODUCT(ABS(IFERROR(K21:M21*1,0)))/COUNT(K21:M21),"accelerating", IF(ABS(N21)<0.75*SUMPRODUCT(ABS(IFERROR(K21:M21*1,0)))/COUNT(K21:M21),"decelerating","steady pace")), IF(SUMPRODUCT(--(IFERROR(K21:M21*L21:N21,0)<0))=1, IF(INDEX(K21:N21,MATCH(TRUE,INDEX(ISNUMBER(K21:N21),0),0))>0,"Reversing – peak ","Reversing – trough ")& INDEX($E$4:$I$4,MATCH(IF(INDEX(K21:N21,MATCH(TRUE,INDEX(ISNUMBER(K21:N21),0),0))>0,MAX(E21:I21),MIN(E21:I21)),E21:I21,0)), "Volatile – direction changed "&SUMPRODUCT(--(IFERROR(K21:M21*L21:N21,0)<0))&"x")))} -> Persistent rise – accelerating
B22: CapEx / CFO | E22: ='Common Size&Ratio'!E173 -> 0.26827652 | F22: ='Common Size&Ratio'!F173 -> 0.32092211 | G22: ='Common Size&Ratio'!G173 -> 0.37518136 | H22: ='Common Size&Ratio'!H173 -> 0.474075 | I22: ='Common Size&Ratio'!I173 -> 0.63382076 | J22: =(I22-E22)*100 -> 36.554424 | K22: =(F22-E22)*100 -> 5.2645587 | L22: =(G22-F22)*100 -> 5.4259254 | M22: =(H22-G22)*100 -> 9.8893638 | N22: =(I22-H22)*100 -> 15.974576 | O22: =IF(J22>0,"Up",IF(J22<0,"Down","Flat")) -> Up | P22: {=IF(COUNT(K22:N22)<2,"n/a", IF(OR(COUNTIF(K22:N22,">0")=COUNT(K22:N22),COUNTIF(K22:N22,"<0")=COUNT(K22:N22)), IF(COUNTIF(K22:N22,">0")=COUNT(K22:N22),"Persistent rise – ","Persistent decline – ")& IF(ABS(N22)>1.25*SUMPRODUCT(ABS(IFERROR(K22:M22*1,0)))/COUNT(K22:M22),"accelerating", IF(ABS(N22)<0.75*SUMPRODUCT(ABS(IFERROR(K22:M22*1,0)))/COUNT(K22:M22),"decelerating","steady pace")), IF(SUMPRODUCT(--(IFERROR(K22:M22*L22:N22,0)<0))=1, IF(INDEX(K22:N22,MATCH(TRUE,INDEX(ISNUMBER(K22:N22),0),0))>0,"Reversing – peak ","Reversing – trough ")& INDEX($E$4:$I$4,MATCH(IF(INDEX(K22:N22,MATCH(TRUE,INDEX(ISNUMBER(K22:N22),0),0))>0,MAX(E22:I22),MIN(E22:I22)),E22:I22,0)), "Volatile – direction changed "&SUMPRODUCT(--(IFERROR(K22:M22*L22:N22,0)<0))&"x")))} -> Persistent rise – accelerating
B23: CapEx / D&A | E23: ='Common Size&Ratio'!E172 -> 1.6518672 | F23: ='Common Size&Ratio'!F172 -> 2.0277758 | G23: ='Common Size&Ratio'!G172 -> 2.1221968 | H23: ='Common Size&Ratio'!H172 -> 2.1931505 | I23: ='Common Size&Ratio'!I172 -> 3.0089791 | J23: =(I23-E23) -> 1.3571119 | K23: =(F23-E23) -> 0.37590855 | L23: =(G23-F23) -> 0.094421001 | M23: =(H23-G23) -> 0.070953771 | N23: =(I23-H23) -> 0.81582854 | O23: =IF(J23>0,"Up",IF(J23<0,"Down","Flat")) -> Up | P23: {=IF(COUNT(K23:N23)<2,"n/a", IF(OR(COUNTIF(K23:N23,">0")=COUNT(K23:N23),COUNTIF(K23:N23,"<0")=COUNT(K23:N23)), IF(COUNTIF(K23:N23,">0")=COUNT(K23:N23),"Persistent rise – ","Persistent decline – ")& IF(ABS(N23)>1.25*SUMPRODUCT(ABS(IFERROR(K23:M23*1,0)))/COUNT(K23:M23),"accelerating", IF(ABS(N23)<0.75*SUMPRODUCT(ABS(IFERROR(K23:M23*1,0)))/COUNT(K23:M23),"decelerating","steady pace")), IF(SUMPRODUCT(--(IFERROR(K23:M23*L23:N23,0)<0))=1, IF(INDEX(K23:N23,MATCH(TRUE,INDEX(ISNUMBER(K23:N23),0),0))>0,"Reversing – peak ","Reversing – trough ")& INDEX($E$4:$I$4,MATCH(IF(INDEX(K23:N23,MATCH(TRUE,INDEX(ISNUMBER(K23:N23),0),0))>0,MAX(E23:I23),MIN(E23:I23)),E23:I23,0)), "Volatile – direction changed "&SUMPRODUCT(--(IFERROR(K23:M23*L23:N23,0)<0))&"x")))} -> Persistent rise – accelerating
B24: Net PP&E ($m) | E24: ='Fin Statement'!E104 -> 74398 | F24: ='Fin Statement'!F104 -> 95641 | G24: ='Fin Statement'!G104 -> 135591 | H24: ='Fin Statement'!H104 -> 204966 | I24: ='Fin Statement'!I104 -> 313076 | J24: =(I24-E24) -> 238678 | K24: =(F24-E24) -> 21243 | L24: =(G24-F24) -> 39950 | M24: =(H24-G24) -> 69375 | N24: =(I24-H24) -> 108110 | O24: =IF(J24>0,"Up",IF(J24<0,"Down","Flat")) -> Up | P24: {=IF(COUNT(K24:N24)<2,"n/a", IF(OR(COUNTIF(K24:N24,">0")=COUNT(K24:N24),COUNTIF(K24:N24,"<0")=COUNT(K24:N24)), IF(COUNTIF(K24:N24,">0")=COUNT(K24:N24),"Persistent rise – ","Persistent decline – ")& IF(ABS(N24)>1.25*SUMPRODUCT(ABS(IFERROR(K24:M24*1,0)))/COUNT(K24:M24),"accelerating", IF(ABS(N24)<0.75*SUMPRODUCT(ABS(IFERROR(K24:M24*1,0)))/COUNT(K24:M24),"decelerating","steady pace")), IF(SUMPRODUCT(--(IFERROR(K24:M24*L24:N24,0)<0))=1, IF(INDEX(K24:N24,MATCH(TRUE,INDEX(ISNUMBER(K24:N24),0),0))>0,"Reversing – peak ","Reversing – trough ")& INDEX($E$4:$I$4,MATCH(IF(INDEX(K24:N24,MATCH(TRUE,INDEX(ISNUMBER(K24:N24),0),0))>0,MAX(E24:I24),MIN(E24:I24)),E24:I24,0)), "Volatile – direction changed "&SUMPRODUCT(--(IFERROR(K24:M24*L24:N24,0)<0))&"x")))} -> Persistent rise – accelerating
B25: Net PP&E / total assets | E25: ='Common Size&Ratio'!E101 -> 0.20391953 | F25: ='Common Size&Ratio'!F101 -> 0.23215187 | G25: ='Common Size&Ratio'!G101 -> 0.26474189 | H25: ='Common Size&Ratio'!H101 -> 0.33112279 | I25: ='Common Size&Ratio'!I101 -> 0.41282425 | J25: =(I25-E25)*100 -> 20.890472 | K25: =(F25-E25)*100 -> 2.8232347 | L25: =(G25-F25)*100 -> 3.2590016 | M25: =(H25-G25)*100 -> 6.6380901 | N25: =(I25-H25)*100 -> 8.1701456 | O25: =IF(J25>0,"Up",IF(J25<0,"Down","Flat")) -> Up | P25: {=IF(COUNT(K25:N25)<2,"n/a", IF(OR(COUNTIF(K25:N25,">0")=COUNT(K25:N25),COUNTIF(K25:N25,"<0")=COUNT(K25:N25)), IF(COUNTIF(K25:N25,">0")=COUNT(K25:N25),"Persistent rise – ","Persistent decline – ")& IF(ABS(N25)>1.25*SUMPRODUCT(ABS(IFERROR(K25:M25*1,0)))/COUNT(K25:M25),"accelerating", IF(ABS(N25)<0.75*SUMPRODUCT(ABS(IFERROR(K25:M25*1,0)))/COUNT(K25:M25),"decelerating","steady pace")), IF(SUMPRODUCT(--(IFERROR(K25:M25*L25:N25,0)<0))=1, IF(INDEX(K25:N25,MATCH(TRUE,INDEX(ISNUMBER(K25:N25),0),0))>0,"Reversing – peak ","Reversing – trough ")& INDEX($E$4:$I$4,MATCH(IF(INDEX(K25:N25,MATCH(TRUE,INDEX(ISNUMBER(K25:N25),0),0))>0,MAX(E25:I25),MIN(E25:I25)),E25:I25,0)), "Volatile – direction changed "&SUMPRODUCT(--(IFERROR(K25:M25*L25:N25,0)<0))&"x")))} -> Persistent rise – accelerating
B26: Depreciation & amortization ($m) | E26: ='Fin Statement'!E21 -> 14460 | F26: ='Fin Statement'!F21 -> 13861 | G26: ='Fin Statement'!G21 -> 20958 | H26: ='Fin Statement'!H21 -> 29433 | I26: ='Fin Statement'!I21 -> 38534 | J26: =(I26-E26) -> 24074 | K26: =(F26-E26) -> -599 | L26: =(G26-F26) -> 7097 | M26: =(H26-G26) -> 8475 | N26: =(I26-H26) -> 9101 | O26: =IF(J26>0,"Up",IF(J26<0,"Down","Flat")) -> Up | P26: {=IF(COUNT(K26:N26)<2,"n/a", IF(OR(COUNTIF(K26:N26,">0")=COUNT(K26:N26),COUNTIF(K26:N26,"<0")=COUNT(K26:N26)), IF(COUNTIF(K26:N26,">0")=COUNT(K26:N26),"Persistent rise – ","Persistent decline – ")& IF(ABS(N26)>1.25*SUMPRODUCT(ABS(IFERROR(K26:M26*1,0)))/COUNT(K26:M26),"accelerating", IF(ABS(N26)<0.75*SUMPRODUCT(ABS(IFERROR(K26:M26*1,0)))/COUNT(K26:M26),"decelerating","steady pace")), IF(SUMPRODUCT(--(IFERROR(K26:M26*L26:N26,0)<0))=1, IF(INDEX(K26:N26,MATCH(TRUE,INDEX(ISNUMBER(K26:N26),0),0))>0,"Reversing – peak ","Reversing – trough ")& INDEX($E$4:$I$4,MATCH(IF(INDEX(K26:N26,MATCH(TRUE,INDEX(ISNUMBER(K26:N26),0),0))>0,MAX(E26:I26),MIN(E26:I26)),E26:I26,0)), "Volatile – direction changed "&SUMPRODUCT(--(IFERROR(K26:M26*L26:N26,0)<0))&"x")))} -> Reversing – trough 2023
B27: D&A / revenue | E27: ='Common Size&Ratio'!E174 -> 0.072930852 | F27: ='Common Size&Ratio'!F174 -> 0.0654083 | G27: ='Common Size&Ratio'!G174 -> 0.085500281 | H27: ='Common Size&Ratio'!H174 -> 0.10447459 | I27: ='Common Size&Ratio'!I174 -> 0.11612258 | J27: =(I27-E27)*100 -> 4.3191726 | K27: =(F27-E27)*100 -> -0.75225514 | L27: =(G27-F27)*100 -> 2.0091981 | M27: =(H27-G27)*100 -> 1.8974311 | N27: =(I27-H27)*100 -> 1.1647985 | O27: =IF(J27>0,"Up",IF(J27<0,"Down","Flat")) -> Up | P27: {=IF(COUNT(K27:N27)<2,"n/a", IF(OR(COUNTIF(K27:N27,">0")=COUNT(K27:N27),COUNTIF(K27:N27,"<0")=COUNT(K27:N27)), IF(COUNTIF(K27:N27,">0")=COUNT(K27:N27),"Persistent rise – ","Persistent decline – ")& IF(ABS(N27)>1.25*SUMPRODUCT(ABS(IFERROR(K27:M27*1,0)))/COUNT(K27:M27),"accelerating", IF(ABS(N27)<0.75*SUMPRODUCT(ABS(IFERROR(K27:M27*1,0)))/COUNT(K27:M27),"decelerating","steady pace")), IF(SUMPRODUCT(--(IFERROR(K27:M27*L27:N27,0)<0))=1, IF(INDEX(K27:N27,MATCH(TRUE,INDEX(ISNUMBER(K27:N27),0),0))>0,"Reversing – peak ","Reversing – trough ")& INDEX($E$4:$I$4,MATCH(IF(INDEX(K27:N27,MATCH(TRUE,INDEX(ISNUMBER(K27:N27),0),0))>0,MAX(E27:I27),MIN(E27:I27)),E27:I27,0)), "Volatile – direction changed "&SUMPRODUCT(--(IFERROR(K27:M27*L27:N27,0)<0))&"x")))} -> Reversing – trough 2023
B28: Net PP&E ÷ D&A | E28: =E24/E26 -> 5.1450899 | F28: =F24/F26 -> 6.9000072 | G28: =G24/G26 -> 6.4696536 | H28: =H24/H26 -> 6.9638161 | I28: =I24/I26 -> 8.1246691 | J28: =(I28-E28) -> 2.9795792 | K28: =(F28-E28) -> 1.7549173 | L28: =(G28-F28) -> -0.43035362 | M28: =(H28-G28) -> 0.49416253 | N28: =(I28-H28) -> 1.160853 | O28: =IF(J28>0,"Up",IF(J28<0,"Down","Flat")) -> Up | P28: {=IF(COUNT(K28:N28)<2,"n/a", IF(OR(COUNTIF(K28:N28,">0")=COUNT(K28:N28),COUNTIF(K28:N28,"<0")=COUNT(K28:N28)), IF(COUNTIF(K28:N28,">0")=COUNT(K28:N28),"Persistent rise – ","Persistent decline – ")& IF(ABS(N28)>1.25*SUMPRODUCT(ABS(IFERROR(K28:M28*1,0)))/COUNT(K28:M28),"accelerating", IF(ABS(N28)<0.75*SUMPRODUCT(ABS(IFERROR(K28:M28*1,0)))/COUNT(K28:M28),"decelerating","steady pace")), IF(SUMPRODUCT(--(IFERROR(K28:M28*L28:N28,0)<0))=1, IF(INDEX(K28:N28,MATCH(TRUE,INDEX(ISNUMBER(K28:N28),0),0))>0,"Reversing – peak ","Reversing – trough ")& INDEX($E$4:$I$4,MATCH(IF(INDEX(K28:N28,MATCH(TRUE,INDEX(ISNUMBER(K28:N28),0),0))>0,MAX(E28:I28),MIN(E28:I28)),E28:I28,0)), "Volatile – direction changed "&SUMPRODUCT(--(IFERROR(K28:M28*L28:N28,0)<0))&"x")))} -> Volatile – direction changed 2x
B30: Cash Generation
B31: Net cash from operations — CFO ($m) | E31: ='Fin Statement'!E74 -> 89035 | F31: ='Fin Statement'!F74 -> 87582 | G31: ='Fin Statement'!G74 -> 118548 | H31: ='Fin Statement'!H74 -> 136162 | I31: ='Fin Statement'!I74 -> 182935 | J31: =I31-E31 -> 93900 | K31: =F31-E31 -> -1453 | L31: =G31-F31 -> 30966 | M31: =H31-G31 -> 17614 | N31: =I31-H31 -> 46773 | O31: =IF(J31>0,"Up",IF(J31<0,"Down","Flat")) -> Up | P31: {=IF(COUNT(K31:N31)<2,"n/a", IF(OR(COUNTIF(K31:N31,">0")=COUNT(K31:N31),COUNTIF(K31:N31,"<0")=COUNT(K31:N31)), IF(COUNTIF(K31:N31,">0")=COUNT(K31:N31),"Persistent rise – ","Persistent decline – ")& IF(ABS(N31)>1.25*SUMPRODUCT(ABS(IFERROR(K31:M31*1,0)))/COUNT(K31:M31),"accelerating", IF(ABS(N31)<0.75*SUMPRODUCT(ABS(IFERROR(K31:M31*1,0)))/COUNT(K31:M31),"decelerating","steady pace")), IF(SUMPRODUCT(--(IFERROR(K31:M31*L31:N31,0)<0))=1, IF(INDEX(K31:N31,MATCH(TRUE,INDEX(ISNUMBER(K31:N31),0),0))>0,"Reversing – peak ","Reversing – trough ")& INDEX($E$4:$I$4,MATCH(IF(INDEX(K31:N31,MATCH(TRUE,INDEX(ISNUMBER(K31:N31),0),0))>0,MAX(E31:I31),MIN(E31:I31)),E31:I31,0)), "Volatile – direction changed "&SUMPRODUCT(--(IFERROR(K31:M31*L31:N31,0)<0))&"x")))} -> Reversing – trough 2023
B32: CFO margin (CFO ÷ revenue) | E32: ='Common Size&Ratio'!E167 -> 0.44905936 | F32: ='Common Size&Ratio'!F167 -> 0.41328835 | G32: ='Common Size&Ratio'!G167 -> 0.48362856 | H32: ='Common Size&Ratio'!H167 -> 0.48331701 | I32: ='Common Size&Ratio'!I167 -> 0.55127637 | J32: =(I32-E32)*100 -> 10.221701 | K32: =(F32-E32)*100 -> -3.5771017 | L32: =(G32-F32)*100 -> 7.0340214 | M32: =(H32-G32)*100 -> -0.031155518 | N32: =(I32-H32)*100 -> 6.7959367 | O32: =IF(J32>0,"Up",IF(J32<0,"Down","Flat")) -> Up | P32: {=IF(COUNT(K32:N32)<2,"n/a", IF(OR(COUNTIF(K32:N32,">0")=COUNT(K32:N32),COUNTIF(K32:N32,"<0")=COUNT(K32:N32)), IF(COUNTIF(K32:N32,">0")=COUNT(K32:N32),"Persistent rise – ","Persistent decline – ")& IF(ABS(N32)>1.25*SUMPRODUCT(ABS(IFERROR(K32:M32*1,0)))/COUNT(K32:M32),"accelerating", IF(ABS(N32)<0.75*SUMPRODUCT(ABS(IFERROR(K32:M32*1,0)))/COUNT(K32:M32),"decelerating","steady pace")), IF(SUMPRODUCT(--(IFERROR(K32:M32*L32:N32,0)<0))=1, IF(INDEX(K32:N32,MATCH(TRUE,INDEX(ISNUMBER(K32:N32),0),0))>0,"Reversing – peak ","Reversing – trough ")& INDEX($E$4:$I$4,MATCH(IF(INDEX(K32:N32,MATCH(TRUE,INDEX(ISNUMBER(K32:N32),0),0))>0,MAX(E32:I32),MIN(E32:I32)),E32:I32,0)), "Volatile – direction changed "&SUMPRODUCT(--(IFERROR(K32:M32*L32:N32,0)<0))&"x")))} -> Volatile – direction changed 3x
B33: Net income ($m) | E33: ='Fin Statement'!E29 -> 72738 | F33: ='Fin Statement'!F29 -> 72361 | G33: ='Fin Statement'!G29 -> 88136 | H33: ='Fin Statement'!H29 -> 101832 | I33: ='Fin Statement'!I29 -> 133749 | J33: =I33-E33 -> 61011 | K33: =F33-E33 -> -377 | L33: =G33-F33 -> 15775 | M33: =H33-G33 -> 13696 | N33: =I33-H33 -> 31917 | O33: =IF(J33>0,"Up",IF(J33<0,"Down","Flat")) -> Up | P33: {=IF(COUNT(K33:N33)<2,"n/a", IF(OR(COUNTIF(K33:N33,">0")=COUNT(K33:N33),COUNTIF(K33:N33,"<0")=COUNT(K33:N33)), IF(COUNTIF(K33:N33,">0")=COUNT(K33:N33),"Persistent rise – ","Persistent decline – ")& IF(ABS(N33)>1.25*SUMPRODUCT(ABS(IFERROR(K33:M33*1,0)))/COUNT(K33:M33),"accelerating", IF(ABS(N33)<0.75*SUMPRODUCT(ABS(IFERROR(K33:M33*1,0)))/COUNT(K33:M33),"decelerating","steady pace")), IF(SUMPRODUCT(--(IFERROR(K33:M33*L33:N33,0)<0))=1, IF(INDEX(K33:N33,MATCH(TRUE,INDEX(ISNUMBER(K33:N33),0),0))>0,"Reversing – peak ","Reversing – trough ")& INDEX($E$4:$I$4,MATCH(IF(INDEX(K33:N33,MATCH(TRUE,INDEX(ISNUMBER(K33:N33),0),0))>0,MAX(E33:I33),MIN(E33:I33)),E33:I33,0)), "Volatile – direction changed "&SUMPRODUCT(--(IFERROR(K33:M33*L33:N33,0)<0))&"x")))} -> Reversing – trough 2023
B34: CFO / net income | E34: ='Common Size&Ratio'!E170 -> 1.2240507 | F34: ='Common Size&Ratio'!F170 -> 1.2103481 | G34: ='Common Size&Ratio'!G170 -> 1.3450576 | H34: ='Common Size&Ratio'!H170 -> 1.3371239 | I34: ='Common Size&Ratio'!I170 -> 1.3677485 | J34: =I34-E34 -> 0.14369784 | K34: =F34-E34 -> -0.013702587 | L34: =G34-F34 -> 0.13470952 | M34: =H34-G34 -> -0.0079337479 | N34: =I34-H34 -> 0.030624654 | O34: =IF(J34>0,"Up",IF(J34<0,"Down","Flat")) -> Up | P34: {=IF(COUNT(K34:N34)<2,"n/a", IF(OR(COUNTIF(K34:N34,">0")=COUNT(K34:N34),COUNTIF(K34:N34,"<0")=COUNT(K34:N34)), IF(COUNTIF(K34:N34,">0")=COUNT(K34:N34),"Persistent rise – ","Persistent decline – ")& IF(ABS(N34)>1.25*SUMPRODUCT(ABS(IFERROR(K34:M34*1,0)))/COUNT(K34:M34),"accelerating", IF(ABS(N34)<0.75*SUMPRODUCT(ABS(IFERROR(K34:M34*1,0)))/COUNT(K34:M34),"decelerating","steady pace")), IF(SUMPRODUCT(--(IFERROR(K34:M34*L34:N34,0)<0))=1, IF(INDEX(K34:N34,MATCH(TRUE,INDEX(ISNUMBER(K34:N34),0),0))>0,"Reversing – peak ","Reversing – trough ")& INDEX($E$4:$I$4,MATCH(IF(INDEX(K34:N34,MATCH(TRUE,INDEX(ISNUMBER(K34:N34),0),0))>0,MAX(E34:I34),MIN(E34:I34)),E34:I34,0)), "Volatile – direction changed "&SUMPRODUCT(--(IFERROR(K34:M34*L34:N34,0)<0))&"x")))} -> Volatile – direction changed 3x
B35: Capital expenditure ($m) | E35: =E20 -> 23886 | F35: =F20 -> 28107 | G35: =G20 -> 44477 | H35: =H20 -> 64551 | I35: =I20 -> 115948 | J35: =I35-E35 -> 92062 | K35: =F35-E35 -> 4221 | L35: =G35-F35 -> 16370 | M35: =H35-G35 -> 20074 | N35: =I35-H35 -> 51397 | O35: =IF(J35>0,"Up",IF(J35<0,"Down","Flat")) -> Up | P35: {=IF(COUNT(K35:N35)<2,"n/a", IF(OR(COUNTIF(K35:N35,">0")=COUNT(K35:N35),COUNTIF(K35:N35,"<0")=COUNT(K35:N35)), IF(COUNTIF(K35:N35,">0")=COUNT(K35:N35),"Persistent rise – ","Persistent decline – ")& IF(ABS(N35)>1.25*SUMPRODUCT(ABS(IFERROR(K35:M35*1,0)))/COUNT(K35:M35),"accelerating", IF(ABS(N35)<0.75*SUMPRODUCT(ABS(IFERROR(K35:M35*1,0)))/COUNT(K35:M35),"decelerating","steady pace")), IF(SUMPRODUCT(--(IFERROR(K35:M35*L35:N35,0)<0))=1, IF(INDEX(K35:N35,MATCH(TRUE,INDEX(ISNUMBER(K35:N35),0),0))>0,"Reversing – peak ","Reversing – trough ")& INDEX($E$4:$I$4,MATCH(IF(INDEX(K35:N35,MATCH(TRUE,INDEX(ISNUMBER(K35:N35),0),0))>0,MAX(E35:I35),MIN(E35:I35)),E35:I35,0)), "Volatile – direction changed "&SUMPRODUCT(--(IFERROR(K35:M35*L35:N35,0)<0))&"x")))} -> Persistent rise – accelerating
B36: Free cash flow — FCF ($m) | E36: ='Common Size&Ratio'!E168 -> 65149 | F36: ='Common Size&Ratio'!F168 -> 59475 | G36: ='Common Size&Ratio'!G168 -> 74071 | H36: ='Common Size&Ratio'!H168 -> 71611 | I36: ='Common Size&Ratio'!I168 -> 66987 | J36: =I36-E36 -> 1838 | K36: =F36-E36 -> -5674 | L36: =G36-F36 -> 14596 | M36: =H36-G36 -> -2460 | N36: =I36-H36 -> -4624 | O36: =IF(J36>0,"Up",IF(J36<0,"Down","Flat")) -> Up | P36: {=IF(COUNT(K36:N36)<2,"n/a", IF(OR(COUNTIF(K36:N36,">0")=COUNT(K36:N36),COUNTIF(K36:N36,"<0")=COUNT(K36:N36)), IF(COUNTIF(K36:N36,">0")=COUNT(K36:N36),"Persistent rise – ","Persistent decline – ")& IF(ABS(N36)>1.25*SUMPRODUCT(ABS(IFERROR(K36:M36*1,0)))/COUNT(K36:M36),"accelerating", IF(ABS(N36)<0.75*SUMPRODUCT(ABS(IFERROR(K36:M36*1,0)))/COUNT(K36:M36),"decelerating","steady pace")), IF(SUMPRODUCT(--(IFERROR(K36:M36*L36:N36,0)<0))=1, IF(INDEX(K36:N36,MATCH(TRUE,INDEX(ISNUMBER(K36:N36),0),0))>0,"Reversing – peak ","Reversing – trough ")& INDEX($E$4:$I$4,MATCH(IF(INDEX(K36:N36,MATCH(TRUE,INDEX(ISNUMBER(K36:N36),0),0))>0,MAX(E36:I36),MIN(E36:I36)),E36:I36,0)), "Volatile – direction changed "&SUMPRODUCT(--(IFERROR(K36:M36*L36:N36,0)<0))&"x")))} -> Volatile – direction changed 2x
B37: FCF margin (FCF ÷ revenue) | E37: ='Common Size&Ratio'!E169 -> 0.32858728 | F37: ='Common Size&Ratio'!F169 -> 0.28065498 | G37: ='Common Size&Ratio'!G169 -> 0.30218014 | H37: ='Common Size&Ratio'!H169 -> 0.2541885 | I37: ='Common Size&Ratio'!I169 -> 0.20186597 | J37: =(I37-E37)*100 -> -12.672131 | K37: =(F37-E37)*100 -> -4.79323 | L37: =(G37-F37)*100 -> 2.1525159 | M37: =(H37-G37)*100 -> -4.7991642 | N37: =(I37-H37)*100 -> -5.2322531 | O37: =IF(J37>0,"Up",IF(J37<0,"Down","Flat")) -> Down | P37: {=IF(COUNT(K37:N37)<2,"n/a", IF(OR(COUNTIF(K37:N37,">0")=COUNT(K37:N37),COUNTIF(K37:N37,"<0")=COUNT(K37:N37)), IF(COUNTIF(K37:N37,">0")=COUNT(K37:N37),"Persistent rise – ","Persistent decline – ")& IF(ABS(N37)>1.25*SUMPRODUCT(ABS(IFERROR(K37:M37*1,0)))/COUNT(K37:M37),"accelerating", IF(ABS(N37)<0.75*SUMPRODUCT(ABS(IFERROR(K37:M37*1,0)))/COUNT(K37:M37),"decelerating","steady pace")), IF(SUMPRODUCT(--(IFERROR(K37:M37*L37:N37,0)<0))=1, IF(INDEX(K37:N37,MATCH(TRUE,INDEX(ISNUMBER(K37:N37),0),0))>0,"Reversing – peak ","Reversing – trough ")& INDEX($E$4:$I$4,MATCH(IF(INDEX(K37:N37,MATCH(TRUE,INDEX(ISNUMBER(K37:N37),0),0))>0,MAX(E37:I37),MIN(E37:I37)),E37:I37,0)), "Volatile – direction changed "&SUMPRODUCT(--(IFERROR(K37:M37*L37:N37,0)<0))&"x")))} -> Volatile – direction changed 2x
B38: FCF / net income | E38: =E36/E33 -> 0.89566664 | F38: =F36/F33 -> 0.82192065 | G38: =G36/G33 -> 0.84041708 | H38: =H36/H33 -> 0.70322688 | I38: =I36/I33 -> 0.50084113 | J38: =I38-E38 -> -0.39482551 | K38: =F38-E38 -> -0.073745991 | L38: =G38-F38 -> 0.018496435 | M38: =H38-G38 -> -0.1371902 | N38: =I38-H38 -> -0.20238576 | O38: =IF(J38>0,"Up",IF(J38<0,"Down","Flat")) -> Down | P38: {=IF(COUNT(K38:N38)<2,"n/a", IF(OR(COUNTIF(K38:N38,">0")=COUNT(K38:N38),COUNTIF(K38:N38,"<0")=COUNT(K38:N38)), IF(COUNTIF(K38:N38,">0")=COUNT(K38:N38),"Persistent rise – ","Persistent decline – ")& IF(ABS(N38)>1.25*SUMPRODUCT(ABS(IFERROR(K38:M38*1,0)))/COUNT(K38:M38),"accelerating", IF(ABS(N38)<0.75*SUMPRODUCT(ABS(IFERROR(K38:M38*1,0)))/COUNT(K38:M38),"decelerating","steady pace")), IF(SUMPRODUCT(--(IFERROR(K38:M38*L38:N38,0)<0))=1, IF(INDEX(K38:N38,MATCH(TRUE,INDEX(ISNUMBER(K38:N38),0),0))>0,"Reversing – peak ","Reversing – trough ")& INDEX($E$4:$I$4,MATCH(IF(INDEX(K38:N38,MATCH(TRUE,INDEX(ISNUMBER(K38:N38),0),0))>0,MAX(E38:I38),MIN(E38:I38)),E38:I38,0)), "Volatile – direction changed "&SUMPRODUCT(--(IFERROR(K38:M38*L38:N38,0)<0))&"x")))} -> Volatile – direction changed 2x
B39: Allocation: dividends paid ($m) | E39: =ABS('Fin Statement'!E78) -> 18135 | F39: =ABS('Fin Statement'!F78) -> 19800 | G39: =ABS('Fin Statement'!G78) -> 21771 | H39: =ABS('Fin Statement'!H78) -> 24082 | I39: =ABS('Fin Statement'!I78) -> 26445 | J39: =I39-E39 -> 8310 | K39: =F39-E39 -> 1665 | L39: =G39-F39 -> 1971 | M39: =H39-G39 -> 2311 | N39: =I39-H39 -> 2363 | O39: =IF(J39>0,"Up",IF(J39<0,"Down","Flat")) -> Up | P39: {=IF(COUNT(K39:N39)<2,"n/a", IF(OR(COUNTIF(K39:N39,">0")=COUNT(K39:N39),COUNTIF(K39:N39,"<0")=COUNT(K39:N39)), IF(COUNTIF(K39:N39,">0")=COUNT(K39:N39),"Persistent rise – ","Persistent decline – ")& IF(ABS(N39)>1.25*SUMPRODUCT(ABS(IFERROR(K39:M39*1,0)))/COUNT(K39:M39),"accelerating", IF(ABS(N39)<0.75*SUMPRODUCT(ABS(IFERROR(K39:M39*1,0)))/COUNT(K39:M39),"decelerating","steady pace")), IF(SUMPRODUCT(--(IFERROR(K39:M39*L39:N39,0)<0))=1, IF(INDEX(K39:N39,MATCH(TRUE,INDEX(ISNUMBER(K39:N39),0),0))>0,"Reversing – peak ","Reversing – trough ")& INDEX($E$4:$I$4,MATCH(IF(INDEX(K39:N39,MATCH(TRUE,INDEX(ISNUMBER(K39:N39),0),0))>0,MAX(E39:I39),MIN(E39:I39)),E39:I39,0)), "Volatile – direction changed "&SUMPRODUCT(--(IFERROR(K39:M39*L39:N39,0)<0))&"x")))} -> Persistent rise – steady pace
B40: Allocation: net share repurchases ($m) | E40: =ABS('Fin Statement'!E77) -> 30855 | F40: =ABS('Fin Statement'!F77) -> 20379 | G40: =ABS('Fin Statement'!G77) -> 15252 | H40: =ABS('Fin Statement'!H77) -> 16364 | I40: =ABS('Fin Statement'!I77) -> 20262 | J40: =I40-E40 -> -10593 | K40: =F40-E40 -> -10476 | L40: =G40-F40 -> -5127 | M40: =H40-G40 -> 1112 | N40: =I40-H40 -> 3898 | O40: =IF(J40>0,"Up",IF(J40<0,"Down","Flat")) -> Down | P40: {=IF(COUNT(K40:N40)<2,"n/a", IF(OR(COUNTIF(K40:N40,">0")=COUNT(K40:N40),COUNTIF(K40:N40,"<0")=COUNT(K40:N40)), IF(COUNTIF(K40:N40,">0")=COUNT(K40:N40),"Persistent rise – ","Persistent decline – ")& IF(ABS(N40)>1.25*SUMPRODUCT(ABS(IFERROR(K40:M40*1,0)))/COUNT(K40:M40),"accelerating", IF(ABS(N40)<0.75*SUMPRODUCT(ABS(IFERROR(K40:M40*1,0)))/COUNT(K40:M40),"decelerating","steady pace")), IF(SUMPRODUCT(--(IFERROR(K40:M40*L40:N40,0)<0))=1, IF(INDEX(K40:N40,MATCH(TRUE,INDEX(ISNUMBER(K40:N40),0),0))>0,"Reversing – peak ","Reversing – trough ")& INDEX($E$4:$I$4,MATCH(IF(INDEX(K40:N40,MATCH(TRUE,INDEX(ISNUMBER(K40:N40),0),0))>0,MAX(E40:I40),MIN(E40:I40)),E40:I40,0)), "Volatile – direction changed "&SUMPRODUCT(--(IFERROR(K40:M40*L40:N40,0)<0))&"x")))} -> Reversing – trough 2024
B41: CapEx + dividends + net repurchases ($m) | E41: =E35+E39+E40 -> 72876 | F41: =F35+F39+F40 -> 68286 | G41: =G35+G39+G40 -> 81500 | H41: =H35+H39+H40 -> 104997 | I41: =I35+I39+I40 -> 162655 | J41: =I41-E41 -> 89779 | K41: =F41-E41 -> -4590 | L41: =G41-F41 -> 13214 | M41: =H41-G41 -> 23497 | N41: =I41-H41 -> 57658 | O41: =IF(J41>0,"Up",IF(J41<0,"Down","Flat")) -> Up | P41: {=IF(COUNT(K41:N41)<2,"n/a", IF(OR(COUNTIF(K41:N41,">0")=COUNT(K41:N41),COUNTIF(K41:N41,"<0")=COUNT(K41:N41)), IF(COUNTIF(K41:N41,">0")=COUNT(K41:N41),"Persistent rise – ","Persistent decline – ")& IF(ABS(N41)>1.25*SUMPRODUCT(ABS(IFERROR(K41:M41*1,0)))/COUNT(K41:M41),"accelerating", IF(ABS(N41)<0.75*SUMPRODUCT(ABS(IFERROR(K41:M41*1,0)))/COUNT(K41:M41),"decelerating","steady pace")), IF(SUMPRODUCT(--(IFERROR(K41:M41*L41:N41,0)<0))=1, IF(INDEX(K41:N41,MATCH(TRUE,INDEX(ISNUMBER(K41:N41),0),0))>0,"Reversing – peak ","Reversing – trough ")& INDEX($E$4:$I$4,MATCH(IF(INDEX(K41:N41,MATCH(TRUE,INDEX(ISNUMBER(K41:N41),0),0))>0,MAX(E41:I41),MIN(E41:I41)),E41:I41,0)), "Volatile – direction changed "&SUMPRODUCT(--(IFERROR(K41:M41*L41:N41,0)<0))&"x")))} -> Reversing – trough 2023
B42: CFO less listed uses ($m) | E42: =E31-E41 -> 16159 | F42: =F31-F41 -> 19296 | G42: =G31-G41 -> 37048 | H42: =H31-H41 -> 31165 | I42: =I31-I41 -> 20280 | J42: =I42-E42 -> 4121 | K42: =F42-E42 -> 3137 | L42: =G42-F42 -> 17752 | M42: =H42-G42 -> -5883 | N42: =I42-H42 -> -10885 | O42: =IF(J42>0,"Up",IF(J42<0,"Down","Flat")) -> Up | P42: {=IF(COUNT(K42:N42)<2,"n/a", IF(OR(COUNTIF(K42:N42,">0")=COUNT(K42:N42),COUNTIF(K42:N42,"<0")=COUNT(K42:N42)), IF(COUNTIF(K42:N42,">0")=COUNT(K42:N42),"Persistent rise – ","Persistent decline – ")& IF(ABS(N42)>1.25*SUMPRODUCT(ABS(IFERROR(K42:M42*1,0)))/COUNT(K42:M42),"accelerating", IF(ABS(N42)<0.75*SUMPRODUCT(ABS(IFERROR(K42:M42*1,0)))/COUNT(K42:M42),"decelerating","steady pace")), IF(SUMPRODUCT(--(IFERROR(K42:M42*L42:N42,0)<0))=1, IF(INDEX(K42:N42,MATCH(TRUE,INDEX(ISNUMBER(K42:N42),0),0))>0,"Reversing – peak ","Reversing – trough ")& INDEX($E$4:$I$4,MATCH(IF(INDEX(K42:N42,MATCH(TRUE,INDEX(ISNUMBER(K42:N42),0),0))>0,MAX(E42:I42),MIN(E42:I42)),E42:I42,0)), "Volatile – direction changed "&SUMPRODUCT(--(IFERROR(K42:M42*L42:N42,0)<0))&"x")))} -> Reversing – peak 2024
B43: CFO coverage of listed uses (CFO ÷ uses) | E43: =E31/E41 -> 1.2217328 | F43: =F31/F41 -> 1.2825762 | G43: =G31/G41 -> 1.4545767 | H43: =H31/H41 -> 1.296818 | I43: =I31/I41 -> 1.1246811 | J43: =I43-E43 -> -0.097051733 | K43: =F43-E43 -> 0.060843417 | L43: =G43-F43 -> 0.17200046 | M43: =H43-G43 -> -0.15775868 | N43: =I43-H43 -> -0.17213693 | O43: =IF(J43>0,"Up",IF(J43<0,"Down","Flat")) -> Down | P43: {=IF(COUNT(K43:N43)<2,"n/a", IF(OR(COUNTIF(K43:N43,">0")=COUNT(K43:N43),COUNTIF(K43:N43,"<0")=COUNT(K43:N43)), IF(COUNTIF(K43:N43,">0")=COUNT(K43:N43),"Persistent rise – ","Persistent decline – ")& IF(ABS(N43)>1.25*SUMPRODUCT(ABS(IFERROR(K43:M43*1,0)))/COUNT(K43:M43),"accelerating", IF(ABS(N43)<0.75*SUMPRODUCT(ABS(IFERROR(K43:M43*1,0)))/COUNT(K43:M43),"decelerating","steady pace")), IF(SUMPRODUCT(--(IFERROR(K43:M43*L43:N43,0)<0))=1, IF(INDEX(K43:N43,MATCH(TRUE,INDEX(ISNUMBER(K43:N43),0),0))>0,"Reversing – peak ","Reversing – trough ")& INDEX($E$4:$I$4,MATCH(IF(INDEX(K43:N43,MATCH(TRUE,INDEX(ISNUMBER(K43:N43),0),0))>0,MAX(E43:I43),MIN(E43:I43)),E43:I43,0)), "Volatile – direction changed "&SUMPRODUCT(--(IFERROR(K43:M43*L43:N43,0)<0))&"x")))} -> Reversing – peak 2024
B44: Memo: net debt repayment (+) / issuance (−) ($m) | E44: =ABS('Fin Statement'!E76) -> 9023 | F44: =ABS('Fin Statement'!F76) -> 2750 | G44: =ABS('Fin Statement'!G76) -> 575 | H44: =ABS('Fin Statement'!H76) -> 8962 | I44: =ABS('Fin Statement'!I76) -> 3000 | J44: =I44-E44 -> -6023 | K44: =F44-E44 -> -6273 | L44: =G44-F44 -> -2175 | M44: =H44-G44 -> 8387 | N44: =I44-H44 -> -5962 | O44: =IF(J44>0,"Up",IF(J44<0,"Down","Flat")) -> Down | P44: {=IF(COUNT(K44:N44)<2,"n/a", IF(OR(COUNTIF(K44:N44,">0")=COUNT(K44:N44),COUNTIF(K44:N44,"<0")=COUNT(K44:N44)), IF(COUNTIF(K44:N44,">0")=COUNT(K44:N44),"Persistent rise – ","Persistent decline – ")& IF(ABS(N44)>1.25*SUMPRODUCT(ABS(IFERROR(K44:M44*1,0)))/COUNT(K44:M44),"accelerating", IF(ABS(N44)<0.75*SUMPRODUCT(ABS(IFERROR(K44:M44*1,0)))/COUNT(K44:M44),"decelerating","steady pace")), IF(SUMPRODUCT(--(IFERROR(K44:M44*L44:N44,0)<0))=1, IF(INDEX(K44:N44,MATCH(TRUE,INDEX(ISNUMBER(K44:N44),0),0))>0,"Reversing – peak ","Reversing – trough ")& INDEX($E$4:$I$4,MATCH(IF(INDEX(K44:N44,MATCH(TRUE,INDEX(ISNUMBER(K44:N44),0),0))>0,MAX(E44:I44),MIN(E44:I44)),E44:I44,0)), "Volatile – direction changed "&SUMPRODUCT(--(IFERROR(K44:M44*L44:N44,0)<0))&"x")))} -> Volatile – direction changed 2x
B45: Memo: CFO less listed uses and net debt repayment ($m) | E45: =E42-E44 -> 7136 | F45: =F42-F44 -> 16546 | G45: =G42-G44 -> 36473 | H45: =H42-H44 -> 22203 | I45: =I42-I44 -> 17280 | J45: =I45-E45 -> 10144 | K45: =F45-E45 -> 9410 | L45: =G45-F45 -> 19927 | M45: =H45-G45 -> -14270 | N45: =I45-H45 -> -4923 | O45: =IF(J45>0,"Up",IF(J45<0,"Down","Flat")) -> Up | P45: {=IF(COUNT(K45:N45)<2,"n/a", IF(OR(COUNTIF(K45:N45,">0")=COUNT(K45:N45),COUNTIF(K45:N45,"<0")=COUNT(K45:N45)), IF(COUNTIF(K45:N45,">0")=COUNT(K45:N45),"Persistent rise – ","Persistent decline – ")& IF(ABS(N45)>1.25*SUMPRODUCT(ABS(IFERROR(K45:M45*1,0)))/COUNT(K45:M45),"accelerating", IF(ABS(N45)<0.75*SUMPRODUCT(ABS(IFERROR(K45:M45*1,0)))/COUNT(K45:M45),"decelerating","steady pace")), IF(SUMPRODUCT(--(IFERROR(K45:M45*L45:N45,0)<0))=1, IF(INDEX(K45:N45,MATCH(TRUE,INDEX(ISNUMBER(K45:N45),0),0))>0,"Reversing – peak ","Reversing – trough ")& INDEX($E$4:$I$4,MATCH(IF(INDEX(K45:N45,MATCH(TRUE,INDEX(ISNUMBER(K45:N45),0),0))>0,MAX(E45:I45),MIN(E45:I45)),E45:I45,0)), "Volatile – direction changed "&SUMPRODUCT(--(IFERROR(K45:M45*L45:N45,0)<0))&"x")))} -> Reversing – peak 2024
B47: Financing
B48: Total interest-bearing debt ($m) | E48: =WACC!E17 -> 49781 | F48: =WACC!F17 -> 47237 | G48: =WACC!G17 -> 51630 | H48: =WACC!H17 -> 43151 | I48: =WACC!I17 -> 106888 | J48: =I48-E48 -> 57107 | K48: =F48-E48 -> -2544 | L48: =G48-F48 -> 4393 | M48: =H48-G48 -> -8479 | N48: =I48-H48 -> 63737 | O48: =IF(J48>0,"Up",IF(J48<0,"Down","Flat")) -> Up | P48: {=IF(COUNT(K48:N48)<2,"n/a", IF(OR(COUNTIF(K48:N48,">0")=COUNT(K48:N48),COUNTIF(K48:N48,"<0")=COUNT(K48:N48)), IF(COUNTIF(K48:N48,">0")=COUNT(K48:N48),"Persistent rise – ","Persistent decline – ")& IF(ABS(N48)>1.25*SUMPRODUCT(ABS(IFERROR(K48:M48*1,0)))/COUNT(K48:M48),"accelerating", IF(ABS(N48)<0.75*SUMPRODUCT(ABS(IFERROR(K48:M48*1,0)))/COUNT(K48:M48),"decelerating","steady pace")), IF(SUMPRODUCT(--(IFERROR(K48:M48*L48:N48,0)<0))=1, IF(INDEX(K48:N48,MATCH(TRUE,INDEX(ISNUMBER(K48:N48),0),0))>0,"Reversing – peak ","Reversing – trough ")& INDEX($E$4:$I$4,MATCH(IF(INDEX(K48:N48,MATCH(TRUE,INDEX(ISNUMBER(K48:N48),0),0))>0,MAX(E48:I48),MIN(E48:I48)),E48:I48,0)), "Volatile – direction changed "&SUMPRODUCT(--(IFERROR(K48:M48*L48:N48,0)<0))&"x")))} -> Volatile – direction changed 3x
B49: Cash and short-term investments ($m) | E49: ='Fin Statement'!E98 -> 13931 | F49: ='Fin Statement'!F98 -> 34704 | G49: ='Fin Statement'!G98 -> 18315 | H49: ='Fin Statement'!H98 -> 30242 | I49: ='Fin Statement'!I98 -> 20935 | J49: =I49-E49 -> 7004 | K49: =F49-E49 -> 20773 | L49: =G49-F49 -> -16389 | M49: =H49-G49 -> 11927 | N49: =I49-H49 -> -9307 | O49: =IF(J49>0,"Up",IF(J49<0,"Down","Flat")) -> Up | P49: {=IF(COUNT(K49:N49)<2,"n/a", IF(OR(COUNTIF(K49:N49,">0")=COUNT(K49:N49),COUNTIF(K49:N49,"<0")=COUNT(K49:N49)), IF(COUNTIF(K49:N49,">0")=COUNT(K49:N49),"Persistent rise – ","Persistent decline – ")& IF(ABS(N49)>1.25*SUMPRODUCT(ABS(IFERROR(K49:M49*1,0)))/COUNT(K49:M49),"accelerating", IF(ABS(N49)<0.75*SUMPRODUCT(ABS(IFERROR(K49:M49*1,0)))/COUNT(K49:M49),"decelerating","steady pace")), IF(SUMPRODUCT(--(IFERROR(K49:M49*L49:N49,0)<0))=1, IF(INDEX(K49:N49,MATCH(TRUE,INDEX(ISNUMBER(K49:N49),0),0))>0,"Reversing – peak ","Reversing – trough ")& INDEX($E$4:$I$4,MATCH(IF(INDEX(K49:N49,MATCH(TRUE,INDEX(ISNUMBER(K49:N49),0),0))>0,MAX(E49:I49),MIN(E49:I49)),E49:I49,0)), "Volatile – direction changed "&SUMPRODUCT(--(IFERROR(K49:M49*L49:N49,0)<0))&"x")))} -> Volatile – direction changed 3x
B50: Net cash ($m) = cash & ST investments − debt | E50: =E49-E48 -> -35850 | F50: =F49-F48 -> -12533 | G50: =G49-G48 -> -33315 | H50: =H49-H48 -> -12909 | I50: =I49-I48 -> -85953 | J50: =I50-E50 -> -50103 | K50: =F50-E50 -> 23317 | L50: =G50-F50 -> -20782 | M50: =H50-G50 -> 20406 | N50: =I50-H50 -> -73044 | O50: =IF(J50>0,"Up",IF(J50<0,"Down","Flat")) -> Down | P50: {=IF(COUNT(K50:N50)<2,"n/a", IF(OR(COUNTIF(K50:N50,">0")=COUNT(K50:N50),COUNTIF(K50:N50,"<0")=COUNT(K50:N50)), IF(COUNTIF(K50:N50,">0")=COUNT(K50:N50),"Persistent rise – ","Persistent decline – ")& IF(ABS(N50)>1.25*SUMPRODUCT(ABS(IFERROR(K50:M50*1,0)))/COUNT(K50:M50),"accelerating", IF(ABS(N50)<0.75*SUMPRODUCT(ABS(IFERROR(K50:M50*1,0)))/COUNT(K50:M50),"decelerating","steady pace")), IF(SUMPRODUCT(--(IFERROR(K50:M50*L50:N50,0)<0))=1, IF(INDEX(K50:N50,MATCH(TRUE,INDEX(ISNUMBER(K50:N50),0),0))>0,"Reversing – peak ","Reversing – trough ")& INDEX($E$4:$I$4,MATCH(IF(INDEX(K50:N50,MATCH(TRUE,INDEX(ISNUMBER(K50:N50),0),0))>0,MAX(E50:I50),MIN(E50:I50)),E50:I50,0)), "Volatile – direction changed "&SUMPRODUCT(--(IFERROR(K50:M50*L50:N50,0)<0))&"x")))} -> Volatile – direction changed 3x
B51: Total stockholders' equity ($m) | E51: ='Fin Statement'!E131 -> 166542 | F51: ='Fin Statement'!F131 -> 206223 | G51: ='Fin Statement'!G131 -> 268477 | H51: ='Fin Statement'!H131 -> 343479 | I51: ='Fin Statement'!I131 -> 442387 | J51: =I51-E51 -> 275845 | K51: =F51-E51 -> 39681 | L51: =G51-F51 -> 62254 | M51: =H51-G51 -> 75002 | N51: =I51-H51 -> 98908 | O51: =IF(J51>0,"Up",IF(J51<0,"Down","Flat")) -> Up | P51: {=IF(COUNT(K51:N51)<2,"n/a", IF(OR(COUNTIF(K51:N51,">0")=COUNT(K51:N51),COUNTIF(K51:N51,"<0")=COUNT(K51:N51)), IF(COUNTIF(K51:N51,">0")=COUNT(K51:N51),"Persistent rise – ","Persistent decline – ")& IF(ABS(N51)>1.25*SUMPRODUCT(ABS(IFERROR(K51:M51*1,0)))/COUNT(K51:M51),"accelerating", IF(ABS(N51)<0.75*SUMPRODUCT(ABS(IFERROR(K51:M51*1,0)))/COUNT(K51:M51),"decelerating","steady pace")), IF(SUMPRODUCT(--(IFERROR(K51:M51*L51:N51,0)<0))=1, IF(INDEX(K51:N51,MATCH(TRUE,INDEX(ISNUMBER(K51:N51),0),0))>0,"Reversing – peak ","Reversing – trough ")& INDEX($E$4:$I$4,MATCH(IF(INDEX(K51:N51,MATCH(TRUE,INDEX(ISNUMBER(K51:N51),0),0))>0,MAX(E51:I51),MIN(E51:I51)),E51:I51,0)), "Volatile – direction changed "&SUMPRODUCT(--(IFERROR(K51:M51*L51:N51,0)<0))&"x")))} -> Persistent rise – accelerating
B52: Debt-to-equity | E52: ='Common Size&Ratio'!E154 -> 0.29890958 | F52: ='Common Size&Ratio'!F154 -> 0.22905786 | G52: ='Common Size&Ratio'!G154 -> 0.19230698 | H52: ='Common Size&Ratio'!H154 -> 0.12562922 | I52: ='Common Size&Ratio'!I154 -> 0.091083147 | J52: =(I52-E52)*100 -> -20.782644 | K52: =(F52-E52)*100 -> -6.985172 | L52: =(G52-F52)*100 -> -3.6750889 | M52: =(H52-G52)*100 -> -6.6677753 | N52: =(I52-H52)*100 -> -3.4546077 | O52: =IF(J52>0,"Up",IF(J52<0,"Down","Flat")) -> Down | P52: {=IF(COUNT(K52:N52)<2,"n/a", IF(OR(COUNTIF(K52:N52,">0")=COUNT(K52:N52),COUNTIF(K52:N52,"<0")=COUNT(K52:N52)), IF(COUNTIF(K52:N52,">0")=COUNT(K52:N52),"Persistent rise – ","Persistent decline – ")& IF(ABS(N52)>1.25*SUMPRODUCT(ABS(IFERROR(K52:M52*1,0)))/COUNT(K52:M52),"accelerating", IF(ABS(N52)<0.75*SUMPRODUCT(ABS(IFERROR(K52:M52*1,0)))/COUNT(K52:M52),"decelerating","steady pace")), IF(SUMPRODUCT(--(IFERROR(K52:M52*L52:N52,0)<0))=1, IF(INDEX(K52:N52,MATCH(TRUE,INDEX(ISNUMBER(K52:N52),0),0))>0,"Reversing – peak ","Reversing – trough ")& INDEX($E$4:$I$4,MATCH(IF(INDEX(K52:N52,MATCH(TRUE,INDEX(ISNUMBER(K52:N52),0),0))>0,MAX(E52:I52),MIN(E52:I52)),E52:I52,0)), "Volatile – direction changed "&SUMPRODUCT(--(IFERROR(K52:M52*L52:N52,0)<0))&"x")))} -> Persistent decline – decelerating
B53: Debt-to-assets | E53: ='Common Size&Ratio'!E155 -> 0.13644611 | F53: ='Common Size&Ratio'!F155 -> 0.11465959 | G53: ='Common Size&Ratio'!G155 -> 0.10080775 | H53: ='Common Size&Ratio'!H155 -> 0.069710486 | I53: ='Common Size&Ratio'!I155 -> 0.053131956 | J53: =(I53-E53)*100 -> -8.3314158 | K53: =(F53-E53)*100 -> -2.1786522 | L53: =(G53-F53)*100 -> -1.3851841 | M53: =(H53-G53)*100 -> -3.1097265 | N53: =(I53-H53)*100 -> -1.657853 | O53: =IF(J53>0,"Up",IF(J53<0,"Down","Flat")) -> Down | P53: {=IF(COUNT(K53:N53)<2,"n/a", IF(OR(COUNTIF(K53:N53,">0")=COUNT(K53:N53),COUNTIF(K53:N53,"<0")=COUNT(K53:N53)), IF(COUNTIF(K53:N53,">0")=COUNT(K53:N53),"Persistent rise – ","Persistent decline – ")& IF(ABS(N53)>1.25*SUMPRODUCT(ABS(IFERROR(K53:M53*1,0)))/COUNT(K53:M53),"accelerating", IF(ABS(N53)<0.75*SUMPRODUCT(ABS(IFERROR(K53:M53*1,0)))/COUNT(K53:M53),"decelerating","steady pace")), IF(SUMPRODUCT(--(IFERROR(K53:M53*L53:N53,0)<0))=1, IF(INDEX(K53:N53,MATCH(TRUE,INDEX(ISNUMBER(K53:N53),0),0))>0,"Reversing – peak ","Reversing – trough ")& INDEX($E$4:$I$4,MATCH(IF(INDEX(K53:N53,MATCH(TRUE,INDEX(ISNUMBER(K53:N53),0),0))>0,MAX(E53:I53),MIN(E53:I53)),E53:I53,0)), "Volatile – direction changed "&SUMPRODUCT(--(IFERROR(K53:M53*L53:N53,0)<0))&"x")))} -> Persistent decline – decelerating
B54: CFO / debt | E54: ='Common Size&Ratio'!E156 -> 1.7885338 | F54: ='Common Size&Ratio'!F156 -> 1.8540974 | G54: ='Common Size&Ratio'!G156 -> 2.2961069 | H54: ='Common Size&Ratio'!H156 -> 3.1554773 | I54: ='Common Size&Ratio'!I156 -> 4.540006 | J54: =I54-E54 -> 2.7514722 | K54: =F54-E54 -> 0.065563646 | L54: =G54-F54 -> 0.44200949 | M54: =H54-G54 -> 0.85937036 | N54: =I54-H54 -> 1.3845287 | O54: =IF(J54>0,"Up",IF(J54<0,"Down","Flat")) -> Up | P54: {=IF(COUNT(K54:N54)<2,"n/a", IF(OR(COUNTIF(K54:N54,">0")=COUNT(K54:N54),COUNTIF(K54:N54,"<0")=COUNT(K54:N54)), IF(COUNTIF(K54:N54,">0")=COUNT(K54:N54),"Persistent rise – ","Persistent decline – ")& IF(ABS(N54)>1.25*SUMPRODUCT(ABS(IFERROR(K54:M54*1,0)))/COUNT(K54:M54),"accelerating", IF(ABS(N54)<0.75*SUMPRODUCT(ABS(IFERROR(K54:M54*1,0)))/COUNT(K54:M54),"decelerating","steady pace")), IF(SUMPRODUCT(--(IFERROR(K54:M54*L54:N54,0)<0))=1, IF(INDEX(K54:N54,MATCH(TRUE,INDEX(ISNUMBER(K54:N54),0),0))>0,"Reversing – peak ","Reversing – trough ")& INDEX($E$4:$I$4,MATCH(IF(INDEX(K54:N54,MATCH(TRUE,INDEX(ISNUMBER(K54:N54),0),0))>0,MAX(E54:I54),MIN(E54:I54)),E54:I54,0)), "Volatile – direction changed "&SUMPRODUCT(--(IFERROR(K54:M54*L54:N54,0)<0))&"x")))} -> Persistent rise – accelerating
B55: Interest expense ($m, absolute) | E55: =ABS('Fin Statement'!E24) -> 2063 | F55: =ABS('Fin Statement'!F24) -> 1968 | G55: =ABS('Fin Statement'!G24) -> 2935 | H55: =ABS('Fin Statement'!H24) -> 2385 | I55: =ABS('Fin Statement'!I24) -> 3051 | J55: =I55-E55 -> 988 | K55: =F55-E55 -> -95 | L55: =G55-F55 -> 967 | M55: =H55-G55 -> -550 | N55: =I55-H55 -> 666 | O55: =IF(J55>0,"Up",IF(J55<0,"Down","Flat")) -> Up | P55: {=IF(COUNT(K55:N55)<2,"n/a", IF(OR(COUNTIF(K55:N55,">0")=COUNT(K55:N55),COUNTIF(K55:N55,"<0")=COUNT(K55:N55)), IF(COUNTIF(K55:N55,">0")=COUNT(K55:N55),"Persistent rise – ","Persistent decline – ")& IF(ABS(N55)>1.25*SUMPRODUCT(ABS(IFERROR(K55:M55*1,0)))/COUNT(K55:M55),"accelerating", IF(ABS(N55)<0.75*SUMPRODUCT(ABS(IFERROR(K55:M55*1,0)))/COUNT(K55:M55),"decelerating","steady pace")), IF(SUMPRODUCT(--(IFERROR(K55:M55*L55:N55,0)<0))=1, IF(INDEX(K55:N55,MATCH(TRUE,INDEX(ISNUMBER(K55:N55),0),0))>0,"Reversing – peak ","Reversing – trough ")& INDEX($E$4:$I$4,MATCH(IF(INDEX(K55:N55,MATCH(TRUE,INDEX(ISNUMBER(K55:N55),0),0))>0,MAX(E55:I55),MIN(E55:I55)),E55:I55,0)), "Volatile – direction changed "&SUMPRODUCT(--(IFERROR(K55:M55*L55:N55,0)<0))&"x")))} -> Volatile – direction changed 3x
B56: Interest coverage (EBIT ÷ interest expense) | E56: ='Common Size&Ratio'!E157 -> 40.418323 | F56: ='Common Size&Ratio'!F157 -> 44.981199 | G56: ='Common Size&Ratio'!G157 -> 37.28552 | H56: ='Common Size&Ratio'!H157 -> 53.890147 | I56: ='Common Size&Ratio'!I157 -> 50.880695 | J56: =I56-E56 -> 10.462372 | K56: =F56-E56 -> 4.5628764 | L56: =G56-F56 -> -7.6956796 | M56: =H56-G56 -> 16.604627 | N56: =I56-H56 -> -3.0094519 | O56: =IF(J56>0,"Up",IF(J56<0,"Down","Flat")) -> Up | P56: {=IF(COUNT(K56:N56)<2,"n/a", IF(OR(COUNTIF(K56:N56,">0")=COUNT(K56:N56),COUNTIF(K56:N56,"<0")=COUNT(K56:N56)), IF(COUNTIF(K56:N56,">0")=COUNT(K56:N56),"Persistent rise – ","Persistent decline – ")& IF(ABS(N56)>1.25*SUMPRODUCT(ABS(IFERROR(K56:M56*1,0)))/COUNT(K56:M56),"accelerating", IF(ABS(N56)<0.75*SUMPRODUCT(ABS(IFERROR(K56:M56*1,0)))/COUNT(K56:M56),"decelerating","steady pace")), IF(SUMPRODUCT(--(IFERROR(K56:M56*L56:N56,0)<0))=1, IF(INDEX(K56:N56,MATCH(TRUE,INDEX(ISNUMBER(K56:N56),0),0))>0,"Reversing – peak ","Reversing – trough ")& INDEX($E$4:$I$4,MATCH(IF(INDEX(K56:N56,MATCH(TRUE,INDEX(ISNUMBER(K56:N56),0),0))>0,MAX(E56:I56),MIN(E56:I56)),E56:I56,0)), "Volatile – direction changed "&SUMPRODUCT(--(IFERROR(K56:M56*L56:N56,0)<0))&"x")))} -> Volatile – direction changed 3x
B57: Current ratio | E57: ='Common Size&Ratio'!E149 -> 1.784607 | F57: ='Common Size&Ratio'!F149 -> 1.7691673 | G57: ='Common Size&Ratio'!G149 -> 1.2749549 | H57: ='Common Size&Ratio'!H149 -> 1.3534464 | I57: ='Common Size&Ratio'!I149 -> 1.2303273 | J57: =I57-E57 -> -0.55427971 | K57: =F57-E57 -> -0.01543972 | L57: =G57-F57 -> -0.49421235 | M57: =H57-G57 -> 0.078491541 | N57: =I57-H57 -> -0.12311918 | O57: =IF(J57>0,"Up",IF(J57<0,"Down","Flat")) -> Down | P57: {=IF(COUNT(K57:N57)<2,"n/a", IF(OR(COUNTIF(K57:N57,">0")=COUNT(K57:N57),COUNTIF(K57:N57,"<0")=COUNT(K57:N57)), IF(COUNTIF(K57:N57,">0")=COUNT(K57:N57),"Persistent rise – ","Persistent decline – ")& IF(ABS(N57)>1.25*SUMPRODUCT(ABS(IFERROR(K57:M57*1,0)))/COUNT(K57:M57),"accelerating", IF(ABS(N57)<0.75*SUMPRODUCT(ABS(IFERROR(K57:M57*1,0)))/COUNT(K57:M57),"decelerating","steady pace")), IF(SUMPRODUCT(--(IFERROR(K57:M57*L57:N57,0)<0))=1, IF(INDEX(K57:N57,MATCH(TRUE,INDEX(ISNUMBER(K57:N57),0),0))>0,"Reversing – peak ","Reversing – trough ")& INDEX($E$4:$I$4,MATCH(IF(INDEX(K57:N57,MATCH(TRUE,INDEX(ISNUMBER(K57:N57),0),0))>0,MAX(E57:I57),MIN(E57:I57)),E57:I57,0)), "Volatile – direction changed "&SUMPRODUCT(--(IFERROR(K57:M57*L57:N57,0)<0))&"x")))} -> Volatile – direction changed 2x
B58: Cash ratio | E58: ='Common Size&Ratio'!E151 -> 1.1017543 | F58: ='Common Size&Ratio'!F151 -> 1.0682964 | G58: ='Common Size&Ratio'!G151 -> 0.60296442 | H58: ='Common Size&Ratio'!H151 -> 0.66963843 | I58: ='Common Size&Ratio'!I151 -> 0.45516363 | J58: =I58-E58 -> -0.64659064 | K58: =F58-E58 -> -0.033457892 | L58: =G58-F58 -> -0.46533197 | M58: =H58-G58 -> 0.066674014 | N58: =I58-H58 -> -0.2144748 | O58: =IF(J58>0,"Up",IF(J58<0,"Down","Flat")) -> Down | P58: {=IF(COUNT(K58:N58)<2,"n/a", IF(OR(COUNTIF(K58:N58,">0")=COUNT(K58:N58),COUNTIF(K58:N58,"<0")=COUNT(K58:N58)), IF(COUNTIF(K58:N58,">0")=COUNT(K58:N58),"Persistent rise – ","Persistent decline – ")& IF(ABS(N58)>1.25*SUMPRODUCT(ABS(IFERROR(K58:M58*1,0)))/COUNT(K58:M58),"accelerating", IF(ABS(N58)<0.75*SUMPRODUCT(ABS(IFERROR(K58:M58*1,0)))/COUNT(K58:M58),"decelerating","steady pace")), IF(SUMPRODUCT(--(IFERROR(K58:M58*L58:N58,0)<0))=1, IF(INDEX(K58:N58,MATCH(TRUE,INDEX(ISNUMBER(K58:N58),0),0))>0,"Reversing – peak ","Reversing – trough ")& INDEX($E$4:$I$4,MATCH(IF(INDEX(K58:N58,MATCH(TRUE,INDEX(ISNUMBER(K58:N58),0),0))>0,MAX(E58:I58),MIN(E58:I58)),E58:I58,0)), "Volatile – direction changed "&SUMPRODUCT(--(IFERROR(K58:M58*L58:N58,0)<0))&"x")))} -> Volatile – direction changed 2x
B59: Net debt issuance / (repayment) ($m) | E59: ='Fin Statement'!E76 -> -9023 | F59: ='Fin Statement'!F76 -> -2750 | G59: ='Fin Statement'!G76 -> 575 | H59: ='Fin Statement'!H76 -> -8962 | I59: ='Fin Statement'!I76 -> -3000 | J59: =I59-E59 -> 6023 | K59: =F59-E59 -> 6273 | L59: =G59-F59 -> 3325 | M59: =H59-G59 -> -9537 | N59: =I59-H59 -> 5962 | O59: =IF(J59>0,"Up",IF(J59<0,"Down","Flat")) -> Up | P59: {=IF(COUNT(K59:N59)<2,"n/a", IF(OR(COUNTIF(K59:N59,">0")=COUNT(K59:N59),COUNTIF(K59:N59,"<0")=COUNT(K59:N59)), IF(COUNTIF(K59:N59,">0")=COUNT(K59:N59),"Persistent rise – ","Persistent decline – ")& IF(ABS(N59)>1.25*SUMPRODUCT(ABS(IFERROR(K59:M59*1,0)))/COUNT(K59:M59),"accelerating", IF(ABS(N59)<0.75*SUMPRODUCT(ABS(IFERROR(K59:M59*1,0)))/COUNT(K59:M59),"decelerating","steady pace")), IF(SUMPRODUCT(--(IFERROR(K59:M59*L59:N59,0)<0))=1, IF(INDEX(K59:N59,MATCH(TRUE,INDEX(ISNUMBER(K59:N59),0),0))>0,"Reversing – peak ","Reversing – trough ")& INDEX($E$4:$I$4,MATCH(IF(INDEX(K59:N59,MATCH(TRUE,INDEX(ISNUMBER(K59:N59),0),0))>0,MAX(E59:I59),MIN(E59:I59)),E59:I59,0)), "Volatile – direction changed "&SUMPRODUCT(--(IFERROR(K59:M59*L59:N59,0)<0))&"x")))} -> Volatile – direction changed 2x
B60: Net share issuance / (repurchase) ($m) | E60: ='Fin Statement'!E77 -> -30855 | F60: ='Fin Statement'!F77 -> -20379 | G60: ='Fin Statement'!G77 -> -15252 | H60: ='Fin Statement'!H77 -> -16364 | I60: ='Fin Statement'!I77 -> -20262 | J60: =I60-E60 -> 10593 | K60: =F60-E60 -> 10476 | L60: =G60-F60 -> 5127 | M60: =H60-G60 -> -1112 | N60: =I60-H60 -> -3898 | O60: =IF(J60>0,"Up",IF(J60<0,"Down","Flat")) -> Up | P60: {=IF(COUNT(K60:N60)<2,"n/a", IF(OR(COUNTIF(K60:N60,">0")=COUNT(K60:N60),COUNTIF(K60:N60,"<0")=COUNT(K60:N60)), IF(COUNTIF(K60:N60,">0")=COUNT(K60:N60),"Persistent rise – ","Persistent decline – ")& IF(ABS(N60)>1.25*SUMPRODUCT(ABS(IFERROR(K60:M60*1,0)))/COUNT(K60:M60),"accelerating", IF(ABS(N60)<0.75*SUMPRODUCT(ABS(IFERROR(K60:M60*1,0)))/COUNT(K60:M60),"decelerating","steady pace")), IF(SUMPRODUCT(--(IFERROR(K60:M60*L60:N60,0)<0))=1, IF(INDEX(K60:N60,MATCH(TRUE,INDEX(ISNUMBER(K60:N60),0),0))>0,"Reversing – peak ","Reversing – trough ")& INDEX($E$4:$I$4,MATCH(IF(INDEX(K60:N60,MATCH(TRUE,INDEX(ISNUMBER(K60:N60),0),0))>0,MAX(E60:I60),MIN(E60:I60)),E60:I60,0)), "Volatile – direction changed "&SUMPRODUCT(--(IFERROR(K60:M60*L60:N60,0)<0))&"x")))} -> Reversing – peak 2024
B62: Business Mix
B63: PBP — revenue ($m) | E63: ='Fin Statement'!E35 -> 63364 | F63: ='Fin Statement'!F35 -> 94151 | G63: ='Fin Statement'!G35 -> 106820 | H63: ='Fin Statement'!H35 -> 120810 | I63: ='Fin Statement'!I35 -> 139996 | J63: =(I63-E63) -> 76632 | K63: =(F63-E63) -> 30787 | L63: =(G63-F63) -> 12669 | M63: =(H63-G63) -> 13990 | N63: =(I63-H63) -> 19186 | O63: =IF(J63>0,"Up",IF(J63<0,"Down","Flat")) -> Up | P63: {=IF(COUNT(K63:N63)<2,"n/a", IF(OR(COUNTIF(K63:N63,">0")=COUNT(K63:N63),COUNTIF(K63:N63,"<0")=COUNT(K63:N63)), IF(COUNTIF(K63:N63,">0")=COUNT(K63:N63),"Persistent rise – ","Persistent decline – ")& IF(ABS(N63)>1.25*SUMPRODUCT(ABS(IFERROR(K63:M63*1,0)))/COUNT(K63:M63),"accelerating", IF(ABS(N63)<0.75*SUMPRODUCT(ABS(IFERROR(K63:M63*1,0)))/COUNT(K63:M63),"decelerating","steady pace")), IF(SUMPRODUCT(--(IFERROR(K63:M63*L63:N63,0)<0))=1, IF(INDEX(K63:N63,MATCH(TRUE,INDEX(ISNUMBER(K63:N63),0),0))>0,"Reversing – peak ","Reversing – trough ")& INDEX($E$4:$I$4,MATCH(IF(INDEX(K63:N63,MATCH(TRUE,INDEX(ISNUMBER(K63:N63),0),0))>0,MAX(E63:I63),MIN(E63:I63)),E63:I63,0)), "Volatile – direction changed "&SUMPRODUCT(--(IFERROR(K63:M63*L63:N63,0)<0))&"x")))} -> Persistent rise – steady pace
B64: Intelligent Cloud — revenue ($m) | E64: ='Fin Statement'!E36 -> 74965 | F64: ='Fin Statement'!F36 -> 72944 | G64: ='Fin Statement'!G36 -> 87464 | H64: ='Fin Statement'!H36 -> 106265 | I64: ='Fin Statement'!I36 -> 137791 | J64: =(I64-E64) -> 62826 | K64: =(F64-E64) -> -2021 | L64: =(G64-F64) -> 14520 | M64: =(H64-G64) -> 18801 | N64: =(I64-H64) -> 31526 | O64: =IF(J64>0,"Up",IF(J64<0,"Down","Flat")) -> Up | P64: {=IF(COUNT(K64:N64)<2,"n/a", IF(OR(COUNTIF(K64:N64,">0")=COUNT(K64:N64),COUNTIF(K64:N64,"<0")=COUNT(K64:N64)), IF(COUNTIF(K64:N64,">0")=COUNT(K64:N64),"Persistent rise – ","Persistent decline – ")& IF(ABS(N64)>1.25*SUMPRODUCT(ABS(IFERROR(K64:M64*1,0)))/COUNT(K64:M64),"accelerating", IF(ABS(N64)<0.75*SUMPRODUCT(ABS(IFERROR(K64:M64*1,0)))/COUNT(K64:M64),"decelerating","steady pace")), IF(SUMPRODUCT(--(IFERROR(K64:M64*L64:N64,0)<0))=1, IF(INDEX(K64:N64,MATCH(TRUE,INDEX(ISNUMBER(K64:N64),0),0))>0,"Reversing – peak ","Reversing – trough ")& INDEX($E$4:$I$4,MATCH(IF(INDEX(K64:N64,MATCH(TRUE,INDEX(ISNUMBER(K64:N64),0),0))>0,MAX(E64:I64),MIN(E64:I64)),E64:I64,0)), "Volatile – direction changed "&SUMPRODUCT(--(IFERROR(K64:M64*L64:N64,0)<0))&"x")))} -> Reversing – trough 2023
B65: MPC — revenue ($m) | E65: ='Fin Statement'!E37 -> 59941 | F65: ='Fin Statement'!F37 -> 44820 | G65: ='Fin Statement'!G37 -> 50838 | H65: ='Fin Statement'!H37 -> 54649 | I65: ='Fin Statement'!I37 -> 54052 | J65: =(I65-E65) -> -5889 | K65: =(F65-E65) -> -15121 | L65: =(G65-F65) -> 6018 | M65: =(H65-G65) -> 3811 | N65: =(I65-H65) -> -597 | O65: =IF(J65>0,"Up",IF(J65<0,"Down","Flat")) -> Down | P65: {=IF(COUNT(K65:N65)<2,"n/a", IF(OR(COUNTIF(K65:N65,">0")=COUNT(K65:N65),COUNTIF(K65:N65,"<0")=COUNT(K65:N65)), IF(COUNTIF(K65:N65,">0")=COUNT(K65:N65),"Persistent rise – ","Persistent decline – ")& IF(ABS(N65)>1.25*SUMPRODUCT(ABS(IFERROR(K65:M65*1,0)))/COUNT(K65:M65),"accelerating", IF(ABS(N65)<0.75*SUMPRODUCT(ABS(IFERROR(K65:M65*1,0)))/COUNT(K65:M65),"decelerating","steady pace")), IF(SUMPRODUCT(--(IFERROR(K65:M65*L65:N65,0)<0))=1, IF(INDEX(K65:N65,MATCH(TRUE,INDEX(ISNUMBER(K65:N65),0),0))>0,"Reversing – peak ","Reversing – trough ")& INDEX($E$4:$I$4,MATCH(IF(INDEX(K65:N65,MATCH(TRUE,INDEX(ISNUMBER(K65:N65),0),0))>0,MAX(E65:I65),MIN(E65:I65)),E65:I65,0)), "Volatile – direction changed "&SUMPRODUCT(--(IFERROR(K65:M65*L65:N65,0)<0))&"x")))} -> Volatile – direction changed 2x
B66: PBP — operating income ($m) | E66: ='Fin Statement'!E41 -> 29690 | F66: ='Fin Statement'!F41 -> 50074 | G66: ='Fin Statement'!G41 -> 59661 | H66: ='Fin Statement'!H41 -> 69773 | I66: ='Fin Statement'!I41 -> 83879 | J66: =(I66-E66) -> 54189 | K66: =(F66-E66) -> 20384 | L66: =(G66-F66) -> 9587 | M66: =(H66-G66) -> 10112 | N66: =(I66-H66) -> 14106 | O66: =IF(J66>0,"Up",IF(J66<0,"Down","Flat")) -> Up | P66: {=IF(COUNT(K66:N66)<2,"n/a", IF(OR(COUNTIF(K66:N66,">0")=COUNT(K66:N66),COUNTIF(K66:N66,"<0")=COUNT(K66:N66)), IF(COUNTIF(K66:N66,">0")=COUNT(K66:N66),"Persistent rise – ","Persistent decline – ")& IF(ABS(N66)>1.25*SUMPRODUCT(ABS(IFERROR(K66:M66*1,0)))/COUNT(K66:M66),"accelerating", IF(ABS(N66)<0.75*SUMPRODUCT(ABS(IFERROR(K66:M66*1,0)))/COUNT(K66:M66),"decelerating","steady pace")), IF(SUMPRODUCT(--(IFERROR(K66:M66*L66:N66,0)<0))=1, IF(INDEX(K66:N66,MATCH(TRUE,INDEX(ISNUMBER(K66:N66),0),0))>0,"Reversing – peak ","Reversing – trough ")& INDEX($E$4:$I$4,MATCH(IF(INDEX(K66:N66,MATCH(TRUE,INDEX(ISNUMBER(K66:N66),0),0))>0,MAX(E66:I66),MIN(E66:I66)),E66:I66,0)), "Volatile – direction changed "&SUMPRODUCT(--(IFERROR(K66:M66*L66:N66,0)<0))&"x")))} -> Persistent rise – steady pace
B67: Intelligent Cloud — operating income ($m) | E67: ='Fin Statement'!E42 -> 33203 | F67: ='Fin Statement'!F42 -> 28411 | G67: ='Fin Statement'!G42 -> 37813 | H67: ='Fin Statement'!H42 -> 44589 | I67: ='Fin Statement'!I42 -> 56972 | J67: =(I67-E67) -> 23769 | K67: =(F67-E67) -> -4792 | L67: =(G67-F67) -> 9402 | M67: =(H67-G67) -> 6776 | N67: =(I67-H67) -> 12383 | O67: =IF(J67>0,"Up",IF(J67<0,"Down","Flat")) -> Up | P67: {=IF(COUNT(K67:N67)<2,"n/a", IF(OR(COUNTIF(K67:N67,">0")=COUNT(K67:N67),COUNTIF(K67:N67,"<0")=COUNT(K67:N67)), IF(COUNTIF(K67:N67,">0")=COUNT(K67:N67),"Persistent rise – ","Persistent decline – ")& IF(ABS(N67)>1.25*SUMPRODUCT(ABS(IFERROR(K67:M67*1,0)))/COUNT(K67:M67),"accelerating", IF(ABS(N67)<0.75*SUMPRODUCT(ABS(IFERROR(K67:M67*1,0)))/COUNT(K67:M67),"decelerating","steady pace")), IF(SUMPRODUCT(--(IFERROR(K67:M67*L67:N67,0)<0))=1, IF(INDEX(K67:N67,MATCH(TRUE,INDEX(ISNUMBER(K67:N67),0),0))>0,"Reversing – peak ","Reversing – trough ")& INDEX($E$4:$I$4,MATCH(IF(INDEX(K67:N67,MATCH(TRUE,INDEX(ISNUMBER(K67:N67),0),0))>0,MAX(E67:I67),MIN(E67:I67)),E67:I67,0)), "Volatile – direction changed "&SUMPRODUCT(--(IFERROR(K67:M67*L67:N67,0)<0))&"x")))} -> Reversing – trough 2023
B68: MPC — operating income ($m) | E68: ='Fin Statement'!E43 -> 20490 | F68: ='Fin Statement'!F43 -> 10038 | G68: ='Fin Statement'!G43 -> 11959 | H68: ='Fin Statement'!H43 -> 14166 | I68: ='Fin Statement'!I43 -> 14386 | J68: =(I68-E68) -> -6104 | K68: =(F68-E68) -> -10452 | L68: =(G68-F68) -> 1921 | M68: =(H68-G68) -> 2207 | N68: =(I68-H68) -> 220 | O68: =IF(J68>0,"Up",IF(J68<0,"Down","Flat")) -> Down | P68: {=IF(COUNT(K68:N68)<2,"n/a", IF(OR(COUNTIF(K68:N68,">0")=COUNT(K68:N68),COUNTIF(K68:N68,"<0")=COUNT(K68:N68)), IF(COUNTIF(K68:N68,">0")=COUNT(K68:N68),"Persistent rise – ","Persistent decline – ")& IF(ABS(N68)>1.25*SUMPRODUCT(ABS(IFERROR(K68:M68*1,0)))/COUNT(K68:M68),"accelerating", IF(ABS(N68)<0.75*SUMPRODUCT(ABS(IFERROR(K68:M68*1,0)))/COUNT(K68:M68),"decelerating","steady pace")), IF(SUMPRODUCT(--(IFERROR(K68:M68*L68:N68,0)<0))=1, IF(INDEX(K68:N68,MATCH(TRUE,INDEX(ISNUMBER(K68:N68),0),0))>0,"Reversing – peak ","Reversing – trough ")& INDEX($E$4:$I$4,MATCH(IF(INDEX(K68:N68,MATCH(TRUE,INDEX(ISNUMBER(K68:N68),0),0))>0,MAX(E68:I68),MIN(E68:I68)),E68:I68,0)), "Volatile – direction changed "&SUMPRODUCT(--(IFERROR(K68:M68*L68:N68,0)<0))&"x")))} -> Reversing – trough 2023
B69: PBP — revenue growth (YoY) | E69: =IF(OR(D63="",E63=""),,E63/D63-1) -> 0 | F69: =IF(OR(E63="",F63=""),,F63/E63-1) -> 0.48587526 | G69: =IF(OR(F63="",G63=""),,G63/F63-1) -> 0.13456044 | H69: =IF(OR(G63="",H63=""),,H63/G63-1) -> 0.13096798 | I69: =IF(OR(H63="",I63=""),,I63/H63-1) -> 0.15881136 | J69: =(I69-E69)*100 -> 15.881136 | K69: =(F69-E69)*100 -> 48.587526 | L69: =(G69-F69)*100 -> -35.131482 | M69: =(H69-G69)*100 -> -0.35924566 | N69: =(I69-H69)*100 -> 2.7843373 | O69: =IF(J69>0,"Up",IF(J69<0,"Down","Flat")) -> Up | P69: {=IF(COUNT(K69:N69)<2,"n/a", IF(OR(COUNTIF(K69:N69,">0")=COUNT(K69:N69),COUNTIF(K69:N69,"<0")=COUNT(K69:N69)), IF(COUNTIF(K69:N69,">0")=COUNT(K69:N69),"Persistent rise – ","Persistent decline – ")& IF(ABS(N69)>1.25*SUMPRODUCT(ABS(IFERROR(K69:M69*1,0)))/COUNT(K69:M69),"accelerating", IF(ABS(N69)<0.75*SUMPRODUCT(ABS(IFERROR(K69:M69*1,0)))/COUNT(K69:M69),"decelerating","steady pace")), IF(SUMPRODUCT(--(IFERROR(K69:M69*L69:N69,0)<0))=1, IF(INDEX(K69:N69,MATCH(TRUE,INDEX(ISNUMBER(K69:N69),0),0))>0,"Reversing – peak ","Reversing – trough ")& INDEX($E$4:$I$4,MATCH(IF(INDEX(K69:N69,MATCH(TRUE,INDEX(ISNUMBER(K69:N69),0),0))>0,MAX(E69:I69),MIN(E69:I69)),E69:I69,0)), "Volatile – direction changed "&SUMPRODUCT(--(IFERROR(K69:M69*L69:N69,0)<0))&"x")))} -> Volatile – direction changed 2x
B70: Intelligent Cloud — revenue growth (YoY) | E70: =IF(OR(D64="",E64=""),,E64/D64-1) -> 0 | F70: =IF(OR(E64="",F64=""),,F64/E64-1) -> -0.026959248 | G70: =IF(OR(F64="",G64=""),,G64/F64-1) -> 0.19905681 | H70: =IF(OR(G64="",H64=""),,H64/G64-1) -> 0.21495701 | I70: =IF(OR(H64="",I64=""),,I64/H64-1) -> 0.29667341 | J70: =(I70-E70)*100 -> 29.667341 | K70: =(F70-E70)*100 -> -2.6959248 | L70: =(G70-F70)*100 -> 22.601606 | M70: =(H70-G70)*100 -> 1.59002 | N70: =(I70-H70)*100 -> 8.17164 | O70: =IF(J70>0,"Up",IF(J70<0,"Down","Flat")) -> Up | P70: {=IF(COUNT(K70:N70)<2,"n/a", IF(OR(COUNTIF(K70:N70,">0")=COUNT(K70:N70),COUNTIF(K70:N70,"<0")=COUNT(K70:N70)), IF(COUNTIF(K70:N70,">0")=COUNT(K70:N70),"Persistent rise – ","Persistent decline – ")& IF(ABS(N70)>1.25*SUMPRODUCT(ABS(IFERROR(K70:M70*1,0)))/COUNT(K70:M70),"accelerating", IF(ABS(N70)<0.75*SUMPRODUCT(ABS(IFERROR(K70:M70*1,0)))/COUNT(K70:M70),"decelerating","steady pace")), IF(SUMPRODUCT(--(IFERROR(K70:M70*L70:N70,0)<0))=1, IF(INDEX(K70:N70,MATCH(TRUE,INDEX(ISNUMBER(K70:N70),0),0))>0,"Reversing – peak ","Reversing – trough ")& INDEX($E$4:$I$4,MATCH(IF(INDEX(K70:N70,MATCH(TRUE,INDEX(ISNUMBER(K70:N70),0),0))>0,MAX(E70:I70),MIN(E70:I70)),E70:I70,0)), "Volatile – direction changed "&SUMPRODUCT(--(IFERROR(K70:M70*L70:N70,0)<0))&"x")))} -> Reversing – trough 2023
B71: MPC — revenue growth (YoY) | E71: =IF(OR(D65="",E65=""),,E65/D65-1) -> 0 | F71: =IF(OR(E65="",F65=""),,F65/E65-1) -> -0.25226473 | G71: =IF(OR(F65="",G65=""),,G65/F65-1) -> 0.13427041 | H71: =IF(OR(G65="",H65=""),,H65/G65-1) -> 0.07496361 | I71: =IF(OR(H65="",I65=""),,I65/H65-1) -> -0.010924262 | J71: =(I71-E71)*100 -> -1.0924262 | K71: =(F71-E71)*100 -> -25.226473 | L71: =(G71-F71)*100 -> 38.653514 | M71: =(H71-G71)*100 -> -5.9306805 | N71: =(I71-H71)*100 -> -8.5887872 | O71: =IF(J71>0,"Up",IF(J71<0,"Down","Flat")) -> Down | P71: {=IF(COUNT(K71:N71)<2,"n/a", IF(OR(COUNTIF(K71:N71,">0")=COUNT(K71:N71),COUNTIF(K71:N71,"<0")=COUNT(K71:N71)), IF(COUNTIF(K71:N71,">0")=COUNT(K71:N71),"Persistent rise – ","Persistent decline – ")& IF(ABS(N71)>1.25*SUMPRODUCT(ABS(IFERROR(K71:M71*1,0)))/COUNT(K71:M71),"accelerating", IF(ABS(N71)<0.75*SUMPRODUCT(ABS(IFERROR(K71:M71*1,0)))/COUNT(K71:M71),"decelerating","steady pace")), IF(SUMPRODUCT(--(IFERROR(K71:M71*L71:N71,0)<0))=1, IF(INDEX(K71:N71,MATCH(TRUE,INDEX(ISNUMBER(K71:N71),0),0))>0,"Reversing – peak ","Reversing – trough ")& INDEX($E$4:$I$4,MATCH(IF(INDEX(K71:N71,MATCH(TRUE,INDEX(ISNUMBER(K71:N71),0),0))>0,MAX(E71:I71),MIN(E71:I71)),E71:I71,0)), "Volatile – direction changed "&SUMPRODUCT(--(IFERROR(K71:M71*L71:N71,0)<0))&"x")))} -> Volatile – direction changed 2x
B72: PBP — operating income growth (YoY) | E72: =IF(OR(D66="",E66=""),,E66/D66-1) -> 0 | F72: =IF(OR(E66="",F66=""),,F66/E66-1) -> 0.68656113 | G72: =IF(OR(F66="",G66=""),,G66/F66-1) -> 0.19145664 | H72: =IF(OR(G66="",H66=""),,H66/G66-1) -> 0.16949096 | I72: =IF(OR(H66="",I66=""),,I66/H66-1) -> 0.20216989 | J72: =(I72-E72)*100 -> 20.216989 | K72: =(F72-E72)*100 -> 68.656113 | L72: =(G72-F72)*100 -> -49.510449 | M72: =(H72-G72)*100 -> -2.1965687 | N72: =(I72-H72)*100 -> 3.2678937 | O72: =IF(J72>0,"Up",IF(J72<0,"Down","Flat")) -> Up | P72: {=IF(COUNT(K72:N72)<2,"n/a", IF(OR(COUNTIF(K72:N72,">0")=COUNT(K72:N72),COUNTIF(K72:N72,"<0")=COUNT(K72:N72)), IF(COUNTIF(K72:N72,">0")=COUNT(K72:N72),"Persistent rise – ","Persistent decline – ")& IF(ABS(N72)>1.25*SUMPRODUCT(ABS(IFERROR(K72:M72*1,0)))/COUNT(K72:M72),"accelerating", IF(ABS(N72)<0.75*SUMPRODUCT(ABS(IFERROR(K72:M72*1,0)))/COUNT(K72:M72),"decelerating","steady pace")), IF(SUMPRODUCT(--(IFERROR(K72:M72*L72:N72,0)<0))=1, IF(INDEX(K72:N72,MATCH(TRUE,INDEX(ISNUMBER(K72:N72),0),0))>0,"Reversing – peak ","Reversing – trough ")& INDEX($E$4:$I$4,MATCH(IF(INDEX(K72:N72,MATCH(TRUE,INDEX(ISNUMBER(K72:N72),0),0))>0,MAX(E72:I72),MIN(E72:I72)),E72:I72,0)), "Volatile – direction changed "&SUMPRODUCT(--(IFERROR(K72:M72*L72:N72,0)<0))&"x")))} -> Volatile – direction changed 2x
B73: Intelligent Cloud — operating income growth (YoY) | E73: =IF(OR(D67="",E67=""),,E67/D67-1) -> 0 | F73: =IF(OR(E67="",F67=""),,F67/E67-1) -> -0.14432431 | G73: =IF(OR(F67="",G67=""),,G67/F67-1) -> 0.33092816 | H73: =IF(OR(G67="",H67=""),,H67/G67-1) -> 0.17919763 | I73: =IF(OR(H67="",I67=""),,I67/H67-1) -> 0.27771423 | J73: =(I73-E73)*100 -> 27.771423 | K73: =(F73-E73)*100 -> -14.432431 | L73: =(G73-F73)*100 -> 47.525247 | M73: =(H73-G73)*100 -> -15.173053 | N73: =(I73-H73)*100 -> 9.8516604 | O73: =IF(J73>0,"Up",IF(J73<0,"Down","Flat")) -> Up | P73: {=IF(COUNT(K73:N73)<2,"n/a", IF(OR(COUNTIF(K73:N73,">0")=COUNT(K73:N73),COUNTIF(K73:N73,"<0")=COUNT(K73:N73)), IF(COUNTIF(K73:N73,">0")=COUNT(K73:N73),"Persistent rise – ","Persistent decline – ")& IF(ABS(N73)>1.25*SUMPRODUCT(ABS(IFERROR(K73:M73*1,0)))/COUNT(K73:M73),"accelerating", IF(ABS(N73)<0.75*SUMPRODUCT(ABS(IFERROR(K73:M73*1,0)))/COUNT(K73:M73),"decelerating","steady pace")), IF(SUMPRODUCT(--(IFERROR(K73:M73*L73:N73,0)<0))=1, IF(INDEX(K73:N73,MATCH(TRUE,INDEX(ISNUMBER(K73:N73),0),0))>0,"Reversing – peak ","Reversing – trough ")& INDEX($E$4:$I$4,MATCH(IF(INDEX(K73:N73,MATCH(TRUE,INDEX(ISNUMBER(K73:N73),0),0))>0,MAX(E73:I73),MIN(E73:I73)),E73:I73,0)), "Volatile – direction changed "&SUMPRODUCT(--(IFERROR(K73:M73*L73:N73,0)<0))&"x")))} -> Volatile – direction changed 3x
B74: MPC — operating income growth (YoY) | E74: =IF(OR(D68="",E68=""),,E68/D68-1) -> 0 | F74: =IF(OR(E68="",F68=""),,F68/E68-1) -> -0.51010249 | G74: =IF(OR(F68="",G68=""),,G68/F68-1) -> 0.19137278 | H74: =IF(OR(G68="",H68=""),,H68/G68-1) -> 0.1845472 | I74: =IF(OR(H68="",I68=""),,I68/H68-1) -> 0.015530143 | J74: =(I74-E74)*100 -> 1.5530143 | K74: =(F74-E74)*100 -> -51.010249 | L74: =(G74-F74)*100 -> 70.147527 | M74: =(H74-G74)*100 -> -0.68255805 | N74: =(I74-H74)*100 -> -16.901706 | O74: =IF(J74>0,"Up",IF(J74<0,"Down","Flat")) -> Up | P74: {=IF(COUNT(K74:N74)<2,"n/a", IF(OR(COUNTIF(K74:N74,">0")=COUNT(K74:N74),COUNTIF(K74:N74,"<0")=COUNT(K74:N74)), IF(COUNTIF(K74:N74,">0")=COUNT(K74:N74),"Persistent rise – ","Persistent decline – ")& IF(ABS(N74)>1.25*SUMPRODUCT(ABS(IFERROR(K74:M74*1,0)))/COUNT(K74:M74),"accelerating", IF(ABS(N74)<0.75*SUMPRODUCT(ABS(IFERROR(K74:M74*1,0)))/COUNT(K74:M74),"decelerating","steady pace")), IF(SUMPRODUCT(--(IFERROR(K74:M74*L74:N74,0)<0))=1, IF(INDEX(K74:N74,MATCH(TRUE,INDEX(ISNUMBER(K74:N74),0),0))>0,"Reversing – peak ","Reversing – trough ")& INDEX($E$4:$I$4,MATCH(IF(INDEX(K74:N74,MATCH(TRUE,INDEX(ISNUMBER(K74:N74),0),0))>0,MAX(E74:I74),MIN(E74:I74)),E74:I74,0)), "Volatile – direction changed "&SUMPRODUCT(--(IFERROR(K74:M74*L74:N74,0)<0))&"x")))} -> Volatile – direction changed 2x
B75: PBP — operating margin | E75: =E66/E63 -> 0.46856259 | F75: =F66/F63 -> 0.53184778 | G75: =G66/G63 -> 0.558519 | H75: =H66/H63 -> 0.57754325 | I75: =I66/I63 -> 0.59915283 | J75: =(I75-E75)*100 -> 13.059024 | K75: =(F75-E75)*100 -> 6.3285186 | L75: =(G75-F75)*100 -> 2.6671227 | M75: =(H75-G75)*100 -> 1.9024246 | N75: =(I75-H75)*100 -> 2.1609583 | O75: =IF(J75>0,"Up",IF(J75<0,"Down","Flat")) -> Up | P75: {=IF(COUNT(K75:N75)<2,"n/a", IF(OR(COUNTIF(K75:N75,">0")=COUNT(K75:N75),COUNTIF(K75:N75,"<0")=COUNT(K75:N75)), IF(COUNTIF(K75:N75,">0")=COUNT(K75:N75),"Persistent rise – ","Persistent decline – ")& IF(ABS(N75)>1.25*SUMPRODUCT(ABS(IFERROR(K75:M75*1,0)))/COUNT(K75:M75),"accelerating", IF(ABS(N75)<0.75*SUMPRODUCT(ABS(IFERROR(K75:M75*1,0)))/COUNT(K75:M75),"decelerating","steady pace")), IF(SUMPRODUCT(--(IFERROR(K75:M75*L75:N75,0)<0))=1, IF(INDEX(K75:N75,MATCH(TRUE,INDEX(ISNUMBER(K75:N75),0),0))>0,"Reversing – peak ","Reversing – trough ")& INDEX($E$4:$I$4,MATCH(IF(INDEX(K75:N75,MATCH(TRUE,INDEX(ISNUMBER(K75:N75),0),0))>0,MAX(E75:I75),MIN(E75:I75)),E75:I75,0)), "Volatile – direction changed "&SUMPRODUCT(--(IFERROR(K75:M75*L75:N75,0)<0))&"x")))} -> Persistent rise – decelerating
B76: Intelligent Cloud — operating margin | E76: =E67/E64 -> 0.44291336 | F76: =F67/F64 -> 0.38949057 | G76: =G67/G64 -> 0.43232644 | H76: =H67/H64 -> 0.41960194 | I76: =I67/I64 -> 0.41346677 | J76: =(I76-E76)*100 -> -2.9446587 | K76: =(F76-E76)*100 -> -5.3422791 | L76: =(G76-F76)*100 -> 4.2835875 | M76: =(H76-G76)*100 -> -1.2724504 | N76: =(I76-H76)*100 -> -0.61351664 | O76: =IF(J76>0,"Up",IF(J76<0,"Down","Flat")) -> Down | P76: {=IF(COUNT(K76:N76)<2,"n/a", IF(OR(COUNTIF(K76:N76,">0")=COUNT(K76:N76),COUNTIF(K76:N76,"<0")=COUNT(K76:N76)), IF(COUNTIF(K76:N76,">0")=COUNT(K76:N76),"Persistent rise – ","Persistent decline – ")& IF(ABS(N76)>1.25*SUMPRODUCT(ABS(IFERROR(K76:M76*1,0)))/COUNT(K76:M76),"accelerating", IF(ABS(N76)<0.75*SUMPRODUCT(ABS(IFERROR(K76:M76*1,0)))/COUNT(K76:M76),"decelerating","steady pace")), IF(SUMPRODUCT(--(IFERROR(K76:M76*L76:N76,0)<0))=1, IF(INDEX(K76:N76,MATCH(TRUE,INDEX(ISNUMBER(K76:N76),0),0))>0,"Reversing – peak ","Reversing – trough ")& INDEX($E$4:$I$4,MATCH(IF(INDEX(K76:N76,MATCH(TRUE,INDEX(ISNUMBER(K76:N76),0),0))>0,MAX(E76:I76),MIN(E76:I76)),E76:I76,0)), "Volatile – direction changed "&SUMPRODUCT(--(IFERROR(K76:M76*L76:N76,0)<0))&"x")))} -> Volatile – direction changed 2x
B77: MPC — operating margin | E77: =E68/E65 -> 0.34183614 | F77: =F68/F65 -> 0.22396252 | G77: =G68/G65 -> 0.23523742 | H77: =H68/H65 -> 0.25921792 | I77: =I68/I65 -> 0.26615111 | J77: =(I77-E77)*100 -> -7.5685025 | K77: =(F77-E77)*100 -> -11.787362 | L77: =(G77-F77)*100 -> 1.1274904 | M77: =(H77-G77)*100 -> 2.3980497 | N77: =(I77-H77)*100 -> 0.69331958 | O77: =IF(J77>0,"Up",IF(J77<0,"Down","Flat")) -> Down | P77: {=IF(COUNT(K77:N77)<2,"n/a", IF(OR(COUNTIF(K77:N77,">0")=COUNT(K77:N77),COUNTIF(K77:N77,"<0")=COUNT(K77:N77)), IF(COUNTIF(K77:N77,">0")=COUNT(K77:N77),"Persistent rise – ","Persistent decline – ")& IF(ABS(N77)>1.25*SUMPRODUCT(ABS(IFERROR(K77:M77*1,0)))/COUNT(K77:M77),"accelerating", IF(ABS(N77)<0.75*SUMPRODUCT(ABS(IFERROR(K77:M77*1,0)))/COUNT(K77:M77),"decelerating","steady pace")), IF(SUMPRODUCT(--(IFERROR(K77:M77*L77:N77,0)<0))=1, IF(INDEX(K77:N77,MATCH(TRUE,INDEX(ISNUMBER(K77:N77),0),0))>0,"Reversing – peak ","Reversing – trough ")& INDEX($E$4:$I$4,MATCH(IF(INDEX(K77:N77,MATCH(TRUE,INDEX(ISNUMBER(K77:N77),0),0))>0,MAX(E77:I77),MIN(E77:I77)),E77:I77,0)), "Volatile – direction changed "&SUMPRODUCT(--(IFERROR(K77:M77*L77:N77,0)<0))&"x")))} -> Reversing – trough 2023
B78: PBP — share of segment revenue | E78: ='Common Size&Ratio'!E33 -> 0.31958441 | F78: ='Common Size&Ratio'!F33 -> 0.44428662 | G78: ='Common Size&Ratio'!G33 -> 0.435783 | H78: ='Common Size&Ratio'!H33 -> 0.42882396 | I78: ='Common Size&Ratio'!I33 -> 0.42187928 | J78: =(I78-E78)*100 -> 10.229488 | K78: =(F78-E78)*100 -> 12.470222 | L78: =(G78-F78)*100 -> -0.85036265 | M78: =(H78-G78)*100 -> -0.69590425 | N78: =(I78-H78)*100 -> -0.69446705 | O78: =IF(J78>0,"Up",IF(J78<0,"Down","Flat")) -> Up | P78: {=IF(COUNT(K78:N78)<2,"n/a", IF(OR(COUNTIF(K78:N78,">0")=COUNT(K78:N78),COUNTIF(K78:N78,"<0")=COUNT(K78:N78)), IF(COUNTIF(K78:N78,">0")=COUNT(K78:N78),"Persistent rise – ","Persistent decline – ")& IF(ABS(N78)>1.25*SUMPRODUCT(ABS(IFERROR(K78:M78*1,0)))/COUNT(K78:M78),"accelerating", IF(ABS(N78)<0.75*SUMPRODUCT(ABS(IFERROR(K78:M78*1,0)))/COUNT(K78:M78),"decelerating","steady pace")), IF(SUMPRODUCT(--(IFERROR(K78:M78*L78:N78,0)<0))=1, IF(INDEX(K78:N78,MATCH(TRUE,INDEX(ISNUMBER(K78:N78),0),0))>0,"Reversing – peak ","Reversing – trough ")& INDEX($E$4:$I$4,MATCH(IF(INDEX(K78:N78,MATCH(TRUE,INDEX(ISNUMBER(K78:N78),0),0))>0,MAX(E78:I78),MIN(E78:I78)),E78:I78,0)), "Volatile – direction changed "&SUMPRODUCT(--(IFERROR(K78:M78*L78:N78,0)<0))&"x")))} -> Reversing – peak 2023
B79: Intelligent Cloud — share of segment revenue | E79: ='Common Size&Ratio'!E34 -> 0.37809553 | F79: ='Common Size&Ratio'!F34 -> 0.34421348 | G79: ='Common Size&Ratio'!G34 -> 0.35681824 | H79: ='Common Size&Ratio'!H34 -> 0.37719541 | I79: ='Common Size&Ratio'!I34 -> 0.4152345 | J79: =(I79-E79)*100 -> 3.713897 | K79: =(F79-E79)*100 -> -3.3882044 | L79: =(G79-F79)*100 -> 1.2604756 | M79: =(H79-G79)*100 -> 2.0377174 | N79: =(I79-H79)*100 -> 3.8039085 | O79: =IF(J79>0,"Up",IF(J79<0,"Down","Flat")) -> Up | P79: {=IF(COUNT(K79:N79)<2,"n/a", IF(OR(COUNTIF(K79:N79,">0")=COUNT(K79:N79),COUNTIF(K79:N79,"<0")=COUNT(K79:N79)), IF(COUNTIF(K79:N79,">0")=COUNT(K79:N79),"Persistent rise – ","Persistent decline – ")& IF(ABS(N79)>1.25*SUMPRODUCT(ABS(IFERROR(K79:M79*1,0)))/COUNT(K79:M79),"accelerating", IF(ABS(N79)<0.75*SUMPRODUCT(ABS(IFERROR(K79:M79*1,0)))/COUNT(K79:M79),"decelerating","steady pace")), IF(SUMPRODUCT(--(IFERROR(K79:M79*L79:N79,0)<0))=1, IF(INDEX(K79:N79,MATCH(TRUE,INDEX(ISNUMBER(K79:N79),0),0))>0,"Reversing – peak ","Reversing – trough ")& INDEX($E$4:$I$4,MATCH(IF(INDEX(K79:N79,MATCH(TRUE,INDEX(ISNUMBER(K79:N79),0),0))>0,MAX(E79:I79),MIN(E79:I79)),E79:I79,0)), "Volatile – direction changed "&SUMPRODUCT(--(IFERROR(K79:M79*L79:N79,0)<0))&"x")))} -> Reversing – trough 2023
B80: MPC — share of segment revenue | E80: ='Common Size&Ratio'!E35 -> 0.30232007 | F80: ='Common Size&Ratio'!F35 -> 0.21149989 | G80: ='Common Size&Ratio'!G35 -> 0.20739876 | H80: ='Common Size&Ratio'!H35 -> 0.19398063 | I80: ='Common Size&Ratio'!I35 -> 0.16288622 | J80: =(I80-E80)*100 -> -13.943385 | K80: =(F80-E80)*100 -> -9.0820175 | L80: =(G80-F80)*100 -> -0.41011291 | M80: =(H80-G80)*100 -> -1.3418131 | N80: =(I80-H80)*100 -> -3.1094415 | O80: =IF(J80>0,"Up",IF(J80<0,"Down","Flat")) -> Down | P80: {=IF(COUNT(K80:N80)<2,"n/a", IF(OR(COUNTIF(K80:N80,">0")=COUNT(K80:N80),COUNTIF(K80:N80,"<0")=COUNT(K80:N80)), IF(COUNTIF(K80:N80,">0")=COUNT(K80:N80),"Persistent rise – ","Persistent decline – ")& IF(ABS(N80)>1.25*SUMPRODUCT(ABS(IFERROR(K80:M80*1,0)))/COUNT(K80:M80),"accelerating", IF(ABS(N80)<0.75*SUMPRODUCT(ABS(IFERROR(K80:M80*1,0)))/COUNT(K80:M80),"decelerating","steady pace")), IF(SUMPRODUCT(--(IFERROR(K80:M80*L80:N80,0)<0))=1, IF(INDEX(K80:N80,MATCH(TRUE,INDEX(ISNUMBER(K80:N80),0),0))>0,"Reversing – peak ","Reversing – trough ")& INDEX($E$4:$I$4,MATCH(IF(INDEX(K80:N80,MATCH(TRUE,INDEX(ISNUMBER(K80:N80),0),0))>0,MAX(E80:I80),MIN(E80:I80)),E80:I80,0)), "Volatile – direction changed "&SUMPRODUCT(--(IFERROR(K80:M80*L80:N80,0)<0))&"x")))} -> Persistent decline – steady pace
B81: PBP — share of segment operating income | E81: ='Common Size&Ratio'!E39 -> 0.35606778 | F81: ='Common Size&Ratio'!F39 -> 0.5656609 | G81: ='Common Size&Ratio'!G39 -> 0.5451829 | H81: ='Common Size&Ratio'!H39 -> 0.54286226 | I81: ='Common Size&Ratio'!I39 -> 0.54032866 | J81: =(I81-E81)*100 -> 18.426088 | K81: =(F81-E81)*100 -> 20.959312 | L81: =(G81-F81)*100 -> -2.0478004 | M81: =(H81-G81)*100 -> -0.23206416 | N81: =(I81-H81)*100 -> -0.25335969 | O81: =IF(J81>0,"Up",IF(J81<0,"Down","Flat")) -> Up | P81: {=IF(COUNT(K81:N81)<2,"n/a", IF(OR(COUNTIF(K81:N81,">0")=COUNT(K81:N81),COUNTIF(K81:N81,"<0")=COUNT(K81:N81)), IF(COUNTIF(K81:N81,">0")=COUNT(K81:N81),"Persistent rise – ","Persistent decline – ")& IF(ABS(N81)>1.25*SUMPRODUCT(ABS(IFERROR(K81:M81*1,0)))/COUNT(K81:M81),"accelerating", IF(ABS(N81)<0.75*SUMPRODUCT(ABS(IFERROR(K81:M81*1,0)))/COUNT(K81:M81),"decelerating","steady pace")), IF(SUMPRODUCT(--(IFERROR(K81:M81*L81:N81,0)<0))=1, IF(INDEX(K81:N81,MATCH(TRUE,INDEX(ISNUMBER(K81:N81),0),0))>0,"Reversing – peak ","Reversing – trough ")& INDEX($E$4:$I$4,MATCH(IF(INDEX(K81:N81,MATCH(TRUE,INDEX(ISNUMBER(K81:N81),0),0))>0,MAX(E81:I81),MIN(E81:I81)),E81:I81,0)), "Volatile – direction changed "&SUMPRODUCT(--(IFERROR(K81:M81*L81:N81,0)<0))&"x")))} -> Reversing – peak 2023
B82: Intelligent Cloud — share of segment operating income | E82: ='Common Size&Ratio'!E40 -> 0.39819867 | F82: ='Common Size&Ratio'!F40 -> 0.32094484 | G82: ='Common Size&Ratio'!G40 -> 0.34553562 | H82: ='Common Size&Ratio'!H40 -> 0.34692052 | I82: ='Common Size&Ratio'!I40 -> 0.36700014 | J82: =(I82-E82)*100 -> -3.1198538 | K82: =(F82-E82)*100 -> -7.7253834 | L82: =(G82-F82)*100 -> 2.4590785 | M82: =(H82-G82)*100 -> 0.13848908 | N82: =(I82-H82)*100 -> 2.007962 | O82: =IF(J82>0,"Up",IF(J82<0,"Down","Flat")) -> Down | P82: {=IF(COUNT(K82:N82)<2,"n/a", IF(OR(COUNTIF(K82:N82,">0")=COUNT(K82:N82),COUNTIF(K82:N82,"<0")=COUNT(K82:N82)), IF(COUNTIF(K82:N82,">0")=COUNT(K82:N82),"Persistent rise – ","Persistent decline – ")& IF(ABS(N82)>1.25*SUMPRODUCT(ABS(IFERROR(K82:M82*1,0)))/COUNT(K82:M82),"accelerating", IF(ABS(N82)<0.75*SUMPRODUCT(ABS(IFERROR(K82:M82*1,0)))/COUNT(K82:M82),"decelerating","steady pace")), IF(SUMPRODUCT(--(IFERROR(K82:M82*L82:N82,0)<0))=1, IF(INDEX(K82:N82,MATCH(TRUE,INDEX(ISNUMBER(K82:N82),0),0))>0,"Reversing – peak ","Reversing – trough ")& INDEX($E$4:$I$4,MATCH(IF(INDEX(K82:N82,MATCH(TRUE,INDEX(ISNUMBER(K82:N82),0),0))>0,MAX(E82:I82),MIN(E82:I82)),E82:I82,0)), "Volatile – direction changed "&SUMPRODUCT(--(IFERROR(K82:M82*L82:N82,0)<0))&"x")))} -> Reversing – trough 2023
